Workbook
Name Months: [1]Admin!$A$1:$A$48
Name rawdata: 'raw data'!$1:$1048576
Name Reported: 'raw data'!$D:$D,'raw data'!$F:$F,'raw data'!$H:$H

Sheet raw data
D1: 40513 | F1: 40544 | H1: 40575 | J1: 40603 | L1: 40634 | N1: 40664 | P1: 40695 | R1: 40725 | T1: 40756 | V1: 40787 | X1: 40817 | Z1: 40848 | AB1: 40878 | AD1: 40909 | AF1: 40940 | AH1: 40969 | AJ1: 41000 | AL1: 41030 | AN1: 41061 | AP1: 41091 | AR1: 41122 | AT1: 41153 | AV1: 41183 | AX1: 41214 | AZ1: 41244 | BB1: 41275 | BD1: 41306 | BF1: 41334 | BH1: 41365 | BJ1: 41395 | BL1: 41426 | BN1: 41456 | BP1: 41487 | BR1: 41518 | BT1: 41548 | BV1: 41579 | BX1: 41609 | BZ1: 41640 | CB1: 41671 | CD1: 41699 | CF1: 41730 | CH1: 41760 | CJ1: 41791 | CL1: 41821 | CN1: 41852 | CP1: 41883 | CR1: 41913 | CT1: 41944 | CV1: 41974 | CX1: 42005 | CZ1: 42036 | DB1: 42064 | DD1: 42095 | DF1: 42125 | DH1: 42156 | DJ1: 42186 | DL1: 42217 | DN1: 42248 | DP1: 42278 | DR1: 42309 | DT1: 42339 | DV1: 42370 | DX1: 42401 | DZ1: 42430 | EB1: 42461 | ED1: 42491 | EF1: 42522 | EH1: 42552 | EJ1: 42583 | EL1: 42614 | EN1: 42644 | EP1: 42675 | ER1: 42705 | ET1: 42736 | EV1: 42767 | EX1: 42795 | EZ1: 42826 | FB1: 42856 | FD1: 42887 | FF1: 42917 | FH1: 42948 | FJ1: 42979 | FN1: 43009 | FP1: 43040 | FR1: 43070 | FT1: 43101 | FV1: 43132 | FX1: 43160 | FZ1: 43191 | GB1: 43221 | GD1: 43252 | GF1: 43282 | GH1: 43313 | GJ1: 43344 | GL1: 43374 | GN1: 43405 | GP1: 43435 | GR1: 43466 | GT1: 43497 | GV1: 43525 | GX1: 43556 | GZ1: 43586 | HB1: 43617 | HD1: 43647 | HF1: 43678 | HH1: 43709 | HJ1: 43739 | HL1: 43770 | HN1: 43800 | HP1: 43831 | HR1: 43862 | HT1: 43891 | HV1: 43922 | HX1: 43952 | HZ1: 43983 | IB1: 44013 | ID1: 44044 | IF1: 44075 | IH1: 44105 | IJ1: 44136 | IL1: 44166 | IN1: 44197 | IP1: 44228 | IR1: 44256 | IT1: 44287 | IV1: 44317 | IX1: 44348 | IZ1: 44378 | JB1: 44409 | JD1: 44440
D2: Reported | E2: Alerts | F2: Reported | G2: Alerts | H2: Reported | I2: Alerts | J2: Reported | K2: Alerts | L2: Reported | M2: Alerts | N2: Reported | O2: Alerts | P2: Reported | Q2: Alerts | R2: Reported | S2: Alerts | T2: Reported | U2: Alerts | V2: Reported | W2: Alerts | X2: Reported | Y2: Alerts | Z2: Reported | AA2: Alerts | AB2: Reported | AC2: Alerts | AD2: Reported | AE2: Alerts | AF2: Reported | AG2: Alerts | AH2: Reported | AI2: Alerts | AJ2: Reported | AK2: Alerts | AL2: Reported | AM2: Alerts | AN2: Reported | AO2: Alerts | AP2: Reported | AQ2: Alerts | AR2: Reported | AS2: Alerts | AT2: Reported | AU2: Alerts | AV2: Reported | AW2: Alerts | AX2: Reported | AY2: Alerts | AZ2: Reported | BA2: Alerts | BB2: Reported | BC2: Alerts | BD2: Reported | BE2: Alerts | BF2: Reported | BG2: Alerts | BH2: Reported | BI2: Alerts | BJ2: Reported | BK2: Alerts | BL2: Reported | BM2: Alerts | BN2: Reported | BO2: Alerts | BP2: Reported | BQ2: Alerts | BR2: Reported | BS2: Alerts | BT2: Reported | BU2: Alerts | BV2: Reported | BW2: Alerts | BX2: Reported | BY2: Alerts | BZ2: Reported | CA2: Alerts | CB2: Reported | CC2: Alerts | CD2: Reported | CE2: Alerts | CF2: Reported | CG2: Alerts | CH2: Reported | CI2: Alerts | CJ2: Reported | CK2: Alerts | CL2: Reported | CM2: Alerts | CN2: Reported | CO2: Alerts | CP2: Reported | CQ2: Alerts | CR2: Reported | CS2: Alerts | CT2: Reported | CU2: Alerts | CV2: Reported | CW2: Alerts | CX2: Reported | CY2: Alerts | CZ2: Reported | DA2: Alerts | DB2: Reported | DC2: Alerts | DD2: Reported | DE2: Alerts | DF2: Reported | DG2: Alerts | DH2: Reported | DI2: Alerts | DJ2: Reported | DK2: Alerts | DL2: Reported | DM2: Alerts | DN2: Reported | DO2: Alerts | DP2: Reported | DQ2: Alerts | DR2: Reported | DS2: Alerts | DT2: Reported | DU2: Alerts | DV2: Reported | DW2: Alerts | DX2: Reported | DY2: Alerts | DZ2: Reported | EA2: Alerts | EB2: Reported | EC2: Alerts | ED2: Reported | EE2: Alerts | EF2: Reported | EG2: Alerts | EH2: Reported | EI2: Alerts | EJ2: Reported | EK2: Alerts | EL2: Reported | EM2: Alerts | EN2: Reported | EO2: Alerts | EP2: Reported | EQ2: Alerts | ER2: Reported | ES2: Alerts | ET2: Reported | EU2: Alerts | EV2: Reported | EW2: Alerts | EX2: Reported | EY2: Alerts | EZ2: Reported | FA2: Alerts | FB2: Reported | FC2: Alerts | FD2: Reported | FE2: Alerts | FF2: Reported | FG2: Alerts | FH2: Reported | FI2: Alerts | FJ2: Reported | FK2: Take 1 Alerts | FL2: Take2 12/10/17 | FM2: Alerts | FN2: Reported | FO2: Alerts | FP2: Reported | FQ2: Alerts | FR2: Reported | FS2: Alerts | FT2: Reported | FU2: Alerts | FV2: Reported | FW2: Alerts | FX2: Reported | FY2: Alerts | FZ2: Reported | GA2: Alerts | GB2: Reported | GC2: Alerts | GD2: Reported | GE2: Alerts | GF2: Reported | GG2: Alerts | GH2: Reported | GI2: Alerts | GJ2: Reported | GK2: Alerts | GL2: Reported | GM2: Alerts | GN2: Reported | GO2: Alerts | GP2: Reported | GQ2: Alerts | GR2: Reported | GS2: Alerts | GT2: Reported | GU2: Alerts | GV2: Reported | GW2: Alerts | GX2: Reported | GY2: Alerts | GZ2: Reported | HA2: Alerts | HB2: Reported | HC2: Alerts | HD2: Reported | HE2: Alerts | HF2: Reported | HG2: Alerts | HH2: Reported | HI2: Alerts | HJ2: Reported | HK2: Alerts | HL2: Reported | HM2: Alerts | HN2: Reported | HO2: Alerts | HP2: Reported | HQ2: Alerts | HR2: Reported | HS2: Alerts | HT2: Reported | HU2: Alerts | HV2: Reported | HW2: Alerts | HX2: Reported | HY2: Alerts | HZ2: Reported | IA2: Alerts | IB2: Reported | IC2: Alerts | ID2: Reported | IE2: Alerts | IF2: Reported | IG2: Alerts | IH2: Reported | II2: Alerts | IJ2: Reported | IK2: Alerts | IL2: Reported | IM2: Alerts | IN2: Reported | IO2: Alerts | IP2: Reported | IQ2: Alerts | IR2: Reported | IS2: Alerts | IT2: Reported | IU2: Alerts | IV2: Reported | IW2: Alerts | IX2: Reported | IY2: Alerts | IZ2: Reported | JA2: Alerts | JB2: Reported | JC2: Alerts | JD2: Reported | JE2: Alerts
A3: 1.1 | B3: Flex accounts with >=2 cash credits (CR) & at least 1 withdrawal (WD) in same day (occurred at least three times last month). | C3: Flex Accounts with >2 Cash Credits per Day with withdrawal the same day | D3: 28 | E3: 56 | F3: 14 | G3: 36 | H3: 18 | I3: 50 | J3: 18 | K3: 68 | L3: 9 | M3: 55 | N3: 19 | O3: 69 | P3: 3 | Q3: 19 | R3: 27 | S3: 83 | T3: 17 | U3: 71 | V3: 19 | W3: 75 | X3: 16 | Y3: 67 | Z3: 14 | AA3: 59 | AB3: 16 | AC3: 75 | AD3: 6 | AE3: 36 | AF3: 11 | AG3: 49 | AH3: 20 | AI3: 73 | AJ3: 16 | AK3: 43 | AL3: 6 | AM3: 45 | AN3: 7 | AO3: 26 | AP3: 11 | AQ3: 39 | AR3: 18 | AS3: 40 | AT3: 11 | AU3: 30 | AV3: 10 | AW3: 42 | AX3: 6 | AY3: 33 | AZ3: 9 | BA3: 30 | BB3: 11 | BC3: 37 | BD3: 14 | BE3: 34 | BF3: 12 | BG3: 42 | BH3: 10 | BI3: 30 | BJ3: 4 | BK3: 31 | BL3: 4 | BM3: 27 | BN3: 9 | BO3: 40 | BP3: 3 | BQ3: 30 | BR3: 10 | BS3: 40 | BT3: 10 | BU3: 46 | BV3: 10 | BW3: 39 | BX3: 8 | BY3: 36 | BZ3: 11 | CA3: 53 | CB3: 14 | CC3: 77 | CD3: 16 | CE3: 48 | CF3: 4 | CG3: 12 | CH3: 17 | CI3: 49 | CJ3: 9 | CK3: 38 | CL3: 13 | CM3: 57 | CN3: 9 | CO3: 32 | CP3: 22 | CQ3: 62 | CR3: 10 | CS3: 40 | CT3: 10 | CU3: 33 | CV3: 14 | CW3: 37 | CX3: 10 | CY3: 37 | CZ3: 13 | DA3: 30 | DB3: 17 | DC3: 40 | DD3: 16 | DE3: 44 | DF3: 15 | DG3: 50 | DH3: 12 | DI3: 38 | DJ3: 17 | DK3: 50 | DL3: 13 | DM3: 45 | DN3: 24 | DO3: 49 | DP3: 25 | DQ3: 58 | DR3: 11 | DS3: 31 | DT3: 14 | DU3: 39 | DV3: 10 | DW3: 43 | DX3: 11 | DY3: 34 | DZ3: 7 | EA3: 40 | EB3: 18 | EC3: 42 | ED3: 7 | EE3: 39 | EF3: 16 | EG3: 53 | EH3: 8 | EI3: 45 | EJ3: 15 | EK3: 58 | EL3: 11 | EM3: 35 | EN3: 10 | EO3: 33 | EP3: 12 | EQ3: 41 | ER3: 19 | ES3: 44 | ET3: 11 | EU3: 36 | EV3: 9 | EW3: 34 | EX3: 17 | EY3: 58 | EZ3: 13 | FA3: 41 | FB3: 15 | FC3: 55 | FD3: 14 | FE3: 53 | FF3: 18 | FG3: 49 | FH3: 10 | FI3: 43 | FJ3: 11 | FK3: 46 | FL3: 46 | FM3: 46 | FN3: 1 | FO3: 10 | FP3: 5 | FQ3: 18 | FR3: 4 | FS3: 11 | FT3: 5 | FU3: 13 | FV3: 1 | FW3: 11 | FX3: 1 | FY3: 7 | FZ3: 1 | GA3: 5 | GB3: 1 | GC3: 3 | GD3: 1 | GE3: 6 | GF3: 2 | GG3: 15 | GH3: 4 | GI3: 10 | GJ3: 1 | GK3: 4 | GL3: 3 | GM3: 9 | GN3: 3 | GO3: 9 | GP3: 2 | GQ3: 6 | GR3: 3 | GS3: 8 | GT3: 2 | GU3: 5 | GV3: 2 | GW3: 9 | GX3: 2 | GY3: 6 | GZ3: 1 | HA3: 2 | HB3: 0 | HC3: 2 | HD3: 1 | HE3: 8 | HF3: 1 | HG3: 4 | HH3: 0 | HI3: 6 | HJ3: 2 | HK3: 6 | HL3: 1 | HM3: 8 | HN3: 1 | HO3: 4 | HP3: 4 | HQ3: 7 | HR3: 2 | HS3: 3 | HT3: 2 | HU3: 6 | HV3: 1 | HW3: 6 | HX3: 1 | HY3: 11 | HZ3: 1 | IA3: 12 | IB3: 2 | IC3: 7 | ID3: 1 | IE3: 3 | IF3: 4 | IG3: 7 | IH3: 0 | II3: 3 | IJ3: 1 | IK3: 5 | IL3: 1 | IM3: 1 | IN3: 1 | IO3: 1 | IP3: 0 | IQ3: 1 | IR3: 1 | IS3: 1 | IT3: 0 | IU3: 1 | IV3: 1 | IW3: 3 | IX3: 3 | IY3: 4 | IZ3: 0 | JA3: 2 | JB3: 2 | JC3: 4 | JD3: 3 | JE3: 6
A4: 1.2 | B4: Savings accounts with >=2 cash credits (CR) & at least 1 withdrawal (WD) in same day (occurred at least three times in month). | C4: Save Accounts with >2 Cash Credits per Day with withdrawal the same day | D4: 14 | E4: 26 | F4: 7 | G4: 20 | H4: 2 | I4: 16 | J4: 16 | K4: 48 | L4: 9 | M4: 28 | N4: 20 | O4: 41 | P4: 0 | Q4: 11 | R4: 10 | S4: 42 | T4: 6 | U4: 33 | V4: 6 | W4: 32 | X4: 4 | Y4: 23 | Z4: 6 | AA4: 30 | AB4: 8 | AC4: 25 | AD4: 4 | AE4: 13 | AF4: 2 | AG4: 15 | AH4: 2 | AI4: 13 | AJ4: 3 | AK4: 13 | AL4: 1 | AM4: 15 | AN4: 3 | AO4: 13 | AP4: 3 | AQ4: 17 | AR4: 2 | AS4: 13 | AT4: 4 | AU4: 14 | AV4: 6 | AW4: 19 | AX4: 3 | AY4: 11 | AZ4: 3 | BA4: 10 | BB4: 2 | BC4: 13 | BD4: 5 | BE4: 15 | BF4: 3 | BG4: 17 | BH4: 6 | BI4: 16 | BJ4: 2 | BK4: 16 | BL4: 2 | BM4: 27 | BN4: 2 | BO4: 26 | BP4: 2 | BQ4: 11 | BR4: 1 | BS4: 24 | BT4: 1 | BU4: 15 | BV4: 5 | BW4: 20 | BX4: 3 | BY4: 17 | BZ4: 3 | CA4: 16 | CB4: 2 | CC4: 11 | CD4: 6 | CE4: 17 | CF4: 0 | CG4: 6 | CH4: 5 | CI4: 17 | CJ4: 3 | CK4: 15 | CL4: 5 | CM4: 17 | CN4: 2 | CO4: 10 | CP4: 1 | CQ4: 14 | CR4: 2 | CS4: 13 | CT4: 4 | CU4: 17 | CV4: 6 | CW4: 23 | CX4: 2 | CY4: 18 | CZ4: 1 | DA4: 8 | DB4: 5 | DC4: 13 | DD4: 2 | DE4: 11 | DF4: 5 | DG4: 12 | DH4: 4 | DI4: 17 | DJ4: 8 | DK4: 19 | DL4: 7 | DM4: 20 | DN4: 2 | DO4: 13 | DP4: 7 | DQ4: 15 | DR4: 2 | DS4: 11 | DT4: 3 | DU4: 13 | DV4: 2 | DW4: 11 | DX4: 0 | DY4: 7 | DZ4: 1 | EA4: 18 | EB4: 3 | EC4: 15 | ED4: 6 | EE4: 15 | EF4: 2 | EG4: 11 | EH4: 2 | EI4: 11 | EJ4: 2 | EK4: 17 | EL4: 4 | EM4: 22 | EN4: 1 | EO4: 11 | EP4: 2 | EQ4: 11 | ER4: 5 | ES4: 11 | ET4: 2 | EU4: 10 | EV4: 2 | EW4: 12 | EX4: 1 | EY4: 9 | EZ4: 2 | FA4: 12 | FB4: 4 | FC4: 15 | FD4: 1 | FE4: 12 | FF4: 4 | FG4: 9 | FH4: 3 | FI4: 10 | FJ4: 1 | FK4: 8 | FL4: 8 | FM4: 8 | FN4: 0 | FO4: 2 | FP4: 0 | FQ4: 1 | FR4: 0 | FS4: 2 | FT4: 0 | FU4: 3 | FV4: 3 | FW4: 5 | FX4: 0 | FY4: 0 | FZ4: 0 | GA4: 0 | GB4: 0 | GC4: 2 | GD4: 0 | GE4: 2 | GF4: 1 | GG4: 2 | GH4: 0 | GI4: 0 | GJ4: 0 | GK4: 0 | GL4: 1 | GM4: 3 | GN4: 0 | GO4: 3 | GP4: 0 | GQ4: 0 | GR4: 0 | GS4: 0 | GT4: 0 | GU4: 1 | GV4: 0 | GW4: 0 | GX4: 0 | GY4: 0 | GZ4: 0 | HA4: 0 | HB4: 1 | HC4: 1 | HD4: 0 | HE4: 0 | HF4: 0 | HG4: 0 | HH4: 0 | HI4: 0 | HJ4: 0 | HK4: 0 | HL4: 0 | HM4: 0 | HN4: 1 | HO4: 1 | HP4: 0 | HQ4: 0 | HR4: 0 | HS4: 0 | HT4: 0 | HU4: 0 | HV4: 0 | HW4: 1 | HX4: 0 | HY4: 2 | HZ4: 0 | IA4: 0 | IB4: 0 | IC4: 1 | ID4: 1 | IE4: 2 | IF4: 0 | IG4: 2 | IH4: 0 | II4: 1 | IJ4: 0 | IK4: 0 | IL4: 0 | IM4: 1 | IN4: 0 | IO4: 0 | IP4: 0 | IQ4: 0 | IR4: 0 | IS4: 0 | IT4: 0 | IU4: 0 | IV4: 0 | IW4: 1 | IX4: 0 | IY4: 0 | IZ4: 0 | JA4: 0 | JB4: 0 | JC4: 0 | JD4: 0 | JE4: 0
A5: 1.3 | B5: Flex accounts with large number (7+) of branches used (CR, CQ, WD) and min cash credits of £1k per month. | C5: Flex Accs with >6 branches used | D5: 16 | E5: 27 | F5: 6 | G5: 9 | H5: 3 | I5: 8 | J5: 9 | K5: 28 | L5: 6 | M5: 28 | N5: 10 | O5: 27 | P5: 1 | Q5: 4 | R5: 6 | S5: 23 | T5: 15 | U5: 38 | V5: 27 | W5: 42 | X5: 10 | Y5: 29 | Z5: 10 | AA5: 37 | AB5: 7 | AC5: 27 | AD5: 4 | AE5: 9 | AF5: 8 | AG5: 13 | AH5: 18 | AI5: 38 | AJ5: 7 | AK5: 21 | AL5: 7 | AM5: 15 | AN5: 7 | AO5: 16 | AP5: 11 | AQ5: 21 | AR5: 9 | AS5: 16 | AT5: 18 | AU5: 40 | AV5: 50 | AW5: 112 | AX5: 34 | AY5: 65 | AZ5: 12 | BA5: 47 | BB5: 43 | BC5: 78 | BD5: 20 | BE5: 59 | BF5: 29 | BG5: 72 | BH5: 28 | BI5: 76 | BJ5: 20 | BK5: 66 | BL5: 21 | BM5: 65 | BN5: 33 | BO5: 97 | BP5: 22 | BQ5: 70 | BR5: 24 | BS5: 70 | BT5: 27 | BU5: 95 | BV5: 23 | BW5: 66 | BX5: 32 | BY5: 75 | BZ5: 16 | CA5: 62 | CB5: 25 | CC5: 83 | CD5: 35 | CE5: 77 | CF5: 32 | CG5: 80 | CH5: 27 | CI5: 77 | CJ5: 17 | CK5: 54 | CL5: 50 | CM5: 140 | CN5: 35 | CO5: 90 | CP5: 41 | CQ5: 100 | CR5: 32 | CS5: 92 | CT5: 44 | CU5: 102 | CV5: 42 | CW5: 91 | CX5: 46 | CY5: 83 | CZ5: 42 | DA5: 76 | DB5: 56 | DC5: 115 | DD5: 66 | DE5: 119 | DF5: 45 | DG5: 94 | DH5: 51 | DI5: 91 | DJ5: 62 | DK5: 125 | DL5: 54 | DM5: 130 | DN5: 53 | DO5: 119 | DP5: 43 | DQ5: 84 | DR5: 43 | DS5: 77 | DT5: 64 | DU5: 100 | DV5: 29 | DW5: 75 | DX5: 26 | DY5: 72 | DZ5: 29 | EA5: 76 | EB5: 60 | EC5: 109 | ED5: 36 | EE5: 80 | EF5: 40 | EG5: 101 | EH5: 37 | EI5: 91 | EJ5: 56 | EK5: 115 | EL5: 34 | EM5: 97 | EN5: 56 | EO5: 102 | EP5: 59 | EQ5: 106 | ER5: 44 | ES5: 88 | ET5: 35 | EU5: 73 | EV5: 48 | EW5: 98 | EX5: 49 | EY5: 103 | EZ5: 35 | FA5: 66 | FB5: 48 | FC5: 104 | FD5: 42 | FE5: 99 | FF5: 50 | FG5: 95 | FH5: 37 | FI5: 84 | FJ5: 42 | FK5: 90 | FL5: 90 | FM5: 90 | FN5: 37 | FO5: 106 | FP5: 12 | FQ5: 25 | FR5: 13 | FS5: 17 | FT5: 5 | FU5: 13 | FV5: 5 | FW5: 20 | FX5: 2 | FY5: 6 | FZ5: 2 | GA5: 3 | GB5: 0 | GC5: 0 | GD5: 0 | GE5: 0 | GF5: 0 | GG5: 3 | GH5: 0 | GI5: 1 | GJ5: 1 | GK5: 2 | GL5: 0 | GM5: 1 | GN5: 1 | GO5: 5 | GP5: 1 | GQ5: 2 | GR5: 0 | GS5: 1 | GT5: 0 | GU5: 0 | GV5: 1 | GW5: 2 | GX5: 0 | GY5: 2 | GZ5: 0 | HA5: 2 | HB5: 1 | HC5: 1 | HD5: 0 | HE5: 1 | HF5: 0 | HG5: 0 | HH5: 0 | HI5: 1 | HJ5: 1 | HK5: 4 | HL5: 0 | HM5: 0 | HN5: 0 | HO5: 1 | HP5: 1 | HQ5: 4 | HR5: 0 | HS5: 0 | HT5: 1 | HU5: 1 | HV5: 0 | HW5: 0 | HX5: 0 | HY5: 1 | HZ5: 0 | IA5: 0 | IB5: 0 | IC5: 0 | ID5: 0 | IE5: 0 | IF5: 0 | IG5: 0 | IH5: 0 | II5: 0 | IJ5: 0 | IK5: 0 | IL5: 0 | IM5: 0 | IN5: 0 | IO5: 0 | IP5: 0 | IQ5: 0 | IR5: 0 | IS5: 0 | IT5: 0 | IU5: 0 | IV5: 0 | IW5: 0 | IX5: 0 | IY5: 0 | IZ5: 0 | JA5: 0 | JB5: 0 | JC5: 0 | JD5: 0 | JE5: 0
A6: 1.4 | B6: Savings accounts with large number (7+) of branches used (CR, CQ, WD) and min cash credits of £1k per month. | C6: Save Accs with >6 branches used | D6: 6 | E6: 20 | F6: 3 | G6: 8 | H6: 0 | I6: 5 | J6: 5 | K6: 17 | L6: 1 | M6: 8 | N6: 6 | O6: 16 | P6: 0 | Q6: 5 | R6: 2 | S6: 13 | T6: 3 | U6: 10 | V6: 5 | W6: 15 | X6: 3 | Y6: 9 | Z6: 6 | AA6: 20 | AB6: 3 | AC6: 7 | AD6: 1 | AE6: 4 | AF6: 2 | AG6: 5 | AH6: 4 | AI6: 6 | AJ6: 4 | AK6: 10 | AL6: 2 | AM6: 7 | AN6: 1 | AO6: 4 | AP6: 2 | AQ6: 7 | AR6: 0 | AS6: 3 | AT6: 6 | AU6: 19 | AV6: 14 | AW6: 44 | AX6: 7 | AY6: 35 | AZ6: 3 | BA6: 25 | BB6: 6 | BC6: 35 | BD6: 4 | BE6: 15 | BF6: 5 | BG6: 47 | BH6: 1 | BI6: 30 | BJ6: 2 | BK6: 32 | BL6: 3 | BM6: 35 | BN6: 7 | BO6: 38 | BP6: 6 | BQ6: 29 | BR6: 5 | BS6: 35 | BT6: 7 | BU6: 40 | BV6: 5 | BW6: 33 | BX6: 9 | BY6: 37 | BZ6: 6 | CA6: 33 | CB6: 7 | CC6: 27 | CD6: 8 | CE6: 38 | CF6: 10 | CG6: 33 | CH6: 8 | CI6: 36 | CJ6: 3 | CK6: 36 | CL6: 19 | CM6: 53 | CN6: 9 | CO6: 30 | CP6: 7 | CQ6: 34 | CR6: 4 | CS6: 41 | CT6: 13 | CU6: 36 | CV6: 4 | CW6: 35 | CX6: 12 | CY6: 41 | CZ6: 12 | DA6: 33 | DB6: 14 | DC6: 46 | DD6: 5 | DE6: 28 | DF6: 10 | DG6: 38 | DH6: 11 | DI6: 38 | DJ6: 13 | DK6: 39 | DL6: 13 | DM6: 43 | DN6: 12 | DO6: 43 | DP6: 9 | DQ6: 34 | DR6: 8 | DS6: 35 | DT6: 9 | DU6: 36 | DV6: 4 | DW6: 15 | DX6: 5 | DY6: 32 | DZ6: 12 | EA6: 45 | EB6: 5 | EC6: 25 | ED6: 6 | EE6: 33 | EF6: 4 | EG6: 37 | EH6: 6 | EI6: 36 | EJ6: 9 | EK6: 48 | EL6: 9 | EM6: 35 | EN6: 3 | EO6: 31 | EP6: 5 | EQ6: 22 | ER6: 9 | ES6: 19 | ET6: 7 | EU6: 25 | EV6: 2 | EW6: 35 | EX6: 8 | EY6: 36 | EZ6: 5 | FA6: 29 | FB6: 9 | FC6: 28 | FD6: 2 | FE6: 33 | FF6: 13 | FG6: 47 | FH6: 5 | FI6: 37 | FJ6: 1 | FK6: 19 | FL6: 19 | FM6: 19 | FN6: 2 | FO6: 24 | FP6: 6 | FQ6: 22 | FR6: 4 | FS6: 21 | FT6: 1 | FU6: 32 | FV6: 2 | FW6: 17 | FX6: 3 | FY6: 20 | FZ6: 1 | GA6: 10 | GB6: 2 | GC6: 20 | GD6: 5 | GE6: 18 | GF6: 3 | GG6: 20 | GH6: 4 | GI6: 15 | GJ6: 0 | GK6: 10 | GL6: 5 | GM6: 16 | GN6: 1 | GO6: 16 | GP6: 0 | GQ6: 6 | GR6: 2 | GS6: 10 | GT6: 0 | GU6: 13 | GV6: 2 | GW6: 11 | GX6: 1 | GY6: 9 | GZ6: 1 | HA6: 9 | HB6: 2 | HC6: 13 | HD6: 3 | HE6: 16 | HF6: 1 | HG6: 15 | HH6: 0 | HI6: 4 | HJ6: 2 | HK6: 11 | HL6: 0 | HM6: 6 | HN6: 0 | HO6: 5 | HP6: 0 | HQ6: 5 | HR6: 1 | HS6: 6 | HT6: 0 | HU6: 3 | HV6: 0 | HW6: 0 | HX6: 0 | HY6: 0 | HZ6: 0 | IA6: 0 | IB6: 0 | IC6: 5 | ID6: 1 | IE6: 1 | IF6: 1 | IG6: 1 | IH6: 0 | II6: 2 | IJ6: 0 | IK6: 1 | IL6: 0 | IM6: 1 | IN6: 0 | IO6: 0 | IP6: 0 | IQ6: 2 | IR6: 1 | IS6: 1 | IT6: 0 | IU6: 1 | IV6: 1 | IW6: 3 | IX6: 0 | IY6: 0 | IZ6: 0 | JA6: 0 | JB6: 0 | JC6: 0 | JD6: 0 | JE6: 0
A7: 1.5 | B7: Flex accounts with >=5 £3k+ credits (CR,CQ) and >=4 £3k+ withdrawals (W4,WR) last month. | C7: Accounts with >=5 £3K+ Credits per Month with >=4 £3K+ withdrawal | D7: 3 | E7: 11 | F7: 3 | G7: 6 | H7: 1 | I7: 3 | J7: 3 | K7: 14 | L7: 2 | M7: 5 | N7: 1 | O7: 11 | P7: 0 | Q7: 3 | R7: 0 | S7: 9 | T7: 6 | U7: 26 | V7: 2 | W7: 14 | X7: 1 | Y7: 14 | Z7: 3 | AA7: 9 | AB7: 1 | AC7: 11 | AD7: 0 | AE7: 10 | AF7: 0 | AG7: 3 | AH7: 0 | AI7: 0 | AJ7: 0 | AK7: 0 | AL7: 0 | AM7: 0 | AN7: 0 | AO7: 0 | AP7: 0 | AQ7: 0 | AR7: 1 | AS7: 7 | AT7: 1 | AU7: 8 | AV7: 2 | AW7: 11 | AX7: 1 | AY7: 3 | AZ7: 0 | BA7: 7 | BB7: 0 | BC7: 1 | BD7: 1 | BE7: 1 | BF7: 0 | BG7: 9 | BH7: 0 | BI7: 4 | BJ7: 0 | BK7: 6 | BL7: =0+1 -> 1 | BM7: 6 | BN7: 1 | BO7: 7 | BP7: 0 | BQ7: 5 | BR7: 0 | BS7: 2 | BT7: 2 | BU7: 9 | BV7: 0 | BW7: 6 | BX7: 1 | BY7: 4 | BZ7: 0 | CA7: 4 | CB7: 4 | CC7: 8 | CD7: 1 | CE7: 3 | CF7: 0 | CG7: 4 | CH7: 0 | CI7: 5 | CJ7: 1 | CK7: 5 | CL7: 1 | CM7: 5 | CN7: 1 | CO7: 9 | CP7: 0 | CQ7: 7 | CR7: 1 | CS7: 2 | CT7: 0 | CU7: 2 | CV7: 0 | CW7: 5 | CX7: 1 | CY7: 5 | CZ7: 0 | DA7: 3 | DB7: 1 | DC7: 5 | DD7: 0 | DE7: 2 | DF7: 1 | DG7: 3 | DH7: 1 | DI7: 6 | DJ7: 0 | DK7: 5 | DL7: 2 | DM7: 7 | DN7: 0 | DO7: 2 | DP7: 1 | DQ7: 3 | DR7: 0 | DS7: 5 | DT7: 1 | DU7: 6 | DV7: 0 | DW7: 3 | DX7: 0 | DY7: 4 | DZ7: 0 | EA7: 4 | EB7: 1 | EC7: 6 | ED7: 1 | EE7: 5 | EF7: 0 | EG7: 1 | EH7: 0 | EI7: 5 | EJ7: 1 | EK7: 8 | EL7: 1 | EM7: 3 | EN7: 0 | EO7: 2 | EP7: 0 | EQ7: 3 | ER7: 0 | ES7: 3 | ET7: 1 | EU7: 4
A8: 1.6 | B8: Fixed term Bonds/ISAs closed within 6 months of opening, but after cooling-off period, and Nationwide cheque issued. | C8: Bonds closed within 6 months and Nationwide cheque issued | D8: 0 | E8: 2 | F8: 0 | G8: 4 | H8: 0 | I8: 8 | J8: 0 | K8: 3 | L8: 1 | M8: 14 | N8: 0 | O8: 57 | P8: 0 | Q8: 20 | R8: 0 | S8: 43 | T8: 0 | U8: 47 | V8: 0 | W8: 27 | X8: 0 | Y8: 33 | Z8: 0 | AA8: 2 | AB8: 0 | AC8: 5 | AD8: 0 | AE8: 2 | AF8: 0 | AG8: 6 | AH8: 0 | AI8: 12 | AJ8: 0 | AK8: 9 | AL8: 0 | AM8: 13 | AN8: 0 | AO8: 8 | AP8: 0 | AQ8: 13 | AR8: 0 | AS8: 0 | AT8: 0 | AU8: 9 | AV8: 0 | AW8: 9 | AX8: 0 | AY8: 8 | AZ8: 0 | BA8: 0 | BB8: 0 | BC8: 0 | BD8: 0 | BE8: 0 | BF8: 0 | BG8: 0 | BH8: 0 | BI8: 0 | BJ8: 0 | BK8: 0 | BL8: 0 | BM8: 0 | BN8: 0 | BO8: 0 | BP8: 0 | BQ8: 0 | BR8: 0 | BS8: 0 | BT8: 0 | BU8: 0 | BV8: 0 | BW8: 0 | BX8: 0 | BY8: 0 | BZ8: 0 | CA8: 82 | CB8: 0 | CC8: 88 | CD8: 1 | CE8: 103 | CF8: 0 | CG8: 105 | CH8: 2 | CI8: 87 | CJ8: 1 | CK8: 99 | CL8: 0 | CM8: 148 | CN8: 2 | CO8: 145 | CP8: 1 | CQ8: 162 | CR8: 0 | CS8: 163 | CT8: 1 | CU8: 136 | CV8: 1 | CW8: 125 | CX8: 3 | CY8: 192 | CZ8: 1 | DA8: 233 | DB8: 0 | DC8: 219 | DD8: 0 | DE8: 241
A9: 1.7 | B9: Child accounts with >1 credit (CR, CQ) and at least 1 debit (WA, WD, TW, W4), each £1k+, totalling at least £2k in & £2.5k out last month. | C9: Child accounts with more than £1K in and out in a month | D9: 13 | E9: 41 | F9: 6 | G9: 45 | H9: 9 | I9: 42 | J9: 8 | K9: 45 | L9: 8 | M9: 34 | N9: 7 | O9: 35 | P9: 4 | Q9: 10 | R9: 11 | S9: 40 | T9: 3 | U9: 28 | V9: 12 | W9: 50 | X9: 1 | Y9: 23 | Z9: 1 | AA9: 35 | AB9: 7 | AC9: 27 | AD9: 3 | AE9: 42 | AF9: 5 | AG9: 26 | AH9: 9 | AI9: 43 | AJ9: 8 | AK9: 50 | AL9: 3 | AM9: 27 | AN9: 4 | AO9: 23 | AP9: 3 | AQ9: 41 | AR9: 7 | AS9: 30 | AT9: 4 | AU9: 25 | AV9: 3 | AW9: 20 | AX9: 6 | AY9: 27 | AZ9: 2 | BA9: 11 | BB9: 10 | BC9: 37 | BD9: 7 | BE9: 21 | BF9: 9 | BG9: 27 | BH9: 2 | BI9: 51 | BJ9: 10 | BK9: 24 | BL9: 2 | BM9: 18 | BN9: 2 | BO9: 22 | BP9: 7 | BQ9: 29 | BR9: 5 | BS9: 24 | BT9: 4 | BU9: 31 | BV9: =10+2 -> 12 | BW9: 29 | BX9: 8 | BY9: 15 | BZ9: 13 | CA9: 27 | CB9: 8 | CC9: 18 | CD9: 2 | CE9: 23 | CF9: 7 | CG9: 42 | CH9: 9 | CI9: 31 | CJ9: 8 | CK9: 22 | CL9: 5 | CM9: 21 | CN9: 3 | CO9: 18 | CP9: 4 | CQ9: 18 | CR9: 3 | CS9: 17 | CT9: 4 | CU9: 12 | CV9: 5 | CW9: 19 | CX9: 2 | CY9: 15 | CZ9: 6 | DA9: 16 | DB9: 2 | DC9: 20 | DD9: 9 | DE9: 33 | DF9: 6 | DG9: 18 | DH9: 9 | DI9: 18 | DJ9: 0 | DK9: 12 | DL9: 8 | DM9: 21 | DN9: 5 | DO9: 23 | DP9: 4 | DQ9: 13 | DR9: 6 | DS9: 17 | DT9: 4 | DU9: 12 | DV9: 3 | DW9: 12 | DX9: 3 | DY9: 14 | DZ9: 3 | EA9: 18 | EB9: 1 | EC9: 25 | ED9: 0 | EE9: 11 | EF9: 1 | EG9: 16 | EH9: 2 | EI9: 17 | EJ9: 2 | EK9: 14 | EL9: 0 | EM9: 11 | EN9: 0 | EO9: 9 | EP9: 0 | EQ9: 5 | ER9: 3 | ES9: 13 | ET9: 5 | EU9: 16 | EV9: 0 | EW9: 6 | EX9: 3 | EY9: 14 | EZ9: 1 | FA9: 13 | FB9: 4 | FC9: 12 | FD9: 2 | FE9: 10 | FF9: 3 | FG9: 9 | FH9: 1 | FI9: 20 | FJ9: 3 | FK9: 15 | FL9: 15 | FM9: 15 | FN9: 3 | FO9: 13 | FP9: 4 | FQ9: 9 | FR9: 2 | FS9: 9 | FT9: 6 | FU9: 19 | FV9: 1 | FW9: 10 | FX9: 2 | FY9: 10 | FZ9: 0 | GA9: 19 | GB9: 0 | GC9: 11 | GD9: 2 | GE9: 10 | GF9: 0 | GG9: 5 | GH9: 1 | GI9: 10 | GJ9: 0 | GK9: 12 | GL9: 3 | GM9: 16 | GN9: 0 | GO9: 7 | GP9: 2 | GQ9: 8 | GR9: 2 | GS9: 11 | GT9: 1 | GU9: 9 | GV9: 0 | GW9: 12 | GX9: 1 | GY9: 17 | GZ9: 0 | HA9: 3 | HB9: 2 | HC9: 6 | HD9: 1 | HE9: 14 | HF9: 1 | HG9: 8 | HH9: 3 | HI9: 8 | HJ9: 2 | HK9: 6 | HL9: 0 | HM9: 6 | HN9: 0 | HO9: 7 | HP9: 0 | HQ9: 5 | HR9: 1 | HS9: 3 | HT9: 0 | HU9: 10 | HV9: 0 | HW9: 1 | HX9: 0 | HY9: 2 | HZ9: 0 | IA9: 3 | IB9: 2 | IC9: 8 | ID9: 0 | IE9: 4 | IF9: 3 | IG9: 10 | IH9: 2 | II9: 8 | IJ9: 1 | IK9: 3 | IL9: 1 | IM9: 7 | IN9: 2 | IO9: 2 | IP9: 0 | IQ9: 2 | IR9: 2 | IS9: 8 | IT9: 5 | IU9: 8 | IV9: 1 | IW9: 5 | IX9: 0 | IY9: 4 | IZ9: 2 | JA9: 4 | JB9: 0 | JC9: 4 | JD9: 3 | JE9: 8
A10: 1.11 | B10: Flex accounts of Eastern Europeans, possibly benefits paid (Child Benefit, JSA etc) and may live abroad (2 or more VW in last 3 months). | C10: Flex Accounts of Eastern Europeans, possibly benefits paid (Child Benefit, JSA etc) and may live abroad | P10: 7 | Q10: 68 | T10: 2 | U10: 11 | V10: 3 | W10: 10 | X10: 4 | Y10: 13 | Z10: 1 | AA10: 6 | AB10: 0 | AC10: 8 | AD10: 0 | AE10: 6 | AF10: 0 | AG10: 1 | AH10: 1 | AI10: 8 | AJ10: 1 | AK10: 3 | AL10: 0 | AM10: 0 | AN10: 10 | AO10: 22 | AP10: 3 | AQ10: 12 | AR10: 0 | AS10: 0 | AT10: 2 | AU10: 6 | AV10: 2 | AW10: 5 | AX10: 9 | AY10: 18 | AZ10: 0 | BA10: 0 | BB10: 0 | BC10: 1 | BD10: 0 | BE10: 1 | BF10: 2 | BG10: 3 | BH10: 0 | BI10: 4 | BJ10: 2 | BK10: 2 | BL10: 2 | BM10: 4 | BN10: 0 | BO10: 1 | BP10: 1 | BQ10: 7 | BR10: 0 | BS10: 2 | BT10: 3 | BU10: 16 | BV10: 1 | BW10: 9 | BX10: 4 | BY10: 15 | BZ10: 3 | CA10: 4 | CB10: 3 | CC10: 4 | CD10: 0 | CE10: 2 | CF10: 2 | CG10: 3 | CH10: 0 | CI10: 0 | CJ10: 0 | CK10: 0 | CL10: 0 | CM10: 0 | CN10: 9 | CO10: 11 | CP10: 5 | CQ10: 11 | CR10: 3 | CS10: 6 | CT10: 1 | CU10: 1 | CV10: 9 | CW10: 15 | CX10: 2 | CY10: 5 | CZ10: 6 | DA10: 10 | DB10: 4 | DC10: 7 | DD10: 0 | DE10: 0 | DF10: 0 | DG10: 0 | DH10: 0 | DI10: 0 | DJ10: 0 | DK10: 0 | DL10: 0 | DM10: 0 | DN10: 0 | DO10: 0 | DP10: 0 | DQ10: 0 | DR10: 10 | DS10: 17 | DT10: 6 | DU10: 14 | DV10: 4 | DW10: 8 | DX10: 1 | DY10: 5 | DZ10: 2 | EA10: 11 | EB10: 0 | EC10: 11 | ED10: 2 | EE10: 14 | EF10: 0 | EG10: 12 | EH10: 1 | EI10: 15 | EJ10: 3 | EK10: 23 | EL10: 2 | EM10: 22 | EN10: 2 | EO10: 22 | EP10: 3 | EQ10: 21 | ER10: 1 | ES10: 23 | ET10: 1 | EU10: 17
A11: 1.12 | B11: Debit cards with £2k+ monthly spend on virtual games (includes Second Life, Eve Online and Blizzard). | C11: Debit cards with large (£500+) monthly spend on virtual games | AB11: 0 | AC11: 9 | AD11: 0 | AE11: 4 | AF11: 0 | AG11: 4 | AH11: 1 | AI11: 5 | AJ11: 0 | AK11: 0 | AL11: 0 | AM11: 3 | AN11: 0 | AO11: 4 | AP11: 0 | AQ11: 4 | AR11: 0 | AS11: 5 | AT11: 1 | AU11: 4 | AV11: 0 | AW11: 3 | AX11: 1 | AY11: 4 | AZ11: 1 | BA11: 4 | BB11: 0 | BC11: 3 | BD11: 0 | BE11: 4 | BF11: 0 | BG11: 4 | BH11: 0 | BI11: 4 | BJ11: 0 | BK11: 5 | BL11: 0 | BM11: 4 | BN11: 0 | BO11: 4 | BP11: 0 | BQ11: 5 | BR11: 0 | BS11: 0 | BT11: 0 | BU11: 1 | BV11: 0 | BW11: 1 | BX11: 0 | BY11: 2 | BZ11: 0 | CA11: 5 | CB11: 0 | CC11: 2 | CD11: 0 | CE11: 1 | CF11: 0 | CG11: 2 | CH11: 0 | CI11: 1 | CJ11: 0 | CK11: 0 | CL11: 0 | CM11: 0 | CN11: 0 | CO11: 0 | CP11: 0 | CQ11: 1 | CR11: 0 | CS11: 0 | CT11: 0 | CU11: 0 | CV11: 0 | CW11: 0 | CX11: 0 | CY11: 1 | CZ11: 0 | DA11: 0 | DB11: 0 | DC11: 0 | DD11: 0 | DE11: 0 | DF11: 0 | DG11: 1 | DH11: 0 | DI11: 0 | DJ11: 0 | DK11: 0 | DL11: 0 | DM11: 0 | DN11: 0 | DO11: 0 | DP11: 0 | DQ11: 0 | DR11: 0 | DS11: 0 | DT11: 0 | DU11: 0 | DV11: 0 | DW11: 0 | DX11: 0 | DY11: 0 | DZ11: 0 | EA11: 0 | EB11: 0 | EC11: 0 | ED11: 0 | EE11: 0 | EF11: 0 | EG11: 0 | EH11: 0 | EI11: 0 | EJ11: 0 | EK11: 0 | EL11: 0 | EM11: 0 | EN11: 0 | EO11: 0 | EP11: 0 | EQ11: 0 | ER11: 0 | ES11: 0
A12: 1.13 | B12: Flex accounts receiving 5 or more £3k+ cash credits last month. | C12: Accounts with >=5 £3K+ Cash Credits per Month | AD12: 13 | AE12: 59 | AF12: 1 | AG12: 22 | AH12: 8 | AI12: 28 | AJ12: 3 | AK12: 41 | AL12: 7 | AM12: 28 | AN12: 6 | AO12: 21 | AP12: 3 | AQ12: 41 | AR12: 4 | AS12: 23 | AT12: 2 | AU12: 27 | AV12: 5 | AW12: 52 | AX12: 6 | AY12: 25 | AZ12: 3 | BA12: 30 | BB12: 2 | BC12: 27 | BD12: 3 | BE12: 15 | BF12: 6 | BG12: 23 | BH12: 4 | BI12: 42 | BJ12: 2 | BK12: 25 | BL12: =3+1 -> 4 | BM12: 16 | BN12: 6 | BO12: 47 | BP12: 2 | BQ12: 25 | BR12: 5 | BS12: 26 | BT12: 4 | BU12: 32 | BV12: 4 | BW12: 33 | BX12: 5 | BY12: 32 | BZ12: 2 | CA12: 24 | CB12: 5 | CC12: 18 | CD12: 6 | CE12: 35 | CF12: 2 | CG12: 45 | CH12: 5 | CI12: 27 | CJ12: 4 | CK12: 25 | CL12: 3 | CM12: 35 | CN12: 6 | CO12: 32 | CP12: 7 | CQ12: 47 | CR12: 4 | CS12: 19 | CT12: 9 | CU12: 28 | CV12: 10 | CW12: 45 | CX12: 2 | CY12: 16 | CZ12: 4 | DA12: 12 | DB12: 9 | DC12: 41 | DD12: 9 | DE12: 44 | DF12: 7 | DG12: 25 | DH12: 9 | DI12: 43 | DJ12: 3 | DK12: 28 | DL12: 8 | DM12: 39 | DN12: 10 | DO12: 33 | DP12: 10 | DQ12: 25 | DR12: 6 | DS12: 26 | DT12: 8 | DU12: 40 | DV12: 2 | DW12: 19 | DX12: 2 | DY12: 20 | DZ12: 1 | EA12: 19 | EB12: 17 | EC12: 40 | ED12: 7 | EE12: 44 | EF12: 1 | EG12: 31 | EH12: 1 | EI12: 19 | EJ12: 4 | EK12: 37 | EL12: 3 | EM12: 30 | EN12: 4 | EO12: 19 | EP12: 14 | EQ12: 30 | ER12: 10 | ES12: 26 | ET12: 7 | EU12: 33 | EV12: 1 | EW12: 15 | EX12: 4 | EY12: 26 | EZ12: 4 | FA12: 16 | FB12: 8 | FC12: 44 | FD12: 2 | FE12: 23 | FF12: 9 | FG12: 30 | FH12: 4 | FI12: 25 | FJ12: 7 | FK12: 23 | FL12: 23 | FM12: 23 | FN12: 6 | FO12: 30 | FP12: 6 | FQ12: 22 | FR12: 7 | FS12: 26 | FT12: 8 | FU12: 29 | FV12: 3 | FW12: 25 | FX12: 2 | FY12: 9 | FZ12: 1 | GA12: 15 | GB12: 2 | GC12: 24 | GD12: 4 | GE12: 18 | GF12: 4 | GG12: 18 | GH12: 3 | GI12: 15 | GJ12: 4 | GK12: 18 | GL12: 4 | GM12: 28 | GN12: 0 | GO12: 12 | GP12: 2 | GQ12: 15 | GR12: 3 | GS12: 18 | GT12: 3 | GU12: 11 | GV12: 1 | GW12: 12 | GX12: 5 | GY12: 26 | GZ12: 5 | HA12: 21 | HB12: 2 | HC12: 12 | HD12: 5 | HE12: 25 | HF12: 1 | HG12: 17 | HH12: 0 | HI12: 9 | HJ12: 2 | HK12: 8 | HL12: 0 | HM12: 9 | HN12: 4 | HO12: 17 | HP12: 1 | HQ12: 13 | HR12: 1 | HS12: 13 | HT12: 3 | HU12: 13 | HV12: 1 | HW12: 6 | HX12: 1 | HY12: 6 | HZ12: 1 | IA12: 10 | IB12: 4 | IC12: 13 | ID12: 2 | IE12: 5 | IF12: 0 | IG12: 18 | IH12: 0 | II12: 4 | IJ12: 2 | IK12: 9 | IL12: 1 | IM12: 10 | IN12: 2 | IO12: 6 | IP12: 2 | IQ12: 7 | IR12: 6 | IS12: 10 | IT12: 6 | IU12: 12 | IV12: 0 | IW12: 4 | IX12: 2 | IY12: 10 | IZ12: 3 | JA12: 12 | JB12: 6 | JC12: 15 | JD12: 9 | JE12: 12
A13: 1.14 | B13: Flex accounts where 5+ branches used (CR) and transactions total £2k+ last month. | C13: Flex Accs with 5<>6 branches used and total trans >£2K | AD13: 19 | AE13: 47 | AF13: 25 | AG13: 50 | AH13: 34 | AI13: 60 | AJ13: 20 | AK13: 42 | AL13: 29 | AM13: 72 | AN13: 27 | AO13: 47 | AP13: 18 | AQ13: 40 | AR13: 15 | AS13: 53 | AT13: =43+2 -> 45 | AU13: 86 | AV13: 30 | AW13: 70 | AX13: 22 | AY13: 49 | AZ13: 20 | BA13: 44 | BB13: 25 | BC13: 54 | BD13: 23 | BE13: 57 | BF13: 19 | BG13: 53 | BH13: 26 | BI13: 67 | BJ13: 9 | BK13: 40 | BL13: =24+2 -> 26 | BM13: 59 | BN13: 25 | BO13: 74 | BP13: 22 | BQ13: 68 | BR13: 19 | BS13: 62 | BT13: 30 | BU13: 79 | BV13: 22 | BW13: 49 | BX13: 24 | BY13: 58 | BZ13: 17 | CA13: 51 | CB13: 32 | CC13: 66 | CD13: 36 | CE13: 86 | CF13: 28 | CG13: 65 | CH13: 41 | CI13: 79 | CJ13: 25 | CK13: 68 | CL13: 42 | CM13: 92 | CN13: 26 | CO13: 55 | CP13: 43 | CQ13: 85 | CR13: 38 | CS13: 74 | CT13: 43 | CU13: 71 | CV13: 53 | CW13: 88 | CX13: 27 | CY13: 62 | CZ13: 36 | DA13: 66 | DB13: 43 | DC13: 77 | DD13: 51 | DE13: 88 | DF13: 47 | DG13: 92 | DH13: 42 | DI13: 86 | DJ13: 48 | DK13: 102 | DL13: 51 | DM13: 98 | DN13: 52 | DO13: 84 | DP13: 54 | DQ13: 78 | DR13: 45 | DS13: 78 | DT13: 35 | DU13: 72 | DV13: 34 | DW13: 76 | DX13: 28 | DY13: 75 | DZ13: 34 | EA13: 89 | EB13: 48 | EC13: 93 | ED13: 51 | EE13: 93 | EF13: 32 | EG13: 88 | EH13: 42 | EI13: 101 | EJ13: 47 | EK13: 88 | EL13: 47 | EM13: 108 | EN13: 36 | EO13: 83 | EP13: 61 | EQ13: 95 | ER13: 46 | ES13: 78 | ET13: 48 | EU13: 93 | EV13: 35 | EW13: 69 | EX13: 58 | EY13: 96 | EZ13: 28 | FA13: 56 | FB13: 51 | FC13: 89 | FD13: 36 | FE13: 84 | FF13: 43 | FG13: 96 | FH13: 51 | FI13: 89 | FJ13: 38 | FK13: 94 | FL13: 101 | FM13: 101 | FN13: 53 | FO13: 108 | FP13: 32 | FQ13: 78 | FR13: 32 | FS13: 61 | FT13: 57 | FU13: 112 | FV13: 35 | FW13: 82 | FX13: 13 | FY13: 28 | FZ13: 4 | GA13: 19 | GB13: 6 | GC13: 14 | GD13: 7 | GE13: 18 | GF13: 5 | GG13: 16 | GH13: 3 | GI13: 15 | GJ13: 3 | GK13: 11 | GL13: 3 | GM13: 16 | GN13: 3 | GO13: 13 | GP13: 5 | GQ13: 12 | GR13: 6 | GS13: 22 | GT13: 2 | GU13: 8 | GV13: 5 | GW13: 19 | GX13: 2 | GY13: 11 | GZ13: 2 | HA13: 10 | HB13: 3 | HC13: 14 | HD13: 2 | HE13: 16 | HF13: 5 | HG13: 16 | HH13: 5 | HI13: 14 | HJ13: 5 | HK13: 15 | HL13: 1 | HM13: 11 | HN13: 6 | HO13: 17 | HP13: 5 | HQ13: 16 | HR13: 3 | HS13: 14 | HT13: 1 | HU13: 7 | HV13: 1 | HW13: 1 | HX13: 0 | HY13: 2 | HZ13: 2 | IA13: 7 | IB13: 3 | IC13: 7 | ID13: 1 | IE13: 3 | IF13: 1 | IG13: 5 | IH13: 4 | II13: 5 | IJ13: 1 | IK13: 4 | IL13: 1 | IM13: 2 | IN13: 2 | IO13: 4 | IP13: 0 | IQ13: 0 | IR13: 0 | IS13: 1 | IT13: 1 | IU13: 3 | IV13: 2 | IW13: 4 | IX13: 5 | IY13: 9 | IZ13: 0 | JA13: 5 | JB13: 0 | JC13: 0 | JD13: 4 | JE13: 7
A14: 1.15 | B14: Savings accounts where 5+ branches used (CR) and transactions total £2k+ last month. | C14: Save Accs with 5<>6 branches used | AD14: 10 | AE14: 26 | AF14: 7 | AG14: 37 | AH14: 8 | AI14: 35 | AJ14: 13 | AK14: 41 | AL14: 16 | AM14: 40 | AN14: 13 | AO14: 33 | AP14: 13 | AQ14: 31 | AR14: 11 | AS14: 35 | AT14: 17 | AU14: 52 | AV14: 15 | AW14: 64 | AX14: 13 | AY14: 58 | AZ14: 11 | BA14: 47 | BB14: 16 | BC14: 49 | BD14: 13 | BE14: 47 | BF14: 6 | BG14: 54 | BH14: 15 | BI14: 59 | BJ14: 10 | BK14: 60 | BL14: 9 | BM14: 61 | BN14: 7 | BO14: 61 | BP14: 13 | BQ14: 70 | BR14: 10 | BS14: 42 | BT14: 5 | BU14: 54 | BV14: 4 | BW14: 43 | BX14: 13 | BY14: 48 | BZ14: 12 | CA14: 38 | CB14: 15 | CC14: 43 | CD14: 8 | CE14: 47 | CF14: 8 | CG14: 36 | CH14: 12 | CI14: 52 | CJ14: 9 | CK14: 43 | CL14: 8 | CM14: 60 | CN14: 6 | CO14: 31 | CP14: 5 | CQ14: 48 | CR14: 4 | CS14: 48 | CT14: 10 | CU14: 41 | CV14: 8 | CW14: 34 | CX14: 5 | CY14: 33 | CZ14: 9 | DA14: 39 | DB14: 13 | DC14: 56 | DD14: 14 | DE14: 53 | DF14: 12 | DG14: 35 | DH14: 12 | DI14: 38 | DJ14: 11 | DK14: 47 | DL14: 11 | DM14: 45 | DN14: 12 | DO14: 53 | DP14: 9 | DQ14: 42 | DR14: 14 | DS14: 38 | DT14: 12 | DU14: 34 | DV14: 3 | DW14: 29 | DX14: 7 | DY14: 53 | DZ14: 10 | EA14: 37 | EB14: 12 | EC14: 53 | ED14: 10 | EE14: 34 | EF14: 3 | EG14: 37 | EH14: 7 | EI14: 37 | EJ14: 8 | EK14: 54 | EL14: 8 | EM14: 34 | EN14: 3 | EO14: 29 | EP14: 6 | EQ14: 44 | ER14: 10 | ES14: 37 | ET14: 10 | EU14: 30 | EV14: 5 | EW14: 25 | EX14: 11 | EY14: 38 | EZ14: 8 | FA14: 23 | FB14: 9 | FC14: 39 | FD14: 14 | FE14: 36 | FF14: 10 | FG14: 43 | FH14: 5 | FI14: 24 | FJ14: 7 | FK14: 28 | FL14: 28 | FM14: 28 | FN14: 3 | FO14: 27 | FP14: 3 | FQ14: 8 | FR14: 1 | FS14: 2 | FT14: 2 | FU14: 4 | FV14: 1 | FW14: 4 | FX14: 3 | FY14: 3 | FZ14: 0 | GA14: 3 | GB14: 0 | GC14: 2 | GD14: 0 | GE14: 2 | GF14: 0 | GG14: 4 | GH14: 0 | GI14: 1 | GJ14: 1 | GK14: 2 | GL14: 1 | GM14: 3 | GN14: 0 | GO14: 5 | GP14: 0 | GQ14: 0 | GR14: 1 | GS14: 3 | GT14: 0 | GU14: 4 | GV14: 1 | GW14: 1 | GX14: 0 | GY14: 3 | GZ14: 0 | HA14: 1 | HB14: 0 | HC14: 2 | HD14: 3 | HE14: 3 | HF14: 1 | HG14: 5 | HH14: 0 | HI14: 2 | HJ14: 3 | HK14: 4 | HL14: 0 | HM14: 2 | HN14: 0 | HO14: 1 | HP14: 0 | HQ14: 3 | HR14: 1 | HS14: 2 | HT14: 0 | HU14: 1 | HV14: 0 | HW14: 0 | HX14: 0 | HY14: 0 | HZ14: 0 | IA14: 0 | IB14: 0 | IC14: 0 | ID14: 0 | IE14: 1 | IF14: 1 | IG14: 3 | IH14: 0 | II14: 0 | IJ14: 0 | IK14: 0 | IL14: 0 | IM14: 0 | IN14: 0 | IO14: 0 | IP14: 0 | IQ14: 2 | IR14: 0 | IS14: 0 | IT14: 0 | IU14: 0 | IV14: 0 | IW14: 0 | IX14: 0 | IY14: 0 | IZ14: 0 | JA14: 0 | JB14: 0 | JC14: 0 | JD14: 0 | JE14: 0
A15: 1.16 | B15: Flex accounts receiving £40k+ last month by at least 2 cash credits (CR). | C15: Accounts with >£40K+ Cash Credits per Month | AD15: 8 | AE15: 306 | AF15: 3 | AG15: 40 | AH15: 4 | AI15: 65 | AJ15: 3 | AK15: 55 | AL15: 2 | AM15: 43 | AN15: 1 | AO15: 49 | AP15: 1 | AQ15: 52 | AR15: 1 | AS15: 44 | AT15: 1 | AU15: 52 | AV15: 4 | AW15: 52 | AX15: 2 | AY15: 38 | AZ15: 1 | BA15: 37 | BB15: 2 | BC15: 59 | BD15: 1 | BE15: 24 | BF15: 0 | BG15: 39 | BH15: 2 | BI15: 46 | BJ15: 2 | BK15: 28 | BL15: 0 | BM15: 32 | BN15: 1 | BO15: 50 | BP15: 3 | BQ15: 33 | BR15: 4 | BS15: 41 | BT15: 1 | BU15: 33 | BV15: 0 | BW15: 1 | BX15: 0 | BY15: 41 | BZ15: 2 | CA15: 24 | CB15: 3 | CC15: 17 | CD15: 4 | CE15: 36 | CF15: 2 | CG15: 36 | CH15: 2 | CI15: 20 | CJ15: 5 | CK15: 30 | CL15: 5 | CM15: 40 | CN15: 4 | CO15: 26 | CP15: 3 | CQ15: 37 | CR15: 2 | CS15: 20 | CT15: 6 | CU15: 22 | CV15: 7 | CW15: 36 | CX15: 2 | CY15: 21 | CZ15: 2 | DA15: 10 | DB15: 10 | DC15: 30 | DD15: 2 | DE15: 33 | DF15: 4 | DG15: 24 | DH15: 6 | DI15: 24 | DJ15: 4 | DK15: 22 | DL15: 2 | DM15: 22 | DN15: 1 | DO15: 24 | DP15: 9 | DQ15: 27 | DR15: 4 | DS15: 23 | DT15: 5 | DU15: 33 | DV15: 0 | DW15: 24 | DX15: 2 | DY15: 20 | DZ15: 3 | EA15: 28 | EB15: 11 | EC15: 53 | ED15: 8 | EE15: 49 | EF15: 0 | EG15: 36 | EH15: 3 | EI15: 28 | EJ15: 2 | EK15: 27 | EL15: 1 | EM15: 20 | EN15: 1 | EO15: 18 | EP15: 3 | EQ15: 26 | ER15: 3 | ES15: 21 | ET15: 1 | EU15: 12 | EV15: 0 | EW15: 24 | EX15: 4 | EY15: 36 | EZ15: 5 | FA15: 27 | FB15: 2 | FC15: 22 | FD15: 2 | FE15: 27 | FF15: 4 | FG15: 30 | FH15: 0 | FI15: 19 | FJ15: 3 | FK15: 16 | FL15: 16 | FM15: 16 | FN15: 1 | FO15: 25 | FP15: 2 | FQ15: 10 | FR15: 0 | FS15: 11 | FT15: 4 | FU15: 23 | FV15: 4 | FW15: 10 | FX15: 1 | FY15: 10 | FZ15: 1 | GA15: 11 | GB15: 4 | GC15: 9 | GD15: 2 | GE15: 16 | GF15: 4 | GG15: 11 | GH15: 2 | GI15: 14 | GJ15: 5 | GK15: 10 | GL15: 2 | GM15: 19 | GN15: 0 | GO15: 7 | GP15: 2 | GQ15: 9 | GR15: 0 | GS15: 5 | GT15: 2 | GU15: 8 | GV15: 1 | GW15: 12 | GX15: 3 | GY15: 14 | GZ15: 2 | HA15: 16 | HB15: 0 | HC15: 4 | HD15: 3 | HE15: 21 | HF15: 0 | HG15: 12 | HH15: 0 | HI15: 5 | HJ15: 8 | HK15: 37 | HL15: 4 | HM15: 67 | HN15: 9 | HO15: 65 | HP15: 1 | HQ15: 46 | HR15: 4 | HS15: 56 | HT15: 6 | HU15: 56 | HV15: 2 | HW15: 45 | HX15: 3 | HY15: 56 | HZ15: 3 | IA15: 56 | IB15: 9 | IC15: 68 | ID15: 8 | IE15: 55 | IF15: 4 | IG15: 65 | IH15: 9 | II15: 43 | IJ15: 9 | IK15: 41 | IL15: 3 | IM15: 31 | IN15: Suspended | IO15: Suspended | IP15: Suspended | IQ15: Suspended | IR15: Suspended | IS15: Suspended | IT15: Suspended | IU15: Suspended | IV15: Suspended | IW15: Suspended | IX15: Suspended | IY15: Suspended | IZ15: Suspended | JA15: Suspended | JB15: Suspended | JC15: Suspended | JD15: Suspended | JE15: Suspended
A16: 1.17 | C16: Large No of LAs, C score Flex with CR or WP, Account Recently Opened | AP16: 2 | AQ16: 25
A17: 1.18C | C17: Large No of LAs, C score Flex (>40) | AR17: 9 | AS17: 49 | AT17: 4 | AU17: 16 | AV17: 4 | AW17: 42 | AX17: 5 | AY17: 54
A18: 1.18D | C18: Large No of LAs, D score Flex (>40) | AR18: 7 | AS18: 98 | AT18: 4 | AU18: 31 | AV18: 9 | AW18: 66 | AX18: 4 | AY18: 105
A19: 1.18 | B19: Flex accounts receiving >=30 LAs (each £100+) last month. | C19: Large No of LAs, Flex (>40) | AZ19: 9 | BA19: 82 | BB19: 18 | BC19: 120 | BD19: 8 | BE19: 130 | BF19: 12 | BG19: 133 | BH19: 13 | BI19: 135 | BJ19: 11 | BK19: 179 | BL19: =10+1 -> 11 | BM19: 116 | BN19: 22 | BO19: 200 | BP19: 6 | BQ19: 189 | BR19: 6 | BS19: 123 | BT19: 10 | BU19: 186 | BV19: 25 | BW19: 124 | BX19: 14 | BY19: 57 | BZ19: 7 | CA19: 63 | CB19: 7 | CC19: 39 | CD19: 24 | CE19: 122 | CF19: 14 | CG19: 115 | CH19: 13 | CI19: 114 | CJ19: 14 | CK19: 54 | CL19: 32 | CM19: 172 | CN19: 12 | CO19: 86 | CP19: 17 | CQ19: 106 | CR19: 24 | CS19: 97 | CT19: 30 | CU19: 116 | CV19: 43 | CW19: 156 | CX19: 20 | CY19: 117 | CZ19: 18 | DA19: 71 | DB19: 34 | DC19: 124 | DD19: 36 | DE19: 157 | DF19: 21 | DG19: 87 | DH19: 34 | DI19: 136 | DJ19: 39 | DK19: 170 | DL19: 42 | DM19: 180 | DN19: 27 | DO19: 129 | DP19: 37 | DQ19: 147 | DR19: 25 | DS19: 102 | DT19: 54 | DU19: 202 | DV19: 18 | DW19: 136 | DX19: 32 | DY19: 147 | DZ19: 28 | EA19: 187 | EB19: 49 | EC19: 199 | ED19: 27 | EE19: 135 | EF19: 27 | EG19: 183 | EH19: 29 | EI19: 158 | EJ19: 35 | EK19: 220 | EL19: 34 | EM19: 210 | EN19: 33 | EO19: 139 | EP19: 41 | EQ19: 202 | ER19: 46 | ES19: 225 | ET19: 29 | EU19: 206 | EV19: 30 | EW19: 135 | EX19: 47 | EY19: 279 | EZ19: 35 | FA19: 183 | FB19: 47 | FC19: 263 | FD19: 41 | FE19: 241 | FF19: 47 | FG19: 240 | FH19: 49 | FI19: 282 | FJ19: 38 | FK19: 227 | FL19: 236 | FM19: 236 | FN19: 50 | FO19: 254 | FP19: 55 | FQ19: 302 | FR19: 41 | FS19: 256 | FT19: 54 | FU19: 342 | FV19: 27 | FW19: 196 | FX19: 59 | FY19: 320 | FZ19: 60 | GA19: 287 | GB19: 67 | GC19: 370 | GD19: 51 | GE19: 278 | GF19: 71 | GG19: 282 | GH19: 60 | GI19: 265 | GJ19: 49 | GK19: 218 | GL19: 79 | GM19: 335 | GN19: 69 | GO19: 268 | GP19: 47 | GQ19: 230 | GR19: 61 | GS19: 286 | GT19: 47 | GU19: 199 | GV19: 93 | GW19: 318 | GX19: 84 | GY19: 340 | GZ19: 92 | HA19: 345 | HB19: 66 | HC19: 217 | HD19: 97 | HE19: 324 | HF19: 82 | HG19: 239 | HH19: 48 | HI19: 234 | HJ19: 70 | HK19: 252 | HL19: 64 | HM19: 211 | HN19: 82 | HO19: 222 | HP19: 48 | HQ19: 228 | HR19: 49 | HS19: 180 | HT19: 61 | HU19: 204 | HV19: 96 | HW19: 337 | HX19: 135 | HY19: 423 | HZ19: 130 | IA19: 413 | IB19: 179 | IC19: 484 | ID19: 141 | IE19: 357 | IF19: 122 | IG19: 395 | IH19: 176 | II19: 452 | IJ19: 222 | IK19: 453 | IL19: 220 | IM19: 487 | IN19: 193 | IO19: 413 | IP19: 169 | IQ19: 352 | IR19: 284 | IS19: 601 | IT19: 229 | IU19: 488 | IV19: 189 | IW19: 426 | IX19: 151 | IY19: 367 | IZ19: 200 | JA19: 478 | JB19: 176 | JC19: 446 | JD19: 168 | JE19: 383
A20: 1.19 | B20: Transfers via Chitoro (Zimbabwean money-transfer buisness). | C20: Transfers via Chitoro, Zimbabwe | AR20: 2 | AS20: 23 | AT20: 1 | AU20: 6 | AV20: 0 | AW20: 2 | AX20: 1 | AY20: 25 | AZ20: 0 | BA20: 1 | BB20: 0 | BC20: 1 | BD20: 4 | BE20: 8 | BF20: 0 | BG20: 4 | BH20: 1 | BI20: 5 | BJ20: 1 | BK20: 10 | BL20: 0 | BM20: 4 | BN20: 0 | BO20: 5 | BP20: 0 | BQ20: 7 | BR20: 0 | BS20: 7 | BT20: 0 | BU20: 1 | BV20: 0 | BW20: 0 | BX20: 0 | BY20: 0 | BZ20: 0 | CA20: 3 | CB20: 0 | CC20: 0 | CD20: 0 | CE20: 0 | CF20: 0 | CG20: 0 | CH20: 0 | CI20: 0 | CJ20: 0 | CK20: 0 | CL20: 0 | CM20: 0 | CN20: 0 | CO20: 0 | CP20: 0 | CQ20: 0 | CR20: 0 | CS20: 0 | CT20: 0 | CU20: 0 | CV20: 0 | CW20: 0 | CX20: 0 | CY20: 0 | CZ20: 0 | DA20: 0 | DB20: 0 | DC20: 0 | DD20: 0 | DE20: 0 | DF20: 0 | DG20: 0 | DH20: 0 | DI20: 0 | DJ20: 0 | DK20: 0 | DL20: 0 | DM20: 0 | DN20: 0 | DO20: 0 | DP20: 0 | DQ20: 0 | DR20: 0 | DS20: 0 | DT20: 0 | DU20: 0 | DV20: 0 | DW20: 0 | DX20: 0 | DY20: 0 | DZ20: 0 | EA20: 0 | EB20: 0 | EC20: 0 | ED20: 0 | EE20: 0 | EF20: 0 | EG20: 0 | EH20: 0 | EI20: 0 | EJ20: 0 | EK20: 0 | EL20: 0 | EM20: 0 | EN20: 0 | EO20: 0 | EP20: 0 | EQ20: 0 | ER20: 0 | ES20: 0
A21: 1.20 | C21: £1,000 cash or more via Drop Box | BB21: 4 | BC21: 14 | BD21: 2 | BE21: 11 | BF21: 2 | BG21: 13 | BH21: 2 | BI21: 14 | BJ21: 0 | BK21: 19 | BL21: 3 | BM21: 21 | BN21: 0 | BO21: 0 | BP21: 0 | BQ21: 2
A22: 1.21 | B22: Flex accounts with 40 or more bill payments (WPs), totalling £4.5k or more, last month. | C22: 40 or More WPs in the month | BF22: 1 | BG22: 30 | BH22: 4 | BI22: 23 | BJ22: 5 | BK22: 44 | BL22: 2 | BM22: 25 | BN22: 6 | BO22: 35 | BP22: 1 | BQ22: 44 | BR22: 4 | BS22: 32 | BT22: 4 | BU22: 49 | BV22: 4 | BW22: 34 | BX22: 4 | BY22: 20 | BZ22: 9 | CA22: 46 | CB22: 9 | CC22: 51 | CD22: 11 | CE22: 93 | CF22: 10 | CG22: 120 | CH22: 16 | CI22: 123 | CJ22: 5 | CK22: 59 | CL22: 20 | CM22: 164 | CN22: 12 | CO22: 121 | CP22: 15 | CQ22: 138 | CR22: 18 | CS22: 141 | CT22: 25 | CU22: 122 | CV22: 23 | CW22: 171 | CX22: 15 | CY22: 122 | CZ22: 11 | DA22: 70 | DB22: 24 | DC22: 126 | DD22: 25 | DE22: 178 | DF22: 22 | DG22: 163 | DH22: 28 | DI22: 118 | DJ22: 24 | DK22: 144 | DL22: 27 | DM22: 177 | DN22: 23 | DO22: 126 | DP22: 37 | DQ22: 156 | DR22: 21 | DS22: 127 | DT22: 34 | DU22: 170 | DV22: 14 | DW22: 152 | DX22: 21 | DY22: 131 | DZ22: 31 | EA22: 189 | EB22: 35 | EC22: 197 | ED22: 19 | EE22: 136 | EF22: 25 | EG22: 193 | EH22: 25 | EI22: 168 | EJ22: 29 | EK22: 216 | EL22: 35 | EM22: 205 | EN22: 27 | EO22: 151 | EP22: 36 | EQ22: 195 | ER22: 44 | ES22: 232 | ET22: 41 | EU22: 198 | EV22: 30 | EW22: 159 | EX22: 39 | EY22: 280 | EZ22: 37 | FA22: 216 | FB22: 46 | FC22: 282 | FD22: 35 | FE22: 226 | FF22: 55 | FG22: 261 | FH22: 61 | FI22: 305 | FJ22: 43 | FK22: 300 | FL22: 316 | FM22: 316 | FN22: 46 | FO22: 304 | FP22: 56 | FQ22: 316 | FR22: 40 | FS22: 269 | FT22: 72 | FU22: 342 | FV22: 23 | FW22: 245 | FX22: 70 | FY22: 395 | FZ22: 47 | GA22: 300 | GB22: 73 | GC22: 363 | GD22: 58 | GE22: 366 | GF22: 63 | GG22: 301 | GH22: 55 | GI22: 306 | GJ22: 52 | GK22: 241 | GL22: 70 | GM22: 380 | GN22: 64 | GO22: 311 | GP22: 56 | GQ22: 288 | GR22: 57 | GS22: 268 | GT22: 31 | GU22: 143 | GV22: 79 | GW22: 304 | GX22: 74 | GY22: 293 | GZ22: 80 | HA22: 282 | HB22: 60 | HC22: 231 | HD22: 90 | HE22: 277 | HF22: 103 | HG22: 260 | HH22: 74 | HI22: 239 | HJ22: 74 | HK22: 195 | HL22: 55 | HM22: 226 | HN22: 77 | HO22: 252 | HP22: 49 | HQ22: 279 | HR22: 70 | HS22: 187 | HT22: 90 | HU22: 237 | HV22: 124 | HW22: 327 | HX22: 139 | HY22: 423 | HZ22: 141 | IA22: 429 | IB22: 202 | IC22: 494 | ID22: 172 | IE22: 409 | IF22: 164 | IG22: 407 | IH22: 207 | II22: 490 | IJ22: 275 | IK22: 530 | IL22: 292 | IM22: 635 | IN22: 257 | IO22: 485 | IP22: 264 | IQ22: 509 | IR22: 389 | IS22: 773 | IT22: 294 | IU22: 666 | IV22: 283 | IW22: 566 | IX22: 268 | IY22: 522 | IZ22: 282 | JA22: 625 | JB22: 242 | JC22: 578 | JD22: 266 | JE22: 569
A23: 1.22 | B23: Multiple (4+) Chaps/Swifts received totalling £10k or more. | C23: Multiple Chaps/Swifts received totalling £10K or more | BF23: 9 | BG23: 92 | BH23: 8 | BI23: 96 | BJ23: 11 | BK23: 103 | BL23: =5+1 -> 6 | BM23: 75 | BN23: 6 | BO23: 96 | BP23: 0 | BQ23: 57 | BR23: 11 | BS23: 71 | BT23: 9 | BU23: 89 | BV23: 8 | BW23: 66 | BX23: 9 | BY23: 83 | BZ23: 3 | CA23: 91 | CB23: 9 | CC23: 67 | CD23: 10 | CE23: 100 | CF23: 16 | CG23: 100 | CH23: 8 | CI23: 99 | CJ23: 9 | CK23: 70 | CL23: 6 | CM23: 97 | CN23: 16 | CO23: 78 | CP23: 9 | CQ23: 97 | CR23: 10 | CS23: 87 | CT23: 11 | CU23: 80 | CV23: 13 | CW23: 101 | CX23: 6 | CY23: 73 | CZ23: 13 | DA23: 70 | DB23: 18 | DC23: 98 | DD23: 15 | DE23: 92 | DF23: 12 | DG23: 68 | DH23: 18 | DI23: 111 | DJ23: 15 | DK23: 99 | DL23: 11 | DM23: 70 | DN23: 12 | DO23: 94 | DP23: 13 | DQ23: 75 | DR23: 19 | DS23: 80 | DT23: 18 | DU23: 109 | DV23: 5 | DW23: 76 | DX23: 4 | DY23: 94 | DZ23: 11 | EA23: 117 | EB23: 2 | EC23: 92 | ED23: 2 | EE23: 74 | EF23: 7 | EG23: 142 | EH23: 7 | EI23: 111 | EJ23: 4 | EK23: 113 | EL23: 7 | EM23: 88 | EN23: 5 | EO23: 79 | EP23: 6 | EQ23: 87 | ER23: 8 | ES23: 126 | ET23: 14 | EU23: 116 | EV23: 15 | EW23: 106 | EX23: 11 | EY23: 143 | EZ23: 11 | FA23: 77 | FB23: 19 | FC23: 175 | FD23: 12 | FE23: 150 | FF23: 7 | FG23: 109 | FH23: 11 | FI23: 127 | FJ23: 4 | FK23: 105 | FL23: 105 | FM23: 105 | FN23: 10 | FO23: 115 | FP23: 17 | FQ23: 139 | FR23: 11 | FS23: 139 | FT23: 14 | FU23: 144 | FV23: 8 | FW23: 97 | FX23: 19 | FY23: 130 | FZ23: 19 | GA23: 138 | GB23: 15 | GC23: 158 | GD23: 13 | GE23: 117 | GF23: 13 | GG23: 86 | GH23: 14 | GI23: 82 | GJ23: 9 | GK23: 57 | GL23: 9 | GM23: 80 | GN23: 19 | GO23: 106 | GP23: 7 | GQ23: 75 | GR23: 5 | GS23: 58 | GT23: 8 | GU23: 59 | GV23: 18 | GW23: 72 | GX23: 9 | GY23: 89 | GZ23: 16 | HA23: 93 | HB23: 8 | HC23: 64 | HD23: 9 | HE23: 53 | HF23: 5 | HG23: 35 | HH23: 7 | HI23: 31 | HJ23: 7 | HK23: 29 | HL23: 8 | HM23: 42 | HN23: 8 | HO23: 31 | HP23: 9 | HQ23: 38 | HR23: 9 | HS23: 34 | HT23: 10 | HU23: 56 | HV23: 5 | HW23: 23 | HX23: 5 | HY23: 24 | HZ23: 7 | IA23: 31 | IB23: 12 | IC23: 49 | ID23: 6 | IE23: 32 | IF23: 16 | IG23: 60 | IH23: 8 | II23: 39 | IJ23: 10 | IK23: 33 | IL23: 5 | IM23: 38 | IN23: 4 | IO23: 21 | IP23: 9 | IQ23: 13 | IR23: 6 | IS23: 18 | IT23: 6 | IU23: 19 | IV23: 4 | IW23: 12 | IX23: 8 | IY23: 28 | IZ23: 1 | JA23: 19 | JB23: 7 | JC23: 27 | JD23: 6 | JE23: 31
A24: 1.23 | B24: 10 or more WPs (totalling at least £4.5k) and 2+ Chaps/Swifts (C7s), totalling at least £10k, last month. | C24: 10 or More WPs and 4+ Chaps ge £10K in the month | BL24: 0 | BM24: 1 | BN24: 2 | BO24: 11 | BP24: 0 | BQ24: 1 | BR24: 3 | BS24: 11 | BT24: 0 | BU24: 3 | BV24: 2 | BW24: 4 | BX24: 3 | BY24: 7 | BZ24: 0 | CA24: 14 | CB24: 1 | CC24: 24 | CD24: 3 | CE24: 34 | CF24: 3 | CG24: 16 | CH24: 0 | CI24: 16 | CJ24: 1 | CK24: 11 | CL24: 0 | CM24: 14 | CN24: 11 | CO24: 84 | CP24: 9 | CQ24: 103 | CR24: 10 | CS24: 111 | CT24: 3 | CU24: 70 | CV24: 12 | CW24: 142 | CX24: 9 | CY24: 93 | CZ24: 28 | DA24: 97 | DB24: 13 | DC24: 102 | DD24: 6 | DE24: 107 | DF24: 13 | DG24: 112 | DH24: 14 | DI24: 86 | DJ24: 5 | DK24: 77 | DL24: 6 | DM24: 66 | DN24: 10 | DO24: 81 | DP24: 8 | DQ24: 75 | DR24: 10 | DS24: 77 | DT24: 12 | DU24: 107 | DV24: 5 | DW24: 91 | DX24: 4 | DY24: 77 | DZ24: 8 | EA24: 114 | EB24: 9 | EC24: 89 | ED24: 2 | EE24: 83 | EF24: 4 | EG24: 103 | EH24: 4 | EI24: 97 | EJ24: 6 | EK24: 85 | EL24: 3 | EM24: 84 | EN24: 3 | EO24: 78 | EP24: 9 | EQ24: 91 | ER24: 9 | ES24: 98 | ET24: 10 | EU24: 110 | EV24: 4 | EW24: 92 | EX24: 9 | EY24: 116 | EZ24: 7 | FA24: 81 | FB24: 16 | FC24: 142 | FD24: 9 | FE24: 111 | FF24: 5 | FG24: 111 | FH24: 6 | FI24: 97 | FJ24: 0 | FK24: 87 | FL24: 87 | FM24: 87
A25: 1.24 | B25: New (2 months or less) and sole account with NW, with CQ paid in and closed. | C25: New Accounts with CQ paid in and closed | BL25: 0 | BM25: 0 | BN25: 1 | BO25: 1 | BP25: 0 | BQ25: 0 | BR25: 0 | BS25: 0 | BT25: 0 | BU25: 15 | BV25: 0 | BW25: 0 | BX25: 3 | BY25: 39 | BZ25: 0 | CA25: 53 | CB25: 0 | CC25: 56 | CD25: 3 | CE25: 84 | CF25: 2 | CG25: 75 | CH25: 3 | CI25: 63 | CJ25: 1 | CK25: 68 | CL25: 3 | CM25: 41 | CN25: 1 | CO25: 53 | CP25: 2 | CQ25: 41 | CR25: 5 | CS25: 42 | CT25: 1 | CU25: 40 | CV25: 0 | CW25: 19 | CX25: 1 | CY25: 23 | CZ25: 5 | DA25: 27 | DB25: 5 | DC25: 30 | DD25: 2 | DE25: 27 | DF25: 7 | DG25: 38 | DH25: 1 | DI25: 20 | DJ25: 7 | DK25: 47 | DL25: 2 | DM25: 24 | DN25: 2 | DO25: 38 | DP25: 1 | DQ25: 28 | DR25: 0 | DS25: 27 | DT25: 2 | DU25: 35 | DV25: 2 | DW25: 21 | DX25: 0 | DY25: 41 | DZ25: 0 | EA25: 49 | EB25: 0 | EC25: 26 | ED25: 1 | EE25: 25 | EF25: 0 | EG25: 34 | EH25: 1 | EI25: 33 | EJ25: 3 | EK25: 46 | EL25: 0 | EM25: 30 | EN25: 0 | EO25: 16 | EP25: 0 | EQ25: 15 | ER25: 0 | ES25: 13 | ET25: 1 | EU25: 21 | EV25: 0 | EW25: 27 | EX25: 0 | EY25: 27 | EZ25: 0 | FA25: 53 | FB25: 1 | FC25: 21 | FD25: 2 | FE25: 11 | FF25: 0 | FG25: 26 | FH25: 1 | FI25: 29 | FJ25: 0 | FK25: 25 | FL25: 32 | FM25: 32 | FN25: Suspended | FO25: Suspended | FP25: Suspended | FQ25: Suspended | FR25: Suspended | FS25: Suspended | FT25: Suspended | FU25: Suspended | FV25: Suspended | FW25: Suspended | FX25: Suspended | FY25: Suspended | FZ25: Suspended | GA25: Suspended | GB25: Suspended | GC25: Suspended | GD25: Suspended | GE25: Suspended | GF25: Suspended | GG25: Suspended | GH25: Suspended | GI25: Suspended | GJ25: Suspended | GK25: Suspended | GL25: Suspended | GM25: Suspended | GN25: Suspended | GO25: Suspended | GP25: Suspended | GQ25: Suspended | GR25: Suspended | GS25: Suspended | GT25: Suspended | GU25: Suspended | GV25: Suspended | GW25: Suspended | GX25: Suspended | GY25: Suspended | GZ25: Suspended | HA25: Suspended | HB25: Suspended | HC25: Suspended | HD25: Suspended | HE25: Suspended | HF25: Suspended | HG25: Suspended | HH25: Suspended | HI25: Suspended | HJ25: Suspended | HK25: Suspended | HL25: Suspended | HM25: Suspended | HN25: Suspended | HO25: Suspended | HP25: Suspended | HQ25: Suspended | HR25: Suspended | HS25: Suspended | HT25: Suspended | HU25: Suspended | HV25: Suspended | HW25: Suspended | HX25: Suspended | HY25: Suspended | HZ25: Suspended | IA25: Suspended | IB25: Suspended | IC25: Suspended | ID25: Suspended | IE25: Suspended | IF25: Suspended | IG25: Suspended | IH25: Suspended | II25: Suspended | IJ25: Suspended | IK25: Suspended | IL25: Suspended | IM25: Suspended | IN25: Suspended | IO25: Suspended | IP25: Suspended | IQ25: Suspended | IR25: Suspended | IS25: Suspended | IT25: Suspended | IU25: Suspended | IV25: Suspended | IW25: Suspended | IX25: Suspended | IY25: Suspended | IZ25: Suspended | JA25: Suspended | JB25: Suspended | JC25: Suspended | JD25: Suspended | JE25: Suspended
A26: 1.25 | B26: Debit card purchase (£300+ per transaction and £2.5k+ in total) of large amount of booze/fags - Europe over past 3 months. | C26: Debit Card Purchase of large amount of Booze/Fags -Europe | BX26: 0 | BY26: 2 | BZ26: 0 | CA26: 5 | CB26: 0 | CC26: 2 | CD26: 0 | CE26: 0 | CF26: 0 | CG26: 0 | CH26: 0 | CI26: 0 | CJ26: 3 | CK26: 5 | CL26: 0 | CM26: 5 | CN26: 0 | CO26: 3 | CP26: 1 | CQ26: 1 | CR26: 0 | CS26: 0 | CT26: 0 | CU26: 0 | CV26: 0 | CW26: 1 | CX26: 1 | CY26: 2 | CZ26: 1 | DA26: 1 | DB26: 1 | DC26: 5 | DD26: 1 | DE26: 3 | DF26: 1 | DG26: 1 | DH26: 1 | DI26: 4 | DJ26: 0 | DK26: 0 | DL26: 2 | DM26: 5 | DN26: 1 | DO26: 2 | DP26: 1 | DQ26: 2 | DR26: 2 | DS26: 4 | DT26: 2 | DU26: 2 | DV26: 2 | DW26: 4 | DX26: 1 | DY26: 1 | DZ26: 1 | EA26: 3 | EB26: 0 | EC26: 2 | ED26: 0 | EE26: 3 | EF26: 1 | EG26: 2 | EH26: 2 | EI26: 4 | EJ26: 0 | EK26: 2 | EL26: 0 | EM26: 3 | EN26: 1 | EO26: 5 | EP26: 5 | EQ26: 5 | ER26: 0 | ES26: 0 | ET26: 0 | EU26: 0 | EV26: 4 | EW26: 10 | EX26: 4 | EY26: 6 | EZ26: 2 | FA26: 2 | FB26: 1 | FC26: 2 | FD26: 2 | FE26: 2 | FF26: 2 | FG26: 4 | FH26: 1 | FI26: 2 | FJ26: 4 | FK26: 7 | FL26: 7 | FM26: 7 | FN26: 2 | FO26: 2 | FP26: 0 | FQ26: 2 | FR26: 1 | FS26: 1 | FT26: 2 | FU26: 4 | FV26: 2 | FW26: 2 | FX26: 0 | FY26: 4 | FZ26: 2 | GA26: 2 | GB26: 0 | GC26: 0 | GD26: 1 | GE26: 2 | GF26: 1 | GG26: 5 | GH26: 1 | GI26: 4 | GJ26: 0 | GK26: 2 | GL26: 3 | GM26: 4 | GN26: 1 | GO26: 4 | GP26: 5 | GQ26: 9 | GR26: 0 | GS26: 0 | GT26: 1 | GU26: 2 | GV26: 1 | GW26: 6 | GX26: 0 | GY26: 1 | GZ26: 1 | HA26: 4 | HB26: 3 | HC26: 4 | HD26: 1 | HE26: 1 | HF26: 0 | HG26: 0 | HH26: 0 | HI26: 0 | HJ26: 0 | HK26: 0 | HL26: 0 | HM26: 0 | HN26: 0 | HO26: 0 | HP26: 0 | HQ26: 0 | HR26: 0 | HS26: 0 | HT26: 0 | HU26: 0 | HV26: 0 | HW26: 0 | HX26: 0 | HY26: 0 | HZ26: 0 | IA26: 0 | IB26: 0 | IC26: 0 | ID26: 0 | IE26: 0
A27: 1.26 | B27: Treasurers Trust with high proportion (40% or greater) of cash WDs & balance of £5k+. | C27: Treasureres Trust with High proportion of cash WD | CB27: 0 | CC27: 11 | CD27: 0 | CE27: 12 | CF27: 2 | CG27: 4 | CH27: 1 | CI27: 10 | CJ27: 0 | CK27: 10 | CL27: 1 | CM27: 21 | CN27: 0 | CO27: 13 | CP27: 0 | CQ27: 9 | CR27: 1 | CS27: 13 | CT27: 1 | CU27: 25 | CV27: 2 | CW27: 24 | CX27: 0 | CY27: 8 | CZ27: 1 | DA27: 12 | DB27: 0 | DC27: 11 | DD27: 1 | DE27: 14 | DF27: 0 | DG27: 17 | DH27: 1 | DI27: 14 | DJ27: 2 | DK27: 16 | DL27: 1 | DM27: 9 | DN27: 0 | DO27: 7 | DP27: 1 | DQ27: 18 | DR27: 0 | DS27: 11 | DT27: 0 | DU27: 19 | DV27: 0 | DW27: 8 | DX27: 0 | DY27: 14 | DZ27: 0 | EA27: 11 | EB27: 1 | EC27: 8 | ED27: 1 | EE27: 7 | EF27: 0 | EG27: 20 | EH27: 0 | EI27: 10 | EJ27: 0 | EK27: 7 | EL27: 1 | EM27: 6 | EN27: 1 | EO27: 12 | EP27: 0 | EQ27: 19 | ER27: 0 | ES27: 12 | ET27: 1 | EU27: 7 | EV27: 0 | EW27: 8 | EX27: 0 | EY27: 8 | EZ27: 0 | FA27: 3 | FB27: 0 | FC27: 9 | FD27: 0 | FE27: 10 | FF27: 0 | FG27: 14 | FH27: 0 | FI27: 10 | FJ27: 0 | FK27: 5 | FL27: 7 | FM27: 7 | FN27: 0 | FO27: 11 | FP27: 0 | FQ27: 17 | FR27: 0 | FS27: 12 | FT27: 0 | FU27: 2 | FV27: 0 | FW27: 8 | FX27: 0 | FY27: 5 | FZ27: 0 | GA27: 10 | GB27: 0 | GC27: 7 | GD27: 0 | GE27: 7 | GF27: 0 | GG27: 2 | GH27: 1 | GI27: 6 | GJ27: 0 | GK27: 7 | GL27: 0 | GM27: 11 | GN27: 0 | GO27: 24 | GP27: 0 | GQ27: 6 | GR27: 0 | GS27: 4 | GT27: 0 | GU27: 4 | GV27: 0 | GW27: 11 | GX27: 0 | GY27: 5 | GZ27: 0 | HA27: 4 | HB27: 0 | HC27: 7 | HD27: 0 | HE27: 9 | HF27: 0 | HG27: 5 | HH27: 0 | HI27: 6 | HJ27: 0 | HK27: 4 | HL27: 0 | HM27: 9 | HN27: 0 | HO27: 11 | HP27: 0 | HQ27: 6 | HR27: 0 | HS27: 4 | HT27: 0 | HU27: 5 | HV27: 0 | HW27: 1 | HX27: 0 | HY27: 3 | HZ27: 0 | IA27: 2 | IB27: 0 | IC27: 4 | ID27: 0 | IE27: 3 | IF27: 0 | IG27: 4 | IH27: 0 | II27: 4 | IJ27: 0 | IK27: 6 | IL27: 0 | IM27: 6 | IN27: 0 | IO27: 3 | IP27: 0 | IQ27: 1 | IR27: 0 | IS27: 3 | IT27: 0 | IU27: 5 | IV27: 0 | IW27: 4 | IX27: 1 | IY27: 5 | IZ27: 0 | JA27: 2 | JB27: 0 | JC27: 4 | JD27: 0 | JE27: 3
A28: 1.27 | B28: Accounts with £50k+ in and out via LAs (between 10-29), WPs & VPs (WP+VP 25 plus). | C28: Accounts with 50K plus in and Out via LA, WP, VP | CH28: 10 | CI28: 66 | CJ28: 6 | CK28: 55 | CL28: 7 | CM28: 84 | CN28: 4 | CO28: 49 | CP28: 5 | CQ28: 74 | CR28: 4 | CS28: 93 | CT28: 7 | CU28: 67 | CV28: 10 | CW28: 77 | CX28: 4 | CY28: 75 | CZ28: 6 | DA28: 50 | DB28: 9 | DC28: 63 | DD28: 8 | DE28: 91 | DF28: 7 | DG28: 82 | DH28: 8 | DI28: 92 | DJ28: 20 | DK28: 114 | DL28: 9 | DM28: 104 | DN28: 11 | DO28: 106 | DP28: 12 | DQ28: 115 | DR28: 6 | DS28: 128 | DT28: 12 | DU28: 114 | DV28: 7 | DW28: 104 | DX28: 8 | DY28: 108 | DZ28: 7 | EA28: 146 | EB28: 9 | EC28: 127 | ED28: 5 | EE28: 114 | EF28: 5 | EG28: 123 | EH28: 2 | EI28: 114 | EJ28: 7 | EK28: 152 | EL28: 5 | EM28: 130 | EN28: 10 | EO28: 103 | EP28: 5 | EQ28: 144 | ER28: 8 | ES28: 132 | ET28: 10 | EU28: 153 | EV28: 11 | EW28: 127 | EX28: 8 | EY28: 208 | EZ28: 13 | FA28: 141 | FB28: 11 | FC28: 181 | FD28: 9 | FE28: 172 | FF28: 11 | FG28: 199 | FH28: 10 | FI28: 193 | FJ28: 2 | FK28: 203 | FL28: 206 | FM28: 206 | FN28: Suspended | FO28: Suspended | FP28: Suspended | FQ28: Suspended | FR28: Suspended | FS28: Suspended | FT28: Suspended | FU28: Suspended | FV28: Suspended | FW28: Suspended | FX28: Suspended | FY28: Suspended | FZ28: Suspended | GA28: Suspended | GB28: Suspended | GC28: Suspended | GD28: Suspended | GE28: Suspended | GF28: Suspended | GG28: Suspended | GH28: Suspended | GI28: Suspended | GJ28: Suspended | GK28: Suspended | GL28: Suspended | GM28: Suspended | GN28: Suspended | GO28: Suspended | GP28: Suspended | GQ28: Suspended | GR28: Suspended | GS28: Suspended | GT28: Suspended | GU28: Suspended | GV28: Suspended | GW28: Suspended | GX28: Suspended | GY28: Suspended | GZ28: Suspended | HA28: Suspended | HB28: Suspended | HC28: Suspended | HD28: Suspended | HE28: Suspended | HF28: Suspended | HG28: Suspended | HH28: Suspended | HI28: Suspended | HJ28: Suspended | HK28: Suspended | HL28: Suspended | HM28: Suspended | HN28: Suspended | HO28: Suspended | HP28: Suspended | HQ28: Suspended | HR28: Suspended | HS28: Suspended | HT28: Suspended | HU28: Suspended | HV28: Suspended | HW28: Suspended | HX28: Suspended | HY28: Suspended | HZ28: Suspended | IA28: Suspended | IB28: Suspended | IC28: Suspended | ID28: Suspended | IE28: Suspended | IF28: Suspended | IG28: Suspended | IH28: Suspended | II28: Suspended | IJ28: Suspended | IK28: Suspended | IL28: Suspended | IM28: Suspended | IN28: Suspended | IO28: Suspended | IP28: Suspended | IQ28: Suspended | IR28: Suspended | IS28: Suspended | IT28: Suspended | IU28: Suspended | IV28: Suspended | IW28: Suspended | IX28: Suspended | IY28: Suspended | IZ28: Suspended | JA28: Suspended | JB28: Suspended | JC28: Suspended | JD28: Suspended | JE28: Suspended
A29: 1.28 | B29: Treasurers Trust, Business Investor and Portfolio Investor accounts conducting Swifts. | C29: Organisation Accounts with Swifts | CV29: 0 | CW29: 11 | CX29: 0 | CY29: 6 | CZ29: 0 | DA29: 7 | DB29: 0 | DC29: 7 | DD29: 0 | DE29: 4 | DF29: 1 | DG29: 7 | DH29: 0 | DI29: 9 | DJ29: 0 | DK29: 3 | DL29: 2 | DM29: 9 | DN29: 2 | DO29: 9 | DP29: 1 | DQ29: 7 | DR29: 0 | DS29: 7 | DT29: 0 | DU29: 5 | DV29: 0 | DW29: 8 | DX29: 0 | DY29: 7 | DZ29: 0 | EA29: 5 | EB29: 0 | EC29: 8 | ED29: 0 | EE29: 12 | EF29: 0 | EG29: 6 | EH29: 0 | EI29: 6 | EJ29: 0 | EK29: 3 | EL29: 0 | EM29: 7 | EN29: 0 | EO29: 6 | EP29: 1 | EQ29: 6 | ER29: 0 | ES29: 4 | ET29: 1 | EU29: 5 | EV29: 0 | EW29: 5 | EX29: 0 | EY29: 1 | EZ29: 0 | FA29: 2 | FB29: 0 | FC29: 0 | FD29: 0 | FE29: 2 | FF29: 0 | FG29: 1 | FH29: 0 | FI29: 1 | FJ29: 0 | FK29: 1 | FL29: 1 | FM29: 1 | FN29: 0 | FO29: 2 | FP29: 0 | FQ29: 2 | FR29: 0 | FS29: 1 | FT29: 0 | FU29: 1 | FV29: 0 | FW29: 0 | FX29: 0 | FY29: 0 | FZ29: 0 | GA29: 3 | GB29: 0 | GC29: 0 | GD29: 0 | GE29: 1 | GF29: 0 | GG29: 0 | GH29: 0 | GI29: 1 | GJ29: 0 | GK29: 1 | GL29: 0 | GM29: 0 | GN29: 0 | GO29: 0 | GP29: 0 | GQ29: 1 | GR29: 0 | GS29: 1 | GT29: 0 | GU29: 0 | GV29: 0 | GW29: 0 | GX29: 0 | GY29: 0 | GZ29: 0 | HA29: 1 | HB29: 0 | HC29: 0 | HD29: 0 | HE29: 1 | HF29: 0 | HG29: 1 | HH29: 0 | HI29: 0 | HJ29: 0 | HK29: 1 | HL29: 0 | HM29: 1 | HN29: 0 | HO29: 0 | HP29: 0 | HQ29: 0 | HR29: 0 | HS29: 0 | HT29: 0 | HU29: 1 | HV29: 0 | HW29: 0 | HX29: 0 | HY29: 0 | HZ29: 0 | IA29: 0 | IB29: 0 | IC29: 0 | ID29: 0 | IE29: 1 | IF29: 0 | IG29: 0 | IH29: 0 | II29: 0 | IJ29: 0 | IK29: 0 | IL29: 0 | IM29: 0 | IN29: 0 | IO29: 0 | IP29: 0 | IQ29: 0 | IR29: 0 | IS29: 0 | IT29: 0 | IU29: 0 | IV29: 0 | IW29: 0 | IX29: 0 | IY29: 0 | IZ29: 0 | JA29: 0 | JB29: 0 | JC29: 0 | JD29: 0 | JE29: 0
A30: 1.29 | B30: Accounts with a £40k+ turnover, where 80%+ of debit value is withdrawn via WP or Cash, receiving 20+ credits (each £900+) last month. | DB30: 45 | DC30: 198 | DD30: 27 | DE30: 93 | DF30: 13 | DG30: 79 | DH30: 24 | DI30: 96 | DJ30: 37 | DK30: 142 | DL30: 25 | DM30: 152 | DN30: 22 | DO30: 105 | DP30: 20 | DQ30: 91 | DR30: 18 | DS30: 94 | DT30: 23 | DU30: 111 | DV30: 12 | DW30: 96 | DX30: 13 | DY30: 101 | DZ30: 17 | EA30: 144 | EB30: 22 | EC30: 125 | ED30: 18 | EE30: 106 | EF30: 19 | EG30: 132 | EH30: 13 | EI30: 104 | EJ30: 18 | EK30: 135 | EL30: 15 | EM30: 102 | EN30: 11 | EO30: 93 | EP30: 22 | EQ30: 136 | ER30: 17 | ES30: 119 | ET30: 15 | EU30: 113 | EV30: 16 | EW30: 93 | EX30: 19 | EY30: 164 | EZ30: 14 | FA30: 137 | FB30: 20 | FC30: 138 | FD30: 19 | FE30: 128 | FF30: 15 | FG30: 130 | FH30: 29 | FI30: 189 | FJ30: 31 | FK30: 195 | FL30: 200 | FM30: 200 | FN30: 16 | FO30: 94 | FP30: 13 | FQ30: 83 | FR30: 3 | FS30: 83 | FT30: 13 | FU30: 108 | FV30: 8 | FW30: 81 | FX30: 25 | FY30: 99 | FZ30: 14 | GA30: 89 | GB30: 25 | GC30: 107 | GD30: 13 | GE30: 87 | GF30: 13 | GG30: 82 | GH30: 11 | GI30: 110 | GJ30: 9 | GK30: 66 | GL30: 16 | GM30: 132 | GN30: 11 | GO30: 104 | GP30: 12 | GQ30: 100 | GR30: 19 | GS30: 118 | GT30: 10 | GU30: 85 | GV30: 16 | GW30: 94 | GX30: 11 | GY30: 128 | GZ30: 17 | HA30: 101 | HB30: 11 | HC30: 91 | HD30: 17 | HE30: 94 | HF30: 11 | HG30: 103 | HH30: 0 | HI30: 25 | HJ30: 0 | HK30: 27 | HL30: 3 | HM30: 40 | HN30: 1 | HO30: 32 | HP30: 4 | HQ30: 31 | HR30: 2 | HS30: 17 | HT30: 6 | HU30: 42 | HV30: 7 | HW30: 61 | HX30: 7 | HY30: 61 | HZ30: 11 | IA30: 52 | IB30: 19 | IC30: 67 | ID30: 15 | IE30: 54 | IF30: 7 | IG30: 41 | IH30: 20 | II30: 69 | IJ30: 10 | IK30: 59 | IL30: 14 | IM30: 54 | IN30: Suspended | IO30: Suspended | IP30: Suspended | IQ30: Suspended | IR30: Suspended | IS30: Suspended | IT30: Suspended | IU30: Suspended | IV30: Suspended | IW30: Suspended | IX30: Suspended | IY30: Suspended | IZ30: Suspended | JA30: Suspended | JB30: Suspended | JC30: Suspended | JD30: Suspended | JE30: Suspended
B31: Banking Total | C31: Banking Total | D31: =SUM(D3:D30) -> 80 | E31: =SUM(E3:E30) -> 183 | F31: =SUM(F3:F30) -> 39 | G31: =SUM(G3:G30) -> 128 | H31: =SUM(H3:H30) -> 33 | I31: =SUM(I3:I30) -> 132 | J31: =SUM(J3:J30) -> 59 | K31: =SUM(K3:K30) -> 223 | ... JE31: =SUM(JE3:JE30) -> 1019
A32: 28 | B32: Value of virtual currency transactions are inconsistent with customer's known income | IX32: 67 | IY32: 124 | IZ32: 37 | JA32: 72 | JB32: 26 | JC32: 77 | JD32: 20 | JE32: 69
A33: 44 | B33: Deposit values are inconsistent with customer's prior account activity | IR33: 56 | IS33: 300 | IT33: 45 | IU33: 234 | IV33: 43 | IW33: 238 | IX33: 29 | IY33: 232 | IZ33: 36 | JA33: 212 | JB33: 35 | JC33: 224 | JD33: 17 | JE33: 257
A34: 45 | B34: Non-Cash Deposit values are inconsistent with customer's known income | IR34: 49 | IS34: 94 | IT34: 52 | IU34: 122 | IV34: 46 | IW34: 89 | IX34: 42 | IY34: 93 | IZ34: 35 | JA34: 95 | JB34: 28 | JC34: 80 | JD34: 12 | JE34: 103
A35: 46 | B35: Cash Deposit values are inconsistent with customer's known income | IR35: 91 | IS35: 158 | IT35: 64 | IU35: 123 | IV35: 61 | IW35: 131 | IX35: 93 | IY35: 161 | IZ35: 54 | JA35: 135 | JB35: 56 | JC35: 146 | JD35: 40 | JE35: 164
A36: 47a | B36: Significant deviation from historical profile based on value of debit transactions | IR36: 41 | IS36: 139 | IT36: 29 | IU36: 137 | IV36: 29 | IW36: 143 | IX36: 21 | IY36: 116 | IZ36: 27 | JA36: 95 | JB36: 17 | JC36: 110 | JD36: 10 | JE36: 132
A37: 47b | B37: Significant deviation from historical profile based on volume of transactions | IR37: 24 | IS37: 86 | IT37: 20 | IU37: 83 | IV37: 20 | IW37: 76 | IX37: 15 | IY37: 61 | IZ37: 15 | JA37: 79 | JB37: 13 | JC37: 90 | JD37: 3 | JE37: 74
A38: 48 | B38: Significant Deviation from Peer-Group activity based on Total Volume and/or Value of Transaction | IV38: 126 | IW38: 311 | IX38: 63 | IY38: 299 | IZ38: 66 | JA38: 293 | JB38: 67 | JC38: 271 | JD38: 16 | JE38: 260
A39: 48b | B39: Significant Deviation from Peer-Group activity based on Total Volume and/or Value of Transaction | JB39: 1 | JC39: 14 | JD39: 0 | JE39: 13
A40: 49 | B40: Significant Deviation from Peer-Group activity based on Total Volume of Distinct Counter Part | IV40: 188 | IW40: 331 | IX40: 123 | IY40: 368 | IZ40: 107 | JA40: 332 | JB40: 108 | JC40: 305 | JD40: 47 | JE40: 300
A41: 49b | B41: Significant Deviation from Peer-Group activity based on Total Volume of Distinct Counter Part | JB41: 6 | JC41: 16 | JD41: 1 | JE41: 15
A42: 51 | B42: Significant Deviation from Peer-Group activity based on Volume/Value of High-Risk Transaction | IV42: 136 | IW42: 259 | IX42: 98 | IY42: 245 | IZ42: 127 | JA42: 320 | JB42: 112 | JC42: 295 | JD42: 58 | JE42: 280
A43: 51b | B43: Significant Deviation from Peer-Group activity based on Volume/Value of High-Risk Transaction | JB43: 2 | JC43: 15 | JD43: 0 | JE43: 14
B44: Banking New Total | C44: Banking New Total | IR44: =SUM(IR33:IR37) -> 261 | IS44: =SUM(IS33:IS37) -> 777 | IT44: =SUM(IT33:IT37) -> 210 | IU44: =SUM(IU33:IU37) -> 699 | IV44: =SUM(IV33:IV42) -> 649 | IW44: =SUM(IW33:IW42) -> 1578 | IX44: =SUM(IX32:IX42) -> 551 | IY44: =SUM(IY32:IY42) -> 1699 | IZ44: =SUM(IZ32:IZ42) -> 504 | JA44: =SUM(JA32:JA42) -> 1633 | JB44: =SUM(JB32:JB43) -> 471 | JC44: =SUM(JC32:JC43) -> 1643 | JD44: =SUM(JD32:JD43) -> 224 | JE44: =SUM(JE32:JE43) -> 1681
A45: 3.1 | B45: Accounts, 24+ months old, redeemed whilst in arrears for 12+ months with a £5k+ payment. | C45: Redeemed while in Arrears | D45: 0 | E45: 1 | F45: 0 | G45: 0 | H45: 0 | I45: 0 | J45: 0 | K45: 1 | L45: 0 | M45: 2 | N45: 0 | O45: 0 | P45: 0 | Q45: 0 | R45: 0 | S45: 0 | T45: 0 | U45: 0 | V45: 0 | W45: 0 | X45: 0 | Y45: 2 | Z45: 0 | AA45: 0 | AB45: 0 | AC45: 0 | AD45: 0 | AE45: 0 | AF45: 0 | AG45: 0 | AH45: 0 | AI45: 0 | AJ45: 0 | AK45: 1 | AL45: 0 | AM45: 0 | AN45: 0 | AO45: 0 | AP45: 0 | AQ45: 0 | AR45: 0 | AS45: 0 | AT45: 0 | AU45: 0 | AV45: 0 | AW45: 0 | AX45: 0 | AY45: 0 | AZ45: 0 | BA45: 0 | BB45: 0 | BC45: 0 | BD45: 0 | BE45: 1 | BF45: 0 | BG45: 0 | BJ45: 0 | BK45: 0 | BL45: 0 | BM45: 0 | BN45: 0 | BO45: 0 | BP45: 0 | BQ45: 2 | BR45: 0 | BS45: 2 | BT45: 0 | BU45: 0 | BV45: 0 | BW45: 3 | BX45: 0 | BY45: 2 | BZ45: 0 | CA45: 1 | CB45: 0 | CC45: 0 | CD45: 0 | CE45: 0 | CF45: 0 | CG45: 0 | CH45: 0 | CI45: 2 | CJ45: 0 | CK45: 0 | CL45: 1 | CM45: 3 | CN45: 0 | CO45: 0 | CP45: 0 | CQ45: 0 | CR45: 0 | CS45: 0 | CT45: 0 | CU45: 0 | CV45: 0 | CW45: 0 | CX45: 0 | CY45: 0 | CZ45: 0 | DA45: 0 | DB45: 0 | DC45: 0 | DD45: 0 | DE45: 0 | DF45: 0 | DG45: 0 | DH45: 0 | DI45: 0 | DJ45: 0 | DK45: 0 | DL45: 0 | DM45: 0 | DN45: 0 | DO45: 0 | DP45: 0 | DQ45: 0 | DR45: 0 | DS45: 0 | DT45: 0 | DU45: 0 | DV45: 0 | DW45: 0 | DX45: 0 | DY45: 0 | DZ45: 0 | EA45: 0 | EB45: 0 | EC45: 0 | ED45: 0 | EE45: 0 | EF45: 0 | EG45: 0 | EH45: 0 | EI45: 1 | EJ45: 0 | EK45: 0 | EL45: 0 | EM45: 0 | EN45: 0 | EO45: 0 | EP45: 0 | EQ45: 0 | ER45: 0 | ES45: 0 | ET45: 0 | EU45: 0
A46: 3.2 | B46: Accounts (with at least six excepted payments) receiving overpayments totalling at least £10k, for 3+ months in the past 6 months. | C46: Accounts with Overpayments (at least 6*expected) for 3 consecutive Months | D46: 4 | E46: 32 | F46: 4 | G46: 39 | H46: 1 | I46: 37 | J46: 3 | K46: 45 | L46: 1 | M46: 38 | N46: 2 | O46: 49 | P46: 1 | Q46: 15 | R46: 1 | S46: 40 | T46: 1 | U46: 42 | V46: 2 | W46: 43 | X46: 0 | Y46: 48 | Z46: 0 | AA46: 53 | AB46: 0 | AC46: 19 | AD46: 0 | AE46: 13 | AF46: 1 | AG46: 7 | AH46: 0 | AI46: 5 | AJ46: 0 | AK46: 11 | AL46: 0 | AM46: 3 | AN46: 1 | AO46: 9 | AP46: 0 | AQ46: 10 | AR46: 0 | AS46: 9 | AT46: 0 | AU46: 10 | AV46: 2 | AW46: 12 | AX46: 0 | AY46: 8 | AZ46: 0 | BA46: 6 | BB46: 0 | BC46: 5 | BD46: 0 | BE46: 6 | BF46: 0 | BG46: 8 | BJ46: 1 | BK46: 43 | BL46: 1 | BM46: 30 | BN46: 0 | BO46: 21 | BP46: 0 | BQ46: 22 | BR46: 1 | BS46: 16 | BT46: 0 | BU46: 16 | BV46: 1 | BW46: 16 | BX46: 0 | BY46: 15 | BZ46: 2 | CA46: 18 | CB46: 1 | CC46: 21 | CD46: 0 | CE46: 16 | CF46: 0 | CG46: 22 | CH46: 1 | CI46: 23 | CJ46: 0 | CK46: 17 | CL46: 0 | CM46: 22 | CN46: 0 | CO46: 15 | CP46: 1 | CQ46: 14 | CR46: 0 | CS46: 14 | CT46: 0 | CU46: 8 | CV46: 1 | CW46: 13 | CX46: 0 | CY46: 13 | CZ46: 2 | DA46: 22 | DB46: 2 | DC46: 6 | DD46: 0 | DE46: 16 | DF46: 1 | DG46: 13 | DH46: 1 | DI46: 14 | DJ46: 1 | DK46: 9 | DL46: 0 | DM46: 8 | DN46: 1 | DO46: 11 | DP46: 1 | DQ46: 13 | DR46: 0 | DS46: 15 | DT46: 0 | DU46: 16 | DV46: 1 | DW46: 10 | DX46: 1 | DY46: 15 | DZ46: 1 | EA46: 13 | EB46: 1 | EC46: 12 | ED46: 1 | EE46: 13 | EF46: 0 | EG46: 14 | EH46: 1 | EI46: 13 | EJ46: 1 | EK46: 21 | EL46: 0 | EM46: 14 | EN46: 2 | EO46: 22 | EP46: 1 | EQ46: 20 | ER46: 0 | ES46: 15 | ET46: 0 | EU46: 21 | EV46: 1 | EW46: 6 | EX46: 0 | EY46: 15 | EZ46: 1 | FA46: 15
A47: 3.3 | B47: Mortgages (customer < 55 years old) with variable overpayments over the past 3 months: 1st month overpay >=£2k, next month no overpay, 3rd month overpay >=£1k. | C47: Mortgages with variable overpayments | L47: 2 | M47: 80 | N47: 1 | O47: 54 | P47: 0 | Q47: 25 | R47: 0 | S47: 0 | T47: 0 | U47: 52 | V47: 1 | W47: 53 | X47: 0 | Y47: 66 | Z47: 3 | AA47: 76 | AB47: 0 | AC47: 37 | AD47: 0 | AE47: 33 | AF47: 1 | AG47: 23 | AH47: 1 | AI47: 31 | AJ47: 0 | AK47: 22 | AL47: 1 | AM47: 27 | AN47: 0 | AO47: 30 | AP47: 1 | AQ47: 24 | AR47: 0 | AS47: 21 | AT47: 0 | AU47: 23 | AW47: 23 | AX47: 0 | AY47: 26 | AZ47: 2 | BA47: 18 | BB47: 1 | BC47: 19 | BD47: 0 | BE47: 22 | BF47: 0 | BG47: 21 | BJ47: 0 | BK47: 31 | BL47: 1 | BM47: 27 | BN47: 0 | BO47: 23 | BP47: 0 | BQ47: 19 | BR47: 0 | BS47: 27 | BT47: 2 | BU47: 27 | BV47: 0 | BW47: 20 | BX47: 0 | BY47: 18 | BZ47: 0 | CA47: 14 | CB47: 0 | CC47: 24 | CD47: 0 | CE47: 22 | CF47: 0 | CG47: 12 | CH47: 2 | CI47: 28 | CJ47: 2 | CK47: 22 | CL47: 1 | CM47: 20 | CN47: 1 | CO47: 23 | CP47: 0 | CQ47: 18 | CR47: 3 | CS47: 24 | CT47: 2 | CU47: 24 | CV47: 0 | CW47: 10 | CX47: 1 | CY47: 16 | CZ47: 3 | DA47: 33 | DB47: 4 | DC47: 53 | DD47: 2 | DE47: 43 | DF47: 2 | DG47: 49 | DH47: 4 | DI47: 44 | DJ47: 4 | DK47: 41 | DL47: 3 | DM47: 56 | DN47: 3 | DO47: 42 | DP47: 2 | DQ47: 45 | DR47: 0 | DS47: 34 | DT47: 0 | DU47: 34 | DV47: 3 | DW47: 36 | DX47: 0 | DY47: 48 | DZ47: 3 | EA47: 46 | EB47: 2 | EC47: 40 | ED47: 0 | EE47: 30 | EF47: 1 | EG47: 55 | EH47: 1 | EI47: 32 | EJ47: 3 | EK47: 48 | EL47: 0 | EM47: 45 | EN47: 0 | EO47: 36 | EP47: 1 | EQ47: 39 | ER47: 0 | ES47: 39 | ET47: 3 | EU47: 41 | EV47: 2 | EW47: 25 | EX47: 1 | EY47: 47 | EZ47: 0 | FA47: 39
A48: 3.4 | B48: Overpayments totalling £501+ each month, for past 6 months, on mortgages <12 months old. | C48: Overpayments of £500 for 6 months | N48: 0 | O48: 59 | P48: 0 | Q48: 10 | R48: 0 | S48: 0 | T48: 0 | U48: 30 | V48: 0 | W48: 51 | X48: 0 | Y48: 52 | Z48: 1 | AA48: 52 | AB48: 0 | AC48: 36 | AD48: 0 | AE48: 34 | AF48: 0 | AG48: 47 | AH48: 1 | AI48: 61 | AJ48: 0 | AK48: 79 | AL48: 0 | AM48: 28 | AN48: 0 | AO48: 43 | AP48: 0 | AQ48: 58 | AR48: 0 | AS48: 6 | AT48: 0 | AU48: 5 | AV48: 0 | AW48: 3 | AX48: 0 | AY48: 1 | AZ48: 0 | BA48: 3 | BB48: 0 | BC48: 5 | BD48: 0 | BE48: 3 | BF48: 0 | BG48: 4 | BJ48: 0 | BK48: 6 | BL48: 0 | BM48: 5 | BN48: 0 | BO48: 2 | BP48: 0 | BQ48: 3 | BR48: 0 | BS48: 1 | BT48: 0 | BU48: 2 | BV48: 0 | BW48: 2 | BX48: 0 | BY48: 2 | BZ48: 0 | CA48: 5 | CB48: 0 | CC48: 5 | CD48: 0 | CE48: 15 | CF48: 0 | CG48: 15 | CH48: 0 | CI48: 14 | CJ48: 1 | CK48: 24 | CL48: 0 | CM48: 20 | CN48: 0 | CO48: 19 | CP48: 0 | CQ48: 27 | CR48: 0 | CS48: 20 | CT48: 0 | CU48: 23 | CV48: 0 | CW48: 15 | CX48: 0 | CY48: 19 | CZ48: 1 | DA48: 51 | DB48: 0 | DC48: 21 | DD48: 0 | DE48: 38 | DF48: 0 | DG48: 19 | DH48: 0 | DI48: 35 | DJ48: 1 | DK48: 41 | DL48: 0 | DM48: 35 | DN48: 1 | DO48: 30 | DP48: 0 | DQ48: 38 | DR48: 0 | DS48: 35 | DT48: 0 | DU48: 45 | DV48: 0 | DW48: 38 | DX48: 1 | DY48: 39 | DZ48: 0 | EA48: 39 | EB48: 0 | EC48: 31 | ED48: 0 | EE48: 33 | EF48: 0 | EG48: 33 | EH48: 0 | EI48: 35 | EJ48: 0 | EK48: 20 | EL48: 0 | EM48: 26 | EN48: 0 | EO48: 36
A49: 3.5 | B49: Mortages with one or more drawdowns and one or more repayments, each totalling £5k+, in past 6 months. | C49: 3 drawdowns greater than 5K and an overpayment | D49: 0 | E49: 0 | F49: 0 | G49: 2 | H49: 0 | I49: 1 | J49: 0 | K49: 3 | L49: 0 | M49: 1 | N49: 0 | O49: 2 | P49: 0 | Q49: 0 | R49: 0 | S49: 0 | T49: 0 | U49: 2 | V49: 0 | W49: 2 | X49: 0 | Y49: 2 | Z49: 0 | AA49: 0 | AB49: 0 | AC49: 0 | AD49: 0 | AE49: 0 | AF49: 0 | AG49: 0 | AH49: 0 | AI49: 0 | AJ49: 0 | AK49: 0 | AL49: 0 | AM49: 0 | AN49: 0 | AO49: 0 | AP49: 0 | AQ49: 0 | AR49: 0 | AS49: 0 | AT49: 0 | AU49: 0 | AV49: 0 | AW49: 0 | AX49: 0 | AY49: 0 | AZ49: 0 | BA49: 0 | BB49: 0 | BC49: 0 | BD49: 0 | BE49: 0 | BF49: 0 | BG49: 0 | BJ49: 0 | BK49: 0 | BL49: 0 | BM49: 0 | BN49: 0 | BO49: 0 | BP49: 0 | BQ49: 0 | BR49: 0 | BS49: 0 | BT49: 0 | BU49: 0 | BV49: 0 | BW49: 0 | BX49: 0 | BY49: 0 | BZ49: 0 | CA49: 0 | CB49: 0 | CC49: 0 | CD49: 0 | CE49: 0 | CF49: 0 | CG49: 0 | CH49: 0 | CI49: 0 | CJ49: 0 | CK49: 0 | CL49: 0 | CM49: 0 | CN49: 0 | CO49: 0 | CP49: 0 | CQ49: 0 | CR49: 0 | CS49: 0 | CT49: 0 | CU49: 0 | CV49: 0 | CW49: 0 | CX49: 0 | CY49: 0 | CZ49: 0 | DA49: 0 | DB49: 0 | DC49: 0 | DD49: 0 | DE49: 0 | DF49: 0 | DG49: 0 | DH49: 0 | DI49: 0 | DJ49: 0 | DK49: 0 | DL49: 0 | DM49: 0 | DN49: 0 | DO49: 0 | DP49: 0 | DQ49: 0 | DR49: 0 | DS49: 0 | DT49: 0 | DU49: 0 | DV49: 0 | DW49: 0 | DX49: 0 | DY49: 0 | DZ49: 0 | EA49: 0 | EB49: 0 | EC49: 0 | ED49: 0 | EE49: 0 | EF49: 0 | EG49: 0 | EH49: 0 | EI49: 0 | EJ49: 0 | EK49: 0 | EL49: 0 | EM49: 0 | EN49: 0 | EO49: 0 | EP49: 0 | EQ49: 0 | ER49: 0 | ES49: 0 | ET49: 0 | EU49: 0
A50: 3.6 | B50: Mortgage redeemed with a large overpayment - subsequent cheque refund for £5k+. | C50: Mort redeemed by cheque | D50: 1 | E50: 15 | F50: 0 | G50: 15 | H50: 0 | I50: 13 | J50: 0 | K50: 6 | L50: 0 | M50: 12 | N50: 0 | O50: 12 | P50: 0 | Q50: 2 | R50: 0 | S50: 0 | T50: 0 | U50: 14 | V50: 0 | W50: 14 | X50: 0 | Y50: 12 | Z50: 0 | AA50: 0 | AB50: 0 | AC50: 0 | AD50: 0 | AE50: 0 | AF50: 0 | AG50: 0 | AH50: 0 | AI50: 1 | AJ50: 0 | AK50: 0 | AL50: 0 | AM50: 0 | AN50: 0 | AO50: 0 | AP50: 0 | AQ50: 0 | AR50: 0 | AS50: 0 | AT50: 0 | AU50: 0 | AV50: 0 | AW50: 0 | AX50: 0 | AY50: 0 | AZ50: 0 | BA50: 0 | BB50: 0 | BC50: 0 | BD50: 0 | BE50: 2 | BF50: 0 | BG50: 0 | BJ50: 0 | BK50: 0 | BL50: 0 | BM50: 1 | BN50: 0 | BO50: 0 | BP50: 0 | BQ50: 1 | BR50: 0 | BS50: 1 | BT50: 0 | BU50: 1 | BV50: 0 | BW50: 1 | BX50: 0 | BY50: 0 | BZ50: 0 | CA50: 3 | CB50: 0 | CC50: 0 | CD50: 0 | CE50: 0 | CF50: 0 | CG50: 2 | CH50: 0 | CI50: 2 | CJ50: 0 | CK50: 0 | CL50: 0 | CM50: 0 | CN50: 0 | CO50: 0 | CP50: 0 | CQ50: 1 | CR50: 0 | CS50: 0 | CT50: 0 | CU50: 0 | CV50: 0 | CW50: 0 | CX50: 0 | CY50: 2 | CZ50: 0 | DA50: 0 | DB50: 0 | DC50: 1 | DD50: 0 | DE50: 0 | DF50: 0 | DG50: 0 | DH50: 0 | DI50: 3 | DJ50: 0 | DK50: 0 | DL50: 0 | DM50: 1 | DN50: 0 | DO50: 2 | DP50: 0 | DQ50: 0 | DR50: 0 | DS50: 1 | DT50: 0 | DU50: 1 | DV50: 0 | DW50: 0 | DX50: 0 | DY50: 0 | DZ50: 0 | EA50: 0 | EB50: 0 | EC50: 1 | ED50: 0 | EE50: 0 | EF50: 0 | EG50: 0 | EH50: 0 | EI50: 1 | EJ50: 0 | EK50: 0 | EL50: 0 | EM50: 0 | EN50: 0 | EO50: 0 | EP50: 0 | EQ50: 0 | ER50: 0 | ES50: 1 | ET50: 0 | EU50: 0 | EV50: Suspended | EW50: Suspended | EX50: Suspended | EY50: Suspended | EZ50: Suspended | FA50: Suspended
A51: 3.7 | B51: Accounts redeemed within 12 months of inception (customer <55 years old). | C51: Redeemed less than 12 months old | D51: 0 | E51: 78 | F51: 0 | G51: 51 | H51: 1 | I51: 46 | J51: 0 | K51: 59 | L51: 0 | M51: 62 | N51: 0 | O51: 50 | P51: 0 | Q51: 13 | R51: 0 | S51: 0 | T51: 0 | U51: 71 | V51: 0 | W51: 62 | X51: 0 | Y51: 68 | Z51: 0 | AA51: 1 | AB51: 0 | AC51: 2 | AD51: 0 | AE51: 4 | AF51: 0 | AG51: 0 | AH51: 1 | AI51: 5 | AJ51: 0 | AK51: 3 | AL51: 0 | AM51: 2 | AN51: 0 | AO51: 3 | AP51: 0 | AQ51: 1 | AR51: 0 | AS51: 3 | AT51: 0 | AU51: 7 | AV51: 0 | AW51: 3 | AX51: 0 | AY51: 3 | BA51: 1 | BC51: 3 | BD51: 0 | BE51: 1 | BF51: 0 | BG51: 4 | BJ51: 0 | BK51: 5 | BL51: 0 | BM51: 3 | BN51: 0 | BO51: 0 | BP51: 0 | BQ51: 6 | BR51: 0 | BS51: 4 | BT51: 0 | BU51: 3 | BV51: 0 | BW51: 4 | BX51: 0 | BY51: 6 | BZ51: 0 | CA51: 2 | CB51: 0 | CC51: 5 | CD51: 0 | CE51: 6 | CF51: 0 | CG51: 3 | CH51: 0 | CI51: 6 | CJ51: 0 | CK51: 1 | CL51: 0 | CM51: 2 | CN51: 0 | CO51: 2 | CP51: 0 | CQ51: 6 | CR51: 0 | CS51: 4 | CT51: 0 | CU51: 5 | CV51: 0 | CW51: 1 | CX51: 0 | CY51: 0 | CZ51: 0 | DA51: 3 | DB51: 0 | DC51: 5 | DD51: 0 | DE51: 4 | DF51: 0 | DG51: 6 | DH51: 0 | DI51: 0 | DJ51: 0 | DK51: 7 | DL51: 0 | DM51: 2 | DN51: 1 | DO51: 5 | DP51: 0 | DQ51: 8 | DR51: 0 | DS51: 5 | DT51: 0 | DU51: 10 | DV51: 0 | DW51: 4 | DX51: 0 | DY51: 7 | DZ51: 0 | EA51: 9 | EB51: 0 | EC51: 4 | ED51: 0 | EE51: 3 | EF51: 0 | EG51: 7 | EH51: 0 | EI51: 3 | EJ51: 0 | EK51: 2 | EL51: 0 | EM51: 4 | EN51: 0 | EO51: 5 | EP51: 0 | EQ51: 5 | ER51: 1 | ES51: 8 | ET51: 0 | EU51: 3 | EV51: Suspended | EW51: Suspended | EX51: Suspended | EY51: Suspended | EZ51: Suspended | FA51: Suspended
A52: 3.8 | C52: New Accounts (<=5months) with 2-3 missed payments | J52: 0 | K52: 5 | L52: 0 | M52: 4 | N52: 0 | O52: 2 | P52: 0 | Q52: 0 | R52: 0 | S52: 0
A53: 3.9 | B53: An overpayment incurring an early redemption fee on a mortgage <= 12 months old. | C53: Overpayment (non HO) and fee incurred, less than 12 months old | AH53: 1 | AI53: 56 | AJ53: 0 | AK53: 72 | AL53: 0 | AM53: 21 | AN53: 1 | AO53: 22 | AP53: 0 | AQ53: 93 | AR53: 0 | AS53: 28 | AT53: 0 | AU53: 21 | AV53: 0 | AW53: 0 | AX53: 0 | AY53: 0 | AZ53: 0 | BA53: 0 | BB53: 0 | BC53: 0 | BD53: 0 | BE53: 0 | BF53: 0 | BG53: 0 | BJ53: 0 | BK53: 0 | BL53: 0 | BM53: 0 | BN53: 0 | BO53: 0 | BP53: 0 | BQ53: 0 | BR53: 0 | BS53: 0 | BT53: 0 | BU53: 0 | BV53: 0 | BW53: 0 | BX53: 0 | BY53: 0 | BZ53: 0 | CA53: 0 | CB53: 0 | CC53: 0 | CD53: 0 | CE53: 0 | CF53: 0 | CG53: 0 | CH53: 0 | CI53: 0 | CJ53: 0 | CK53: 0 | CL53: 0 | CM53: 0 | CN53: 0 | CO53: 0 | CP53: 0 | CQ53: 0 | CR53: 0 | CS53: 0 | CT53: 0 | CU53: 0 | CV53: 0 | CW53: 0 | CX53: 0 | CY53: 0 | CZ53: 0 | DA53: 0 | DB53: 0 | DC53: 0 | DD53: 0 | DE53: 0 | DF53: 0 | DG53: 0 | DH53: 0 | DI53: 0 | DJ53: 0 | DK53: 0 | DL53: 0 | DM53: 0 | DN53: 0 | DO53: 0 | DP53: 0 | DQ53: 0 | DR53: 0 | DS53: 0 | DT53: 0 | DU53: 0 | DV53: 0 | DW53: 0 | DX53: 0 | DY53: 0 | DZ53: 0 | EA53: 0 | EB53: 0 | EC53: 0 | ED53: 0 | EE53: 0 | EF53: 0 | EG53: 0 | EH53: 0 | EI53: 0 | EJ53: 0 | EK53: 0 | EL53: 0 | EM53: 0 | EN53: 0 | EO53: 0 | EP53: 0 | EQ53: 0 | ER53: 0 | ES53: 0 | ET53: 0 | EU53: 0 | EV53: Suspended | EW53: Suspended | EX53: Suspended | EY53: Suspended | EZ53: Suspended | FA53: Suspended
A54: 3.10 | B54: Mortgage accounts receiving 6 or more electronic payments last month. | C54: 6 or more electronic payments in a month | BJ54: 0 | BK54: 1 | BL54: 1 | BM54: 5 | BN54: 0 | BO54: 4 | BP54: 0 | BQ54: 1 | BR54: 0 | BS54: 0 | BT54: 0 | BU54: 2 | BV54: 0 | BW54: 2 | BX54: 0 | BY54: 0 | BZ54: 0 | CA54: 0 | CB54: 0 | CC54: 2 | CD54: 0 | CE54: 2 | CF54: 0 | CG54: 0 | CH54: 0 | CI54: 3 | CJ54: 0 | CK54: 2 | CL54: 0 | CM54: 2 | CN54: 0 | CO54: 0 | CP54: 0 | CQ54: 3 | CR54: 0 | CS54: 2 | CT54: 0 | CU54: 1 | CV54: 0 | CW54: 0 | CX54: 0 | CY54: 2 | CZ54: 0 | DA54: 4 | DB54: 1 | DC54: 2 | DD54: 0 | DE54: 1 | DF54: 0 | DG54: 0 | DH54: 0 | DI54: 4 | DJ54: 0 | DK54: 6 | DL54: 0 | DM54: 0 | DN54: 0 | DO54: 2 | DP54: 0 | DQ54: 2 | DR54: 0 | DS54: 3 | DT54: 0 | DU54: 2 | DV54: 0 | DW54: 1 | DX54: 0 | DY54: 3 | DZ54: 0 | EA54: 2 | EB54: 0 | EC54: 4 | ED54: 0 | EE54: 0 | EF54: 0 | EG54: 1 | EH54: 0 | EI54: 1 | EJ54: 0 | EK54: 3 | EL54: 0 | EM54: 1 | EN54: 0 | EO54: 1 | EP54: 0 | EQ54: 0 | ER54: 0 | ES54: 0 | ET54: 0 | EU54: 0
A55: 3.11 | B55: Accounts receiving 2 or more chaps payments (one at least £1k) last month. | C55: 2 or more chaps payments in a month | BJ55: 0 | BK55: 20 | BL55: 0 | BM55: 28 | BN55: 1 | BO55: 23 | BP55: 0 | BQ55: 20 | BR55: 0 | BS55: 17 | BT55: 2 | BU55: 26 | BV55: 1 | BW55: 13 | BX55: 0 | BY55: 19 | BZ55: 0 | CA55: 22 | CB55: 0 | CC55: 13 | CD55: 0 | CE55: 17 | CF55: 0 | CG55: 12 | CH55: 0 | CI55: 16 | CJ55: 0 | CK55: 13 | CL55: 0 | CM55: 8 | CN55: 0 | CO55: 7 | CP55: 0 | CQ55: 10 | CR55: 0 | CS55: 14 | CT55: 0 | CU55: 23 | CV55: 0 | CW55: 8 | CX55: 0 | CY55: 9 | CZ55: 0 | DA55: 15 | DB55: 1 | DC55: 14 | DD55: 0 | DE55: 2 | DF55: 0 | DG55: 8 | DH55: 0 | DI55: 19 | DJ55: 0 | DK55: 7 | DL55: 0 | DM55: 13 | DN55: 0 | DO55: 10 | DP55: 0 | DQ55: 14 | DR55: 0 | DS55: 4 | DT55: 1 | DU55: 19 | DV55: 0 | DW55: 7 | DX55: 0 | DY55: 9 | DZ55: 0 | EA55: 12 | EB55: 0 | EC55: 10 | ED55: 0 | EE55: 6 | EF55: 0 | EG55: 8 | EH55: 0 | EI55: 9 | EJ55: 0 | EK55: 5 | EL55: 0 | EM55: 2 | EN55: 0 | EO55: 3 | EP55: 0 | EQ55: 5 | ER55: 0 | ES55: 4
A56: 3.12 | B56: Mortgage redeemed within 12 months of inception | FP56: 0 | FQ56: 21 | FR56: 0 | FS56: 3 | FT56: 0 | FU56: 4 | FV56: 0 | FW56: 6 | FX56: 0 | FY56: 2 | FZ56: 0 | GA56: 2 | GB56: 0 | GC56: 4 | GD56: 0 | GE56: 7 | GF56: 0 | GG56: 7 | GH56: 0 | GI56: 4 | GJ56: 0 | GK56: 3 | GL56: 0 | GM56: 3 | GN56: 0 | GO56: 5 | GP56: 0 | GQ56: 4 | GR56: 0 | GS56: 1 | GT56: 1 | GU56: 2 | GV56: 0 | GW56: 3 | GX56: 1 | GY56: 4 | GZ56: 0 | HA56: 4 | HB56: 0 | HC56: 4 | HD56: 0 | HE56: 8 | HF56: 0 | HG56: 3 | HH56: 0 | HI56: 5 | HJ56: 0 | HK56: 3 | HL56: 0 | HM56: 4 | HN56: 0 | HO56: 2 | HP56: 0 | HQ56: 3 | HR56: 0 | HS56: 2 | HT56: 0 | HU56: 4 | HV56: 0 | HW56: 1 | HX56: 0 | HY56: 3 | HZ56: 0 | IA56: 1 | IB56: 0 | IC56: 1 | ID56: 0 | IE56: 2 | IF56: 0 | IG56: 3 | IH56: 0 | II56: 3 | IJ56: 0 | IK56: 10 | IL56: 0 | IM56: 2 | IN56: 0 | IO56: 1 | IP56: 0 | IQ56: 3 | IR56: 0 | IS56: 7 | IT56: 0 | IU56: 4 | IV56: 0 | IW56: 0 | IX56: 0 | IY56: 10 | IZ56: 0 | JA56: 6 | JB56: 0 | JC56: 6 | JD56: 0 | JE56: 9
A57: 3.13 | B57: Prime Mortgage with a one off overpayment more than 10% (which is not then redeemed in the same month) | FP57: 2 | FQ57: 11 | FR57: 7 | FS57: 39 | FT57: 9 | FU57: 50 | FV57: 3 | FW57: 43 | FX57: 3 | FY57: 44 | FZ57: 5 | GA57: 53 | GB57: 5 | GC57: 58 | GD57: 7 | GE57: 86 | GF57: 6 | GG57: 70 | GH57: 6 | GI57: 80 | GJ57: 9 | GK57: 87 | GL57: 8 | GM57: 84 | GN57: 6 | GO57: 73 | GP57: 3 | GQ57: 68 | GR57: 4 | GS57: 72 | GT57: 6 | GU57: 57 | GV57: 10 | GW57: 54 | GX57: 4 | GY57: 56 | GZ57: 3 | HA57: 41 | HB57: 5 | HC57: 49 | HD57: 3 | HE57: 60 | HF57: 1 | HG57: 47 | HH57: 3 | HI57: 49 | HJ57: 5 | HK57: 50 | HL57: 4 | HM57: 54 | HN57: 2 | HO57: 44 | HP57: 3 | HQ57: 68 | HR57: 12 | HS57: 65 | HT57: 4 | HU57: 45 | HV57: 2 | HW57: 23 | HX57: 4 | HY57: 37 | HZ57: 6 | IA57: 42 | IB57: 4 | IC57: 58 | ID57: 9 | IE57: 48 | IF57: 8 | IG57: 55 | IH57: 3 | II57: 46 | IJ57: 11 | IK57: 54 | IL57: 5 | IM57: 49 | IN57: 4 | IO57: 57 | IP57: 3 | IQ57: 39 | IR57: 4 | IS57: 48 | IT57: 10 | IU57: 46 | IV57: 7 | IW57: 48 | IX57: 6 | IY57: 44 | IZ57: 13 | JA57: 41 | JB57: 14 | JC57: 53 | JD57: 10 | JE57: 55
B58: Mortgage Total | C58: Mortgage Total | D58: =SUM(D45:D57) -> 5 | E58: =SUM(E45:E57) -> 126 | F58: =SUM(F45:F57) -> 4 | G58: =SUM(G45:G57) -> 107 | H58: =SUM(H45:H57) -> 2 | I58: =SUM(I45:I57) -> 97 | J58: =SUM(J45:J57) -> 3 | K58: =SUM(K45:K57) -> 119 | ... JE58: =SUM(JE45:JE57) -> 64
A59: 2.1 | B59: Loans repaid early and within 12 months and Loan Amount >=£10k | C59: Loans over £3000 repaid early and within 12 months | D59: 0 | E59: 0 | F59: 0 | G59: 0 | H59: 0 | I59: 5 | J59: 0 | K59: 51 | L59: 0 | M59: 27 | N59: 0 | O59: 71 | P59: 0 | Q59: 28 | R59: 0 | S59: 10 | T59: 0 | U59: 89 | V59: 0 | W59: 168 | X59: 1 | Y59: 166 | AB59: 0 | AC59: 8 | AD59: 1 | AE59: 1 | AF59: 0 | AG59: 5 | AH59: 0 | AI59: 1 | AJ59: 0 | AK59: 3 | AL59: 0 | AM59: 5 | AN59: 0 | AO59: 3 | AP59: 0 | AQ59: 1 | AR59: 0 | AS59: 10 | AT59: 0 | AU59: 2 | AV59: 0 | AW59: 6 | AX59: 1 | AY59: 7 | AZ59: 0 | BA59: 2 | BB59: 0 | BC59: 2 | BD59: 0 | BE59: 6 | BF59: 0 | BG59: 1 | BH59: 0 | BI59: 5 | BJ59: 0 | BK59: 0 | BL59: 0 | BM59: 3 | BN59: 0 | BO59: 1 | BP59: 0 | BQ59: 0 | BR59: 0 | BS59: 0 | BT59: 0 | BU59: 7 | BV59: 0 | BW59: 4 | BX59: 0 | BY59: 0 | BZ59: 0 | CA59: 2 | CB59: 0 | CC59: 0 | CD59: 0 | CE59: 1 | CF59: 0 | CG59: 0 | CH59: 0 | CI59: 0 | CJ59: 0 | CK59: 0 | CL59: 0 | CM59: 0 | CN59: 0 | CO59: 0 | CP59: 0 | CQ59: 0 | CR59: 0 | CS59: 2 | CT59: 0 | CU59: 0 | CV59: 0 | CW59: 0 | CX59: 0 | CY59: 0 | CZ59: 0 | DA59: 9 | DB59: 0 | DC59: 6 | DD59: 0 | DE59: 0 | DF59: 0 | DG59: 0 | DH59: 0 | DI59: 0 | DJ59: 0 | DK59: 0 | DL59: 0 | DM59: 1 | DN59: 0 | DO59: 4 | DP59: 0 | DQ59: 2 | DR59: 0 | DS59: 0 | DT59: 0 | DU59: 1 | DV59: 0 | DW59: 0 | DX59: 0 | DY59: 0 | DZ59: 0 | EA59: 0 | EB59: 0 | EC59: 4 | ED59: 0 | EE59: 0 | EF59: 0 | EG59: 0 | EH59: 0 | EI59: 0 | EJ59: 0 | EK59: 1 | EL59: 0 | EM59: 2 | EN59: 0 | EO59: 0 | EP59: 0 | EQ59: 5 | ER59: 0 | ES59: 10 | ET59: Suspended | EU59: Suspended | EV59: Suspended | EW59: Suspended | EX59: Suspended | EY59: Suspended | EZ59: Suspended | FA59: Suspended | FB59: Suspended | FC59: Suspended | FD59: Suspended | FE59: Suspended | FF59: Suspended | FG59: Suspended | FH59: Suspended | FI59: Suspended | FJ59: Suspended | FK59: Suspended | FL59: Suspended | FM59: Suspended | FN59: Suspended | FO59: Suspended | FP59: Suspended | FQ59: Suspended | FR59: Suspended | FS59: Suspended | FT59: 2 | FU59: 20 | FV59: 0 | FW59: 0 | FX59: 2 | FY59: 34 | FZ59: 2 | GA59: 59 | GB59: 0 | GC59: 73 | GD59: 0 | GE59: 35 | GF59: 0 | GG59: 15 | GH59: 0 | GI59: 82 | GJ59: 0 | GK59: 40 | GL59: 0 | GM59: 48 | GN59: 1 | GO59: 91 | GP59: 1 | GQ59: 40 | GR59: 0 | GS59: 28 | GT59: 0 | GU59: 25 | GV59: 0 | GW59: 4 | GX59: 0 | GY59: 64 | GZ59: 0 | HA59: 25 | HB59: Suspended | HC59: Suspended | HD59: Suspended | HE59: Suspended | HF59: Suspended | HG59: Suspended | HH59: Suspended | HI59: Suspended | HJ59: Suspended | HK59: Suspended | HL59: Suspended | HM59: Suspended | HN59: Suspended | HO59: Suspended | HP59: Suspended | HQ59: Suspended | HR59: Suspended | HS59: Suspended | HT59: Suspended | HU59: Suspended | HV59: Suspended | HW59: Suspended | HX59: Suspended | HY59: Suspended | HZ59: Suspended | IA59: Suspended | IB59: Suspended | IC59: Suspended | ID59: Suspended | IE59: Suspended | IF59: Suspended | IG59: Suspended | IH59: Suspended | II59: Suspended | IJ59: Suspended | IK59: Suspended | IL59: Suspended | IM59: Suspended | IN59: Suspended | IO59: Suspended | IP59: Suspended | IQ59: Suspended | IR59: Suspended | IS59: Suspended | IT59: Suspended | IU59: Suspended | IV59: Suspended | IW59: Suspended | IX59: Suspended | IY59: Suspended | IZ59: Suspended | JA59: Suspended | JB59: Suspended | JC59: Suspended | JD59: Suspended | JE59: Suspended
A60: 2.2 | C60: Loans with 3 missed DDs in 1st 4 months | D60: 1 | E60: 20 | F60: 0 | G60: 25 | H60: 0 | I60: 4 | J60: 0 | K60: 10 | L60: 0 | M60: 20 | N60: 0 | O60: 21 | P60: 0 | Q60: 7 | R60: 0 | S60: 0
A61: 2.3 | B61: Loans with overpayments equal to or greater than 20% of the loan in first 12 months | C61: Loans with overpayments £1k and greater in 1st 3 months | D61: 2 | E61: 35 | F61: 0 | G61: 38 | H61: 0 | I61: 1 | J61: 0 | K61: 6 | L61: 0 | M61: 7 | N61: 0 | O61: 9 | P61: 0 | Q61: 0 | R61: 0 | S61: 0 | T61: 0 | U61: 7 | V61: 0 | W61: 7 | X61: 0 | Y61: 7 | Z61: 0 | AA61: 13 | AB61: 0 | AC61: 19 | AD61: 0 | AE61: 8 | AF61: 0 | AG61: 11 | AH61: 0 | AI61: 2 | AJ61: 0 | AK61: 7 | AL61: 0 | AM61: 14 | AN61: 0 | AO61: 10 | AP61: 0 | AQ61: 8 | AR61: 0 | AS61: 16 | AT61: 0 | AU61: 5 | AV61: 1 | AW61: 18 | AX61: 0 | AY61: 7 | AZ61: 0 | BA61: 8 | BB61: 0 | BC61: 4 | BD61: 0 | BE61: 4 | BF61: 0 | BG61: 0 | BH61: 0 | BI61: 9 | BJ61: 0 | BK61: 4 | BL61: 1 | BM61: 2 | BN61: 0 | BO61: 2 | BP61: 0 | BQ61: 1 | BR61: 0 | BS61: 5 | BT61: 0 | BU61: 6 | BV61: 0 | BW61: 0 | BX61: 0 | BY61: 2 | BZ61: 0 | CA61: 1 | CB61: 0 | CC61: 3 | CD61: 0 | CE61: 0 | CF61: 0 | CG61: 0 | CH61: 0 | CI61: 1 | CJ61: 0 | CK61: 0 | CL61: 0 | CM61: 0 | CN61: 0 | CO61: 0 | CP61: 0 | CQ61: 0 | CR61: 0 | CS61: 4 | CT61: 0 | CU61: 0 | CV61: 0 | CW61: 5 | CX61: 0 | CY61: 3 | CZ61: 0 | DA61: 19 | DB61: 0 | DC61: 11 | DD61: 0 | DE61: 0 | DF61: 0 | DG61: 0 | DH61: 0 | DI61: 3 | DJ61: 3 | DK61: 73 | DL61: 0 | DM61: 70 | DN61: 4 | DO61: 68 | DP61: 3 | DQ61: 81 | DR61: 2 | DS61: 92 | DT61: 1 | DU61: 93 | DV61: 0 | DW61: 92 | DX61: 2 | DY61: 107 | DZ61: 0 | EA61: 109 | EB61: 0 | EC61: 71 | ED61: 2 | EE61: 81 | EF61: 0 | EG61: 72 | EH61: 0 | EI61: 67 | EJ61: 0 | EK61: 79 | EL61: 1 | EM61: 68 | EN61: 2 | EO61: 89 | EP61: 0 | EQ61: 78 | ER61: 0 | ES61: 111 | ET61: 1 | EU61: 152 | EV61: 0 | EW61: 177 | EX61: 1 | EY61: 49 | EZ61: 1 | FA61: 67 | FB61: 2 | FC61: 46 | FD61: 1 | FE61: 68 | FF61: 2 | FG61: 80 | FH61: 3 | FI61: 81 | FJ61: 0 | FK61: 54 | FL61: 72 | FM61: 78 | FN61: Suspended | FO61: Suspended | FP61: Suspended | FQ61: Suspended | FR61: Suspended | FT61: 1 | FU61: 22 | FV61: 0 | FW61: 0 | FX61: 1 | FY61: 35 | FZ61: 0 | GA61: 4 | GB61: 0 | GC61: 2 | GD61: 0 | GE61: 10 | GF61: 1 | GG61: 8 | GH61: 0 | GI61: 0 | GJ61: 0 | GK61: 26 | GL61: 0 | GM61: 37 | GN61: 0 | GO61: 1 | GP61: 0 | GQ61: 46 | GR61: 0 | GS61: 16 | GT61: 2 | GU61: 37 | GV61: 0 | GW61: 61 | GX61: 0 | GY61: 30 | GZ61: 2 | HA61: 50 | HB61: Suspended | HC61: Suspended | HD61: Suspended | HE61: Suspended | HF61: Suspended | HG61: Suspended | HH61: Suspended | HI61: Suspended | HJ61: Suspended | HK61: Suspended | HL61: Suspended | HM61: Suspended | HN61: Suspended | HO61: Suspended | HP61: Suspended | HQ61: Suspended | HR61: Suspended | HS61: Suspended | HT61: Suspended | HU61: Suspended | HV61: Suspended | HW61: Suspended | HX61: Suspended | HY61: Suspended | HZ61: Suspended | IA61: Suspended | IB61: Suspended | IC61: Suspended | ID61: Suspended | IE61: Suspended | IF61: Suspended | IG61: Suspended | IH61: Suspended | II61: Suspended | IJ61: Suspended | IK61: Suspended | IL61: Suspended | IM61: Suspended | IN61: Suspended | IO61: Suspended | IP61: Suspended | IQ61: Suspended | IR61: Suspended | IS61: Suspended | IT61: Suspended | IU61: Suspended | IV61: Suspended | IW61: Suspended | IX61: Suspended | IY61: Suspended | IZ61: Suspended | JA61: Suspended | JB61: Suspended | JC61: Suspended | JD61: Suspended | JE61: Suspended
A62: 1.8 | C62: Loans over £5000 followed by 4+ Visa payments > £1K within 3 months | D62: 0 | E62: 49 | F62: 0 | G62: 61 | H62: 1 | I62: 34 | J62: 0 | K62: 44 | L62: 2 | M62: 54 | N62: 0 | O62: 48 | P62: 0 | Q62: 15 | R62: 0 | S62: 38 | T62: 0 | U62: 53 | V62: 1 | W62: 64 | X62: 0 | Y62: 84 | Z62: 0 | AA62: 61 | AB62: 0 | AC62: 61
A63: 1.9 | B63: Flex accounts with a £5k+ loan received 3 months ago and 10+ foreign Visa withdrawals (VW), each £100+, totalling £3k+ within past 3 months. | C63: Loans over £5000 followed by 10+ Foreign Visa WD total £3K+ within 3 months | D63: 0 | E63: 5 | F63: 0 | G63: 4 | H63: 0 | I63: 6 | J63: 0 | K63: 4 | L63: 0 | M63: 3 | N63: 0 | O63: 3 | P63: 0 | Q63: 0 | R63: 0 | S63: 2 | T63: 0 | U63: 6 | V63: 1 | W63: 4 | X63: 1 | Y63: 6 | Z63: 0 | AA63: 2 | AB63: 1 | AC63: 3 | AD63: 0 | AE63: 5 | AF63: 1 | AG63: 3 | AH63: 0 | AI63: 2 | AJ63: 0 | AK63: 6 | AL63: 0 | AM63: 2 | AN63: 0 | AO63: 4 | AP63: 0 | AQ63: 4 | AR63: 0 | AS63: 8 | AT63: 0 | AU63: 4 | AV63: 1 | AW63: 4 | AX63: 0 | AY63: 4 | AZ63: 0 | BA63: 4 | BB63: 0 | BC63: 3 | BD63: 0 | BE63: 3 | BF63: 0 | BG63: 2 | BH63: 1 | BI63: 3 | BJ63: 0 | BK63: 4 | BL63: 0 | BM63: 4 | BN63: 0 | BO63: 6 | BP63: 0 | BQ63: 4 | BR63: 0 | BS63: 4 | BT63: 0 | BU63: 6 | BV63: 0 | BW63: 2 | BX63: 0 | BY63: 2 | BZ63: 0 | CA63: 2 | CB63: 0 | CC63: 2 | CD63: 1 | CE63: 3 | CF63: 0 | CG63: 2 | CH63: 0 | CI63: 1 | CJ63: 0 | CK63: 0 | CL63: 0 | CM63: 2 | CN63: 0 | CO63: 2 | CP63: 0 | CQ63: 0 | CR63: 0 | CS63: 6 | CT63: 0 | CU63: 3 | CV63: 1 | CW63: 5 | CX63: 0 | CY63: 1 | CZ63: 0 | DA63: 3 | DB63: 0 | DC63: 2 | DD63: 0 | DE63: 3 | DF63: 0 | DG63: 1 | DH63: 0 | DI63: 1 | DJ63: 0 | DK63: 3 | DL63: 0 | DM63: 4 | DN63: 0 | DO63: 3 | DP63: 0 | DQ63: 1 | DR63: 0 | DS63: 2 | DT63: 0 | DU63: 2 | DV63: 0 | DW63: 0 | DX63: 0 | DY63: 0 | DZ63: 0 | EA63: 1 | EB63: 0 | EC63: 4 | ED63: 0 | EE63: 1 | EF63: 0 | EG63: 1 | EH63: 0 | EI63: 2 | EJ63: 0 | EK63: 2 | EL63: 0 | EM63: 2 | EN63: 0 | EO63: 4
A64: 1.10 | B64: Flex accounts with a £5k+ loan received 3 months ago and a CHAPS/SWIFT to a CoC in past 3 months. | C64: Loans over £5000 with CHAPS/SWIFT to CoC within 3 months | F64: 0 | G64: 4 | H64: 1 | I64: 10 | J64: 0 | K64: 10 | L64: 3 | M64: 11 | N64: 0 | O64: 9 | P64: 0 | Q64: 0 | R64: 1 | S64: 8 | T64: 0 | U64: 11 | V64: 0 | W64: 14 | X64: 0 | Y64: 9 | Z64: 0 | AA64: 12 | AB64: 1 | AC64: 15 | AD64: 0 | AE64: 11 | AF64: 1 | AG64: 9 | AH64: 0 | AI64: 10 | AJ64: 0 | AK64: 13 | AL64: 1 | AM64: 8 | AN64: 1 | AO64: 12 | AP64: 0 | AQ64: 10 | AR64: 0 | AS64: 23 | AT64: 1 | AU64: 13 | AV64: 1 | AW64: 11 | AX64: 2 | AY64: 13 | BA64: 15 | BB64: 1 | BC64: 7 | BD64: 1 | BE64: 10 | BF64: 0 | BG64: 13 | BH64: 3 | BI64: 12 | BJ64: 0 | BK64: 10 | BL64: 0 | BM64: 13 | BN64: 1 | BO64: 14 | BP64: 0 | BQ64: 4 | BR64: 0 | BS64: 12 | BT64: 0 | BU64: 18 | BV64: 0 | BW64: 11 | BX64: 0 | BY64: 13 | BZ64: 0 | CA64: 6 | CB64: 0 | CC64: 16 | CD64: 2 | CE64: 9 | CF64: 1 | CG64: 7 | CH64: 0 | CI64: 0 | CJ64: 0 | CK64: 6 | CL64: 0 | CM64: 11 | CN64: 0 | CO64: 6 | CP64: 2 | CQ64: 12 | CR64: 0 | CS64: 11 | CT64: 0 | CU64: 5 | CV64: 0 | CW64: 9 | CX64: 0 | CY64: 7 | CZ64: 0 | DA64: 6 | DB64: 0 | DC64: 9 | DD64: 0 | DE64: 14 | DF64: 2 | DG64: 13 | DH64: 0 | DI64: 4 | DJ64: 0 | DK64: 9 | DL64: 0 | DM64: 8 | DN64: 0 | DO64: 10 | DP64: 0 | DQ64: 4 | DR64: 1 | DS64: 8 | DT64: 0 | DU64: 10 | DV64: 1 | DW64: 5 | DX64: 0 | DY64: 8 | DZ64: 1 | EA64: 8 | EB64: 0 | EC64: 10 | ED64: 0 | EE64: 9 | EF64: 0 | EG64: 11 | EH64: 0 | EI64: 10 | EJ64: 0 | EK64: 12 | EL64: 0 | EM64: 8 | EN64: 0 | EO64: 11
A65: 2.4 | B65: Multiple Loans 3+ Loans £5k minimum loan value within 1 year | FT65: 1 | FU65: 2 | FV65: 0 | FW65: 0 | FX65: 0 | FY65: 4 | FZ65: 0 | GA65: 1 | GB65: 2 | GC65: 15 | GD65: 0 | GE65: 1 | GF65: 0 | GG65: 0 | GH65: 0 | GI65: 2 | GJ65: 0 | GK65: 4 | GL65: 0 | GM65: 13 | GN65: 0 | GO65: 5 | GP65: 0 | GQ65: 0 | GR65: 2 | GS65: 8 | GT65: 1 | GU65: 1 | GV65: 1 | GW65: 9 | GX65: 2 | GY65: 5 | GZ65: 0 | HA65: 2 | HB65: 0 | HC65: 9 | HD65: 2 | HE65: 2 | HF65: 0 | HG65: 3 | HH65: 0 | HI65: 4 | HJ65: 0 | HK65: 0 | HL65: 0 | HM65: 2 | HN65: 0 | HO65: 7 | HP65: 0 | HQ65: 1 | HR65: 1 | HS65: 4 | HT65: 0 | HU65: 1 | HV65: 0 | HW65: 0 | HX65: 0 | HY65: 4 | HZ65: 1 | IA65: 6 | IB65: 1 | IC65: 7 | ID65: 1 | IE65: 2 | IF65: 0 | IG65: 6 | IH65: 1 | II65: 4 | IJ65: 0 | IK65: 2 | IL65: 1 | IM65: 5 | IN65: 0 | IO65: 2 | IP65: 0 | IQ65: 1 | IR65: 0 | IS65: 1 | IT65: 0 | IU65: 5 | IV65: 0 | IW65: 3 | IX65: 0 | IY65: 3 | IZ65: 1 | JA65: 2 | JB65: 0 | JC65: 2 | JD65: 1 | JE65: 9
A66: 2.5 | B66: Fraud or Suspect in SIRA or Payment from high risk countries/tax havens into customer’s accounts, within 30 days | FT66: 2 | FU66: 2 | FV66: 0 | FW66: 0 | FX66: 0 | FY66: 1 | FZ66: 0 | GA66: 0 | GB66: 0 | GC66: 2 | GD66: 0 | GE66: 1 | GF66: 0 | GG66: 0 | GH66: 0 | GI66: 0 | GJ66: 0 | GK66: 2 | GL66: 0 | GM66: 1 | GN66: 0 | GO66: 0 | GP66: 0 | GQ66: 1 | GR66: 0 | GS66: 1 | GT66: 0 | GU66: 0 | GV66: 0 | GW66: 2 | GX66: 0 | GY66: 2 | GZ66: 0 | HA66: 0 | HB66: 0 | HC66: 0 | HD66: 0 | HE66: 2 | HF66: 0 | HG66: 1 | HH66: 0 | HI66: 0 | HJ66: 0 | HK66: 4 | HL66: 0 | HM66: 0 | HN66: 0 | HO66: 1 | HP66: 0 | HQ66: 1 | HR66: 0 | HS66: 3 | HT66: 0 | HU66: 1 | HV66: 0 | HW66: 0 | HX66: 0 | HY66: 1 | HZ66: 0 | IA66: 0 | IB66: 0 | IC66: 0 | ID66: 0 | IE66: 2 | IF66: 0 | IG66: 3 | IH66: 0 | II66: 1 | IJ66: 0 | IK66: 0 | IL66: 0 | IM66: 0 | IN66: 0 | IO66: 1 | IP66: 1 | IQ66: 2 | IR66: 0 | IS66: 0 | IT66: 0 | IU66: 0 | IV66: 0 | IW66: 0 | IX66: 0 | IY66: 3 | IZ66: 0 | JA66: 1 | JB66: 0 | JC66: 2 | JD66: 0 | JE66: 2
B67: Loan Total | C67: Loan Total | D67: =SUM(D59:D66) -> 3 | E67: =SUM(E59:E66) -> 109 | F67: =SUM(F59:F66) -> 0 | G67: =SUM(G59:G66) -> 132 | H67: =SUM(H59:H66) -> 2 | I67: =SUM(I59:I66) -> 60 | J67: =SUM(J59:J66) -> 0 | K67: =SUM(K59:K66) -> 125 | ... JE67: =SUM(JE59:JE66) -> 11
A68: 4.1 | B68: Credit Card Cash withdrawals in CoC where transactions total £3k+. | C68: Cash withdrawals in Countries of concern | F68: 2 | G68: 16 | H68: 0 | I68: 14 | J68: 1 | K68: 19 | L68: 1 | M68: 18 | N68: 1 | O68: 7 | P68: 0 | Q68: 4 | R68: 0 | S68: 10 | T68: 0 | U68: 20 | V68: 0 | W68: 16 | X68: 1 | Y68: 12 | Z68: 0 | AA68: 11 | AB68: 0 | AC68: 7 | AD68: 0 | AE68: 16 | AF68: 0 | AG68: 10 | AH68: 0 | AI68: 10 | AJ68: 0 | AK68: 10 | AL68: 0 | AM68: 8 | AN68: 0 | AO68: 12 | AP68: 0 | AQ68: 10 | AR68: 0 | AS68: 11 | AT68: 0 | AU68: 2 | AV68: 0 | AW68: 7 | AX68: 0 | AY68: 10 | AZ68: 1 | BA68: 11 | BB68: 0 | BC68: 21 | BD68: 0 | BE68: 7 | BF68: 0 | BG68: 13 | BJ68: 0 | BK68: 12 | BL68: 1 | BM68: 9 | BN68: 0 | BO68: 8 | BP68: 1 | BQ68: 16 | BR68: 0 | BS68: 9 | BT68: 0 | BU68: 14 | BV68: 0 | BW68: 12 | BX68: 0 | BY68: 13 | BZ68: 0 | CA68: 8 | CB68: 0 | CC68: 8 | CD68: 0 | CE68: 4 | CF68: 0 | CG68: 15 | CH68: 0 | CI68: 10 | CJ68: 0 | CK68: 5 | CL68: 1 | CM68: 14 | CN68: 0 | CO68: 14 | CP68: 0 | CQ68: 7 | CR68: 0 | CS68: 7 | CT68: 2 | CU68: 11 | CV68: 0 | CW68: 12 | CX68: 0 | CY68: 10 | CZ68: 0 | DA68: 12 | DB68: 0 | DC68: 11 | DD68: 2 | DE68: 8 | DF68: 0 | DG68: 4 | DH68: 0 | DI68: 5 | DJ68: 0 | DK68: 5 | DL68: 0 | DM68: 11 | DN68: 0 | DO68: 5 | DP68: 0 | DQ68: 10 | DR68: 0 | DS68: 7 | DT68: 1 | DU68: 11 | DV68: 0 | DW68: 10 | DX68: 0 | DY68: 14 | DZ68: 0 | EA68: 11 | EB68: 0 | EC68: 11 | ED68: 0 | EE68: 4 | EF68: 0 | EG68: 6 | EH68: 0 | EI68: 10 | EJ68: 1 | EK68: 13 | EL68: 0 | EM68: 11 | EN68: 0 | EO68: 3 | EP68: 0 | EQ68: 8 | ER68: 0 | ES68: 12 | ET68: 0 | EU68: 9 | EV68: 0 | EW68: 5 | EX68: 0 | EY68: 14 | EZ68: 0 | FA68: 6 | FB68: 0 | FC68: 4 | FD68: 0 | FE68: 3 | FF68: 0 | FG68: 6 | FH68: 1 | FI68: 6 | FJ68: 0 | FK68: 3 | FM68: 3 | FN68: 0 | FO68: 2 | FP68: 0 | FQ68: 6 | FR68: 0 | FS68: 4 | FT68: 0 | FU68: 4 | FV68: 0 | FW68: 7 | FX68: 0 | FY68: 4 | FZ68: 0 | GA68: 3 | GB68: 0 | GC68: 7 | GD68: 0 | GE68: 4 | GF68: 0 | GG68: 5 | GH68: 0 | GI68: 7 | GJ68: 0 | GK68: 5 | GL68: 0 | GM68: 7 | GN68: 0 | GO68: 7 | GP68: 1 | GQ68: 2
A69: 4.2 | C69: Large Non DD payment and a large spend | F69: 1 | G69: 24 | H69: 2 | I69: 16 | J69: 2 | K69: 36 | L69: 0 | M69: 25 | N69: 0 | O69: 30 | P69: 0 | Q69: 13 | R69: 0 | S69: 0 | T69: 1 | U69: 25 | V69: 0 | W69: 30 | X69: 0 | Y69: 24 | Z69: 0 | AA69: 29 | AB69: 1 | AC69: 25
A70: 4.3 | B70: Credit Card with >£10k positive balance for past three months. | C70: Postive Balances on Card (gt £5K) | AD70: 0 | AE70: 3 | AF70: 0 | AG70: 6 | AH70: 0 | AI70: 12 | AJ70: 0 | AK70: 5 | AL70: 0 | AM70: 3 | AN70: 0 | AO70: 9 | AP70: 1 | AQ70: 14 | AR70: 1 | AS70: 12 | AT70: 0 | AU70: 20 | AV70: 0 | AW70: 12 | AX70: 0 | AY70: 8 | AZ70: 2 | BA70: 15 | BB70: 1 | BC70: 12 | BD70: 0 | BE70: 14 | BF70: 0 | BG70: 9 | BJ70: 0 | BK70: 22 | BL70: 0 | BM70: 15 | BN70: 0 | BO70: 11 | BP70: 1 | BQ70: 19 | BR70: 0 | BS70: 0 | BT70: 0 | BU70: 24 | BV70: 1 | BW70: 27 | BX70: 0 | BY70: 14 | BZ70: 0 | CA70: 6 | CB70: 0 | CC70: 5 | CD70: 0 | CE70: 13 | CF70: 0 | CG70: 12 | CH70: 0 | CI70: 12 | CJ70: 0 | CK70: 9 | CL70: 0 | CM70: 16 | CN70: 0 | CO70: 13 | CP70: 0 | CQ70: 10 | CR70: 0 | CS70: 10 | CT70: 0 | CU70: 15 | CV70: 0 | CW70: 12 | CX70: 0 | CY70: 6 | CZ70: 0 | DA70: 21 | DB70: 0 | DC70: 9 | DD70: 0 | DE70: 9 | DF70: 0 | DG70: 17 | DH70: 0 | DI70: 20 | DJ70: 0 | DK70: 12 | DL70: 0 | DM70: 11 | DN70: 0 | DO70: 13 | DP70: 0 | DQ70: 14 | DR70: 0 | DS70: 14 | DT70: 0 | DU70: 11 | DV70: 0 | DW70: 19 | DX70: 0 | DY70: 21 | DZ70: 0 | EA70: 21 | EB70: 0 | EC70: 16 | ED70: 0 | EE70: 20 | EF70: 0 | EG70: 20 | EH70: 2 | EI70: 19 | EJ70: 1 | EK70: 14 | EL70: 0 | EM70: 18 | EN70: 0 | EO70: 18 | EP70: 0 | EQ70: 17 | ER70: 0 | ES70: 21 | ET70: 2 | EU70: 21 | EV70: 0 | EW70: 20 | EX70: 0 | EY70: 5 | EZ70: 0 | FA70: 2 | FB70: 0 | FC70: 0 | FD70: 0 | FE70: 0 | FF70: 0 | FG70: 0 | FH70: 0 | FI70: 0 | FJ70: 0 | FK70: 0 | FM70: 0 | FN70: 0 | FO70: 5 | FP70: 0 | FQ70: 2 | FR70: 0 | FS70: 2 | FT70: 0 | FU70: 2 | FV70: 1 | FW70: 6 | FX70: 0 | FY70: 1 | FZ70: 1 | GA70: 2 | GB70: 0 | GC70: 1 | GD70: 0 | GE70: 4 | GF70: 0 | GG70: 3 | GH70: 0 | GI70: 4 | GJ70: 0 | GK70: 1 | GL70: 0 | GM70: 3 | GN70: 0 | GO70: 2 | GP70: 0 | GQ70: 1 | GR70: 0 | GS70: 2 | GT70: 0 | GU70: 2 | GV70: 0 | GW70: 1 | GX70: 0 | GY70: 1 | GZ70: 0 | HA70: 4 | HB70: 0 | HC70: 1 | HD70: 0 | HE70: 3 | HF70: 0 | HG70: 4 | HH70: 0 | HI70: 4 | HJ70: 0 | HK70: 4 | HL70: 0 | HM70: 5 | HN70: 0 | HO70: 1 | HP70: 0 | HQ70: 4 | HR70: 0 | HS70: 4 | HT70: 0 | HU70: 6 | HV70: 0 | HW70: 5 | HX70: 0 | HY70: 4 | HZ70: 0 | IA70: 6 | IB70: 0 | IC70: 4 | ID70: 0 | IE70: 4 | IF70: 0 | IG70: 7 | IH70: 1 | II70: 11 | IJ70: 0 | IK70: 7 | IL70: 0 | IM70: 7 | IN70: 0 | IO70: 7 | IP70: 0 | IQ70: 5 | IR70: 0 | IS70: 9 | IT70: 0 | IU70: 11 | IV70: 0 | IW70: 9 | IX70: 0 | IY70: 6 | IZ70: 0 | JA70: 7 | JB70: 1 | JC70: 9 | JD70: 1 | JE70: 10
A71: 4.4 | B71: Credit Cards with £2k+ spend on virtual games last month (includes Second Life, Eve Online and Blizzard). | C71: Credit cards with large (£500+) monthly spend on virtual games | AB71: 0 | AC71: 0 | AD71: 0 | AE71: 2 | AF71: 0 | AG71: 1 | AH71: 0 | AI71: 0 | AJ71: 0 | AK71: 1 | AL71: 0 | AM71: 0 | AN71: 0 | AO71: 0 | AP71: 0 | AQ71: 0 | AR71: 0 | AS71: 0 | AT71: 0 | AU71: 0 | AV71: 0 | AW71: 0 | AX71: 0 | AY71: 0 | AZ71: 0 | BA71: 1 | BB71: 0 | BC71: 0 | BD71: 0 | BE71: 0 | BF71: 0 | BG71: 1 | BJ71: 0 | BK71: 1 | BL71: 0 | BM71: 0 | BN71: 0 | BO71: 1 | BP71: 0 | BQ71: 0 | BR71: 0 | BS71: 0 | BT71: 0 | BU71: 1 | BV71: 0 | BW71: 0 | BX71: 0 | BY71: 0 | BZ71: 0 | CA71: 1 | CB71: 0 | CC71: 0 | CD71: 0 | CE71: 0 | CF71: 0 | CG71: 0 | CH71: 0 | CI71: 0 | CJ71: 0 | CK71: 0 | CL71: 0 | CM71: 0 | CN71: 0 | CO71: 0 | CP71: 0 | CQ71: 0 | CR71: 0 | CS71: 0 | CT71: 0 | CU71: 0 | CV71: 0 | CW71: 0 | CX71: 0 | CY71: 0 | CZ71: 0 | DA71: 0 | DB71: 0 | DC71: 0 | DD71: 0 | DE71: 0 | DF71: 0 | DG71: 0 | DH71: 0 | DI71: 0 | DJ71: 0 | DK71: 0 | DL71: 0 | DM71: 0 | DN71: 0 | DO71: 0 | DP71: 0 | DQ71: 0 | DR71: 0 | DS71: 0 | DT71: 0 | DU71: 0 | DV71: 0 | DW71: 0 | DX71: 0 | DY71: 0 | DZ71: 0 | EA71: 0 | EB71: 0 | EC71: 0 | ED71: 0 | EE71: 0 | EF71: 0 | EG71: 0 | EH71: 0 | EI71: 0 | EJ71: 0 | EK71: 0 | EL71: 0 | EM71: 0 | EN71: 0 | EO71: 0 | EP71: 0 | EQ71: 0 | ER71: 0 | ES71: 0
A72: 4.5 | B72: Credit Card purchases, totalling £3k+ in past 3 months, at tobacconists, supermarkets and duty free stores in Europe. | C72: Credit Card Purchase of large amount of Booze/Fags -Europe | AP72: 1 | AQ72: 13 | AR72: 1 | AS72: 1 | AT72: 0 | AU72: 3 | AV72: 6 | AW72: 13 | AX72: 1 | AY72: 1 | AZ72: 1 | BA72: 4 | BB72: 8 | BC72: 11 | BD72: 1 | BE72: 3 | BF72: 1 | BG72: 4 | BJ72: 14 | BK72: 18 | BL72: 0 | BM72: 4 | BN72: 0 | BO72: 1 | BP72: 3 | BQ72: 15 | BR72: 5 | BS72: 7 | BT72: 2 | BU72: 4 | BV72: 0 | BW72: 0 | BX72: 7 | BY72: 12 | BZ72: 4 | CA72: 7 | CB72: 0 | CC72: 4 | CD72: 1 | CE72: 1 | CF72: 6 | CG72: 10 | CH72: 1 | CI72: 5 | CJ72: 3 | CK72: 3 | CL72: 1 | CM72: 5 | CN72: 5 | CO72: 9 | CP72: 2 | CQ72: 6 | CR72: 1 | CS72: 2 | CT72: 2 | CU72: 5 | CV72: 5 | CW72: 9 | CX72: 3 | CY72: 4 | CZ72: 1 | DA72: 13 | DB72: 0 | DC72: 0 | DD72: 3 | DE72: 6 | DF72: 4 | DG72: 8 | DH72: 7 | DI72: 10 | DJ72: 0 | DK72: 1 | DL72: 0 | DM72: 5 | DN72: 2 | DO72: 6 | DP72: 7 | DQ72: 10 | DR72: 0 | DS72: 2 | DT72: 1 | DU72: 5 | DV72: 0 | DW72: 5 | DX72: 5 | DY72: 11 | DZ72: 0 | EA72: 6 | EB72: 1 | EC72: 6 | ED72: 0 | EE72: 3 | EF72: 3 | EG72: 11 | EH72: 1 | EI72: 6 | EJ72: 4 | EK72: 10 | EL72: 2 | EM72: 8 | EN72: 3 | EO72: 11 | EP72: 2 | EQ72: 6 | ER72: 2 | ES72: 11 | ET72: 0 | EU72: 11 | EV72: 2 | EW72: 9 | EX72: 2 | EY72: 10 | EZ72: 2 | FA72: 11 | FB72: 11 | FC72: 17 | FD72: 7 | FE72: 25 | FF72: 2 | FG72: 12 | FH72: 4 | FI72: 19 | FJ72: 6 | FK72: 15 | FM72: 15 | FN72: 2 | FO72: 13 | FP72: 6 | FQ72: 15 | FR72: 2 | FS72: 7 | FT72: 3 | FU72: 10 | FV72: 3 | FW72: 9 | FX72: 3 | FY72: 8 | FZ72: 5 | GA72: 10 | GB72: 4 | GC72: 15 | GD72: 4 | GE72: 24 | GF72: 6 | GG72: 21 | GH72: 7 | GI72: 17 | GJ72: 0 | GK72: 10 | GL72: 5 | GM72: 15 | GN72: 7 | GO72: 20 | GP72: 5 | GQ72: 17 | GR72: 1 | GS72: 9 | GT72: 3 | GU72: 9 | GV72: 5 | GW72: 12 | GX72: 4 | GY72: 20 | GZ72: 4 | HA72: 15 | HB72: 4 | HC72: 17 | HD72: 9 | HE72: 26 | HF72: 5 | HG72: 24 | HH72: 4 | HI72: 23 | HJ72: 5 | HK72: 11 | HL72: 6 | HM72: 18 | HN72: 2 | HO72: 15 | HP72: 4 | HQ72: 11 | HR72: 1 | HS72: 10 | HT72: 1 | HU72: 6 | HV72: 0 | HW72: 5 | HX72: 0 | HY72: 13 | HZ72: 1 | IA72: 12 | IB72: 3 | IC72: 13 | ID72: 1 | IE72: 15
A73: 4.6 | B73: Credit Card with at least £20k in & £20k out last month. | C73: Credit Card with high turnover in month | CH73: 0 | CI73: 5 | CJ73: 0 | CK73: 11 | CL73: 2 | CM73: 8 | CN73: 0 | CO73: 4 | CP73: 1 | CQ73: 8 | CR73: 2 | CS73: 11 | CT73: 0 | CU73: 3 | CV73: 1 | CW73: 12 | CX73: 1 | CY73: 7 | CZ73: 0 | DA73: 9 | DB73: 0 | DC73: 5 | DD73: 1 | DE73: 8 | DF73: 1 | DG73: 7 | DH73: 0 | DI73: 4 | DJ73: 3 | DK73: 19 | DL73: 0 | DM73: 10 | DN73: 1 | DO73: 5 | DP73: 1 | DQ73: 12 | DR73: 1 | DS73: 17 | DT73: 1 | DU73: 15 | DV73: 0 | DW73: 8 | DX73: 2 | DY73: 6 | DZ73: 0 | EA73: 11 | EB73: 0 | EC73: 10 | ED73: 0 | EE73: 9 | EF73: 2 | EG73: 16 | EH73: 0 | EI73: 10 | EJ73: 1 | EK73: 11 | EL73: 2 | EM73: 16 | EN73: 1 | EO73: 10 | EP73: 0 | EQ73: 13 | ER73: 0 | ES73: 17 | ET73: 0 | EU73: 12 | EV73: 0 | EW73: 9 | EX73: 6 | EY73: 104 | EZ73: 0 | FA73: 7 | FB73: 0 | FC73: 14 | FD73: 0 | FE73: 10 | FF73: 1 | FG73: 18 | FH73: 0 | FI73: 21 | FJ73: 0 | FK73: 21 | FM73: 21
B74: Credit Card Total | C74: Credit Card Total | D74: =SUM(D68:D73) -> 0 | E74: =SUM(E68:E73) -> 0 | F74: =SUM(F68:F73) -> 3 | G74: =SUM(G68:G73) -> 40 | H74: =SUM(H68:H73) -> 2 | I74: =SUM(I68:I73) -> 30 | J74: =SUM(J68:J73) -> 3 | K74: =SUM(K68:K73) -> 55 | ... JE74: =SUM(JE68:JE73) -> 10
A75: CT1 | B75: Flex accounts with a £5k+ loan received 3 months ago and 10+ foreign Visa withdrawals (VW), each £100+, totalling £3k+ within past 3 months. | C75: Loans over £5000 followed by 10+ Foreign Visa WD total £3K+ within 3 months | EV75: 0 | EW75: 2 | EX75: 0 | EY75: 3 | EZ75: 0 | FA75: 3
A76: CT2 | B76: Flex accounts with a £5k+ loan received 3 months ago and a CHAPS/SWIFT to a CoC in past 3 months. | C76: Loans over £5000 with CHAPS/SWIFT to CoC within 3 months | EV76: 0 | EW76: 6 | EX76: 1 | EY76: 10 | EZ76: 0 | FA76: 6
A77: CT3 | B77: Swift Payments to or from Afghanistan, VISA spend in Afghanistan and Online bank activity in Afghanistan
A78: CT4 | B78: Swift Payments to or from Iraq, VISA spend in Iraq and Online bank activity in Iraq
A79: CT5 | B79: Swift Payments to or from Somalia, VISA spend in Somalia and Online bank activity in Somalia
A80: CT6 | B80: Swift Payments to or from Syria, VISA spend in Syria and Online bank activity in Syria | FR80: 1 | FS80: 7 | FT80: 0 | FU80: 6 | FV80: 0 | FW80: 4 | FX80: 0 | FY80: 8 | FZ80: 3 | GA80: 11 | GB80: 0 | GC80: 10 | GD80: 0 | GE80: 9 | GF80: 3 | GG80: 16 | GH80: 4 | GI80: 15 | GJ80: 1 | GK80: 14 | GL80: 0 | GM80: 16 | GN80: 1 | GO80: 16 | GP80: 1 | GQ80: 18 | GR80: 0 | GS80: 18 | GT80: 0 | GU80: 13 | GV80: 1 | GW80: 15 | GX80: 3 | GY80: 17 | GZ80: 0 | HA80: 18 | HB80: 1 | HC80: 11 | HD80: Suspended | HE80: Suspended | HF80: 0 | HG80: 0 | HH80: 0 | HI80: 0 | HJ80: 0 | HK80: 0 | HL80: 0 | HM80: 0 | HN80: 0 | HO80: 0 | HP80: 0 | HQ80: 0 | HR80: 0 | HS80: 0 | HT80: 0 | HU80: 0 | HV80: 0 | HW80: 0 | HX80: 0 | HY80: 0 | HZ80: 0 | IA80: 0 | IB80: 0 | IC80: 0 | ID80: 0 | IE80: 0 | IF80: 0 | IG80: 0 | IH80: 0 | II80: 0 | IJ80: 0 | IK80: 0 | IL80: 0 | IM80: 0 | IN80: 0 | IO80: 0 | IP80: 0 | IQ80: 0 | IR80: 5 | IS80: 26 | IT80: 1 | IU80: 26 | IV80: 3 | IW80: 20 | IX80: 3 | IY80: 23 | IZ80: 3 | JA80: 34 | JB80: 3 | JC80: 46 | JD80: 1 | JE80: 36
A81: CT7 | B81: Swift Payments to or from Yemen, VISA spend in Yemen and Online bank activity in Yemen | FR81: 0 | FS81: 7 | FT81: 0 | FU81: 2 | FV81: 0 | FW81: 3 | FX81: 0 | FY81: 4 | FZ81: 0 | GA81: 6 | GB81: 0 | GC81: 8 | GD81: 0 | GE81: 7 | GF81: 0 | GG81: 13 | GH81: 0 | GI81: 11 | GJ81: 0 | GK81: 9 | GL81: 1 | GM81: 9 | GN81: 0 | GO81: 2 | GP81: 1 | GQ81: 6 | GR81: 0 | GS81: 5 | GT81: 0 | GU81: 6 | GV81: 1 | GW81: 6 | GX81: 1 | GY81: 6 | GZ81: 1 | HA81: 5 | HB81: 1 | HC81: 8 | HD81: Suspended | HE81: Suspended | HF81: 0 | HG81: 3 | HH81: 0 | HI81: 3 | HJ81: 0 | HK81: 0 | HL81: 0 | HM81: 0 | HN81: 0 | HO81: 1 | HP81: 0 | HQ81: 0 | HR81: 0 | HS81: 1 | HT81: 0 | HU81: 0 | HV81: 1 | HW81: 2 | HX81: 0 | HY81: 1 | HZ81: 0 | IA81: 0 | IB81: 0 | IC81: 0 | ID81: 0 | IE81: 3 | IF81: 0 | IG81: 0 | IH81: 0 | II81: 0 | IJ81: 0 | IK81: 0 | IL81: 0 | IM81: 0 | IN81: 1 | IO81: 1 | IP81: 0 | IQ81: 1 | IR81: 2 | IS81: 21 | IT81: 1 | IU81: 18 | IV81: 2 | IW81: 17 | IX81: 1 | IY81: 13 | IZ81: 1 | JA81: 23 | JB81: 0 | JC81: 36 | JD81: 1 | JE81: 24
A82: CT8 | B82: Swift Payments to or from Libya, VISA spend in Libya and Online bank activity in Libya | FR82: 1 | FS82: 35 | FT82: 0 | FU82: 26 | FV82: 0 | FW82: 32 | FX82: 4 | FY82: 37 | FZ82: 2 | GA82: 28 | GB82: 3 | GC82: 32 | GD82: 5 | GE82: 34 | GF82: 3 | GG82: 30 | GH82: 2 | GI82: 58 | GJ82: 2 | GK82: 41 | GL82: 1 | GM82: 27 | GN82: 0 | GO82: 29 | GP82: 1 | GQ82: 37 | GR82: 0 | GS82: 36 | GT82: 0 | GU82: 36 | GV82: 2 | GW82: 33 | GX82: 2 | GY82: 25 | GZ82: 1 | HA82: 26 | HB82: 3 | HC82: 32 | HD82: Suspended | HE82: Suspended | HF82: 0 | HG82: 0 | HH82: 0 | HI82: 0 | HJ82: 0 | HK82: 1 | HL82: 1 | HM82: 2 | HN82: 0 | HO82: 1 | HP82: 0 | HQ82: 2 | HR82: 1 | HS82: 2 | HT82: 0 | HU82: 1 | HV82: 0 | HW82: 1 | HX82: 0 | HY82: 0 | HZ82: 0 | IA82: 0 | IB82: 0 | IC82: 1 | ID82: 0 | IE82: 0 | IF82: 0 | IG82: 1 | IH82: 0 | II82: 0 | IJ82: 0 | IK82: 0 | IL82: 0 | IM82: 0 | IN82: 0 | IO82: 0 | IP82: 0 | IQ82: 0 | IR82: 5 | IS82: 45 | IT82: 5 | IU82: 54 | IV82: 5 | IW82: 57 | IX82: 5 | IY82: 53 | IZ82: 9 | JA82: 59 | JB82: 9 | JC82: 70 | JD82: 3 | JE82: 55
B83: CTF Total | C83: CTF Total | ES83: =SUM(ES75:ES76) -> 0 | ET83: =SUM(ET75:ET76) -> 0 | EU83: =SUM(EU75:EU76) -> 0 | EV83: =SUM(EV75:EV76) -> 0 | EW83: =SUM(EW75:EW76) -> 8 | EX83: =SUM(EX75:EX76) -> 1 | EY83: =SUM(EY75:EY76) -> 13 | EZ83: =SUM(EZ75:EZ76) -> 0 | ... FQ83: =SUM(FQ75:FQ76) -> 0 | FR83: =SUM(FR75:FR82) -> 2 | FS83: =SUM(FS75:FS82) -> 49 | FT83: =SUM(FT75:FT82) -> 0 | FU83: =SUM(FU75:FU82) -> 34 | FV83: =SUM(FV75:FV82) -> 0 | FW83: =SUM(FW75:FW82) -> 39 | FX83: =SUM(FX75:FX82) -> 4 | FY83: =SUM(FY75:FY82) -> 49 | ... JE83: =SUM(JE75:JE82) -> 115
A84: HRC TM1 | B84: Cash Deposits >=£10K In 3 or more transactions | GN84: 11 | GO84: 43 | GP84: 19 | GQ84: 58 | GR84: 18 | GS84: 43 | GT84: 11 | GU84: 27 | GV84: 14 | GW84: 49 | GX84: 9 | GY84: 41 | GZ84: 10 | HA84: 39 | HB84: 4 | HC84: 12
A85: HRC TM2 | B85: Branch Visits >=3 Branches in 2 weeks | GN85: 6 | GO85: 28 | GP85: 22 | GQ85: 108 | GR85: 24 | GS85: 88 | GT85: 21 | GU85: 72 | GV85: 11 | GW85: 58 | GX85: 18 | GY85: 86 | GZ85: 11 | HA85: 56 | HB85: 4 | HC85: 16
A86: HRC TM3 | B86: Transaction to Coc >=£10k exc if payment to ctry of nationality/residency | GN86: 0 | GO86: 5 | GP86: 2 | GQ86: 9 | GR86: 1 | GS86: 13 | GT86: 1 | GU86: 11 | GV86: 0 | GW86: 17 | GX86: 2 | GY86: 15 | GZ86: 0 | HA86: 1 | HB86: 2 | HC86: 3
A87: HRC TM4 | B87: £30K Credit - Debit 200+ transactions | GN87: 36 | GO87: 204 | GP87: 10 | GQ87: 66 | GR87: 4 | GS87: 45 | GT87: 10 | GU87: 54 | GV87: 13 | GW87: 86 | GX87: 9 | GY87: 91 | GZ87: 12 | HA87: 63 | HB87: 6 | HC87: 33
A88: HRC TM5 | B88: High Value Transactions - Credits >= £100K | GN88: 0 | GO88: 4 | GP88: 1 | GQ88: 11 | GR88: 4 | GS88: 24 | GT88: 1 | GU88: 19 | GV88: 1 | GW88: 13 | GX88: 1 | GY88: 22 | GZ88: 0 | HA88: 11 | HB88: 1 | HC88: 9
B89: HRC TM Total | GN89: =SUM(GN84:GN88) -> 53 | GO89: =SUM(GO84:GO88) -> 284 | GP89: =SUM(GP84:GP88) -> 54 | GQ89: =SUM(GQ84:GQ88) -> 252 | GR89: =SUM(GR84:GR88) -> 51 | GS89: =SUM(GS84:GS88) -> 213 | GT89: =SUM(GT84:GT88) -> 44 | GU89: =SUM(GU84:GU88) -> 183 | ... JE89: =SUM(JE84:JE88) -> 0
A90: HRC TM1 (RRP) | B90: Cash Deposits >=£10K In 3 or more transactions | HB90: 3 | HC90: 28 | HD90: 0 | HE90: 8 | HF90: 3 | HG90: 10 | HH90: 0 | HI90: 11 | HJ90: 0 | HK90: 9 | HL90: 1 | HM90: 6 | HN90: 1 | HO90: 8 | HP90: 0 | HQ90: 6 | HR90: 0 | HS90: 4 | HT90: 0 | HU90: 3 | HV90: 0 | HW90: 2 | HX90: 0 | HY90: 2 | HZ90: 0 | IA90: 5 | IB90: 0 | IC90: 4 | ID90: 0 | IE90: 4 | IF90: 0 | IG90: 7 | IH90: 0 | II90: 1 | IJ90: 0 | IK90: 4 | IL90: 0 | IM90: 8 | IN90: 0 | IO90: 3 | IP90: 0 | IQ90: 7 | IR90: 0 | IS90: 5 | IT90: 0 | IU90: 2 | IV90: 0 | IW90: 0 | IX90: 0 | IY90: 24 | IZ90: 2 | JA90: 11 | JB90: 0 | JC90: 16 | JD90: 2 | JE90: 15
A91: HRC TM2 (RRP) | B91: Branch Visits >=3 Branches in 2 weeks | HB91: 0 | HC91: 56 | HD91: 0 | HE91: 20 | HF91: 1 | HG91: 29 | HH91: 1 | HI91: 10 | HJ91: 0 | HK91: 7 | HL91: 0 | HM91: 2 | HN91: 0 | HO91: 2 | HP91: 0 | HQ91: 5 | HR91: 0 | HS91: 1 | HT91: 0 | HU91: 1 | HV91: 0 | HW91: 2 | HX91: 0 | HY91: 0 | HZ91: 0 | IA91: 1 | IB91: 0 | IC91: 0 | ID91: 0 | IE91: 1 | IF91: 0 | IG91: 3 | IH91: 0 | II91: 2 | IJ91: 0 | IK91: 4 | IL91: 0 | IM91: 1 | IN91: 0 | IO91: 3 | IP91: 0 | IQ91: 1 | IR91: 0 | IS91: 0 | IT91: 0 | IU91: 0 | IV91: 0 | IW91: 0 | IX91: 0 | IY91: 13 | IZ91: 0 | JA91: 2 | JB91: 0 | JC91: 8 | JD91: 0 | JE91: 5
A92: HRC TM3 (RRP) | B92: Transaction to Coc >=£10k exc if payment to ctry of nationality/residency | HB92: 0 | HC92: 6 | HD92: 0 | HE92: 1 | HF92: 0 | HG92: 2 | HH92: 0 | HI92: 0 | HJ92: 0 | HK92: 0 | HL92: 0 | HM92: 1 | HN92: 0 | HO92: 1 | HP92: 0 | HQ92: 1 | HR92: 0 | HS92: 2 | HT92: 0 | HU92: 0 | HV92: 0 | HW92: 0 | HX92: 0 | HY92: 1 | HZ92: 0 | IA92: 0 | IB92: 0 | IC92: 1 | ID92: 0 | IE92: 1 | IF92: 0 | IG92: 1 | IH92: 0 | II92: 0 | IJ92: 0 | IK92: 0 | IL92: 0 | IM92: 0 | IN92: 0 | IO92: 0 | IP92: 0 | IQ92: 1 | IR92: 0 | IS92: 1 | IT92: 0 | IU92: 0 | IV92: 0 | IW92: 0 | IX92: 0 | IY92: 1 | IZ92: 0 | JA92: 0 | JB92: 0 | JC92: 0 | JD92: 0 | JE92: 0
A93: HRC TM4 (RRP) | B93: £30K Credit - Debit 200+ transactions | HB93: 0 | HC93: 52 | HD93: 2 | HE93: 13 | HF93: 4 | HG93: 54 | HH93: 3 | HI93: 41 | HJ93: 1 | HK93: 28 | HL93: 0 | HM93: 73 | HN93: 2 | HO93: 43 | HP93: 0 | HQ93: 45 | HR93: 0 | HS93: 53 | HT93: 1 | HU93: 37 | HV93: 2 | HW93: 45 | HX93: 4 | HY93: 50 | HZ93: 0 | IA93: 53 | IB93: 0 | IC93: 45 | ID93: 0 | IE93: 63 | IF93: 0 | IG93: 65 | IH93: 0 | II93: 42 | IJ93: 0 | IK93: 46 | IL93: 0 | IM93: 71 | IN93: 0 | IO93: 60 | IP93: 0 | IQ93: 74 | IR93: 0 | IS93: 63 | IT93: 0 | IU93: 13 | IV93: 0 | IW93: 0 | IX93: 3 | IY93: 406 | IZ93: 3 | JA93: 202 | JB93: 0 | JC93: 134 | JD93: 8 | JE93: 249
A94: HRC TM5 (RRP) | B94: High Value Transactions - Credits >= £100K | HB94: 0 | HC94: 8 | HD94: 0 | HE94: 2 | HF94: 0 | HG94: 5 | HH94: 0 | HI94: 1 | HJ94: 0 | HK94: 3 | HL94: 0 | HM94: 1 | HN94: 0 | HO94: 3 | HP94: 0 | HQ94: 2 | HR94: 0 | HS94: 1 | HT94: 0 | HU94: 0 | HV94: 0 | HW94: 1 | HX94: 0 | HY94: 1 | HZ94: 0 | IA94: 5 | IB94: 0 | IC94: 2 | ID94: 0 | IE94: 0 | IF94: 0 | IG94: 4 | IH94: 0 | II94: 2 | IJ94: 0 | IK94: 2 | IL94: 0 | IM94: 1 | IN94: 0 | IO94: 1 | IP94: 0 | IQ94: 1 | IR94: 0 | IS94: 3 | IT94: 0 | IU94: 4 | IV94: 0 | IW94: 0 | IX94: 0 | IY94: 75 | IZ94: 0 | JA94: 16 | JB94: 0 | JC94: 8 | JD94: 0 | JE94: 27
B95: RRP TM Total | HB95: =SUM(HB90:HB94) -> 3 | HC95: =SUM(HC90:HC94) -> 150 | HD95: =SUM(HD90:HD94) -> 2 | HE95: =SUM(HE90:HE94) -> 44 | HF95: =SUM(HF90:HF94) -> 8 | HG95: =SUM(HG90:HG94) -> 100 | HH95: =SUM(HH90:HH94) -> 4 | HI95: =SUM(HI90:HI94) -> 63 | ... JE95: =SUM(JE90:JE94) -> 296
A96: HTMS1 | B96: Victims | HH96: 11 | HI96: 58 | HJ96: 15 | HK96: 33 | HL96: 3 | HM96: 10 | HN96: 7 | HO96: 18 | HP96: 23 | HQ96: 56 | HR96: 8 | HS96: 17 | HT96: 16 | HU96: 31 | HV96: 22 | HW96: 48 | HX96: 2 | HY96: 31 | HZ96: 12 | IA96: 19 | IB96: 5 | IC96: 13 | ID96: 20 | IE96: 33 | IF96: 10 | IG96: 27 | IH96: 10 | II96: 24 | IJ96: 13 | IK96: 26 | IL96: 3 | IM96: 7 | IN96: 3 | IO96: 29 | IP96: 9 | IQ96: 18 | IR96: 9 | IS96: 13 | IT96: 21 | IU96: 28 | IV96: 10 | IW96: 23 | IX96: 12 | IY96: 22 | IZ96: 5 | JA96: 10 | JB96: 22 | JC96: 31 | JD96: 3 | JE96: 10
A97: HTMS2 | B97: Offenders | HH97: 0 | HI97: 1 | HJ97: 2 | HK97: 6 | HL97: 1 | HM97: 4 | HN97: 4 | HO97: 4 | HP97: 1 | HQ97: 1 | HR97: 2 | HS97: 12 | HT97: 2 | HU97: 2 | HV97: 1 | HW97: 1 | HX97: 1 | HY97: 1 | HZ97: 5 | IA97: 7 | IB97: 8 | IC97: 8 | ID97: 1 | IE97: 3 | IF97: 5 | IG97: 13 | IH97: 10 | II97: 14 | IJ97: 10 | IK97: 17 | IL97: 0 | IM97: 0 | IN97: 1 | IO97: 8 | IP97: 4 | IQ97: 8 | IR97: 2 | IS97: 7 | IT97: 1 | IU97: 4 | IV97: 2 | IW97: 6 | IX97: 1 | IY97: 1 | IZ97: 1 | JA97: 1 | JB97: 1 | JC97: 2 | JD97: 2 | JE97: 2
A98: HTMS3 | B98: Forced Criminality | HH98: 1 | HI98: 1 | HJ98: 0 | HK98: 1 | HL98: 0 | HM98: 1 | HN98: 0 | HO98: 0 | HP98: 7 | HQ98: 46 | HR98: 0 | HS98: 2 | HT98: 5 | HU98: 15 | HV98: 2 | HW98: 8 | HX98: 0 | HY98: 0 | HZ98: 1 | IA98: 2 | IB98: 2 | IC98: 3 | ID98: 6 | IE98: 37 | IF98: 0 | IG98: 10 | IH98: 2 | II98: 10 | IJ98: 5 | IK98: 10 | IL98: 1 | IM98: 6 | IN98: 0 | IO98: 5 | IP98: 2 | IQ98: 5 | IR98: 2 | IS98: 22 | IT98: 2 | IU98: 10 | IV98: 2 | IW98: 7 | IX98: 4 | IY98: 6 | IZ98: 2 | JA98: 5 | JB98: 1 | JC98: 8 | JD98: 0 | JE98: 10
A99: HTMS4
B100: HTMS Total | HH100: =SUM(HH96:HH99) -> 12 | HI100: =SUM(HI96:HI99) -> 60 | HJ100: =SUM(HJ96:HJ99) -> 17 | HK100: =SUM(HK96:HK99) -> 40 | HL100: =SUM(HL96:HL99) -> 4 | HM100: =SUM(HM96:HM99) -> 15 | HN100: =SUM(HN96:HN99) -> 11 | HO100: =SUM(HO96:HO99) -> 22 | ... JE100: =SUM(JE96:JE99) -> 22
...

Sheet rates
D1: 40513 | E1: 40544 | F1: 40575 | G1: 40603 | H1: 40634 | I1: 40664 | J1: 40695 | K1: 40725 | L1: 40756 | M1: 40787 | N1: 40817 | O1: 40848 | P1: 40878 | Q1: 40909 | R1: 40940 | S1: 40969 | T1: 41000 | U1: 41030 | V1: 41061 | W1: 41091 | X1: 41122 | Y1: 41153 | Z1: 41183 | AA1: 41214 | AB1: 41244 | AC1: 41275 | AD1: 41306 | AE1: 41334 | AF1: 41365 | AG1: 41395 | AH1: 41426 | AI1: 41456 | AJ1: 41487 | AK1: 41518 | AL1: 41548 | AM1: 41579 | AN1: 41609 | AO1: 41640 | AP1: 41671 | AQ1: 41699 | AR1: 41730 | AS1: 41760 | AT1: 41791 | AU1: 41821 | AV1: 41852 | AW1: 41883 | AX1: 41913 | AY1: 41944 | AZ1: 41974 | BA1: 42005 | BB1: 42036 | BC1: 42064 | BD1: 42095 | BE1: 42125 | BF1: 42156 | BG1: 42186 | BH1: 42217 | BI1: 42248 | BJ1: 42278 | BK1: 42309 | BL1: 42339 | BM1: 42370 | BN1: 42401 | BO1: 42430 | BP1: 42461 | BQ1: 42491 | BR1: 42522 | BS1: 42552 | BT1: 42583 | BU1: 42614 | BV1: 42644 | BW1: 42675 | BX1: 42705 | BY1: 42736 | BZ1: 42767 | CA1: 42795 | CB1: 42826 | CC1: 42856 | CD1: 42887 | CE1: 42917 | CF1: 42948 | CG1: 42979 | CH1: 43009 | CI1: 43040 | CJ1: 43070 | CK1: 43101 | CL1: 43132 | CM1: 43160 | CN1: 43191 | CO1: 43221 | CP1: 43252 | CQ1: 43282 | CR1: 43313 | CS1: 43344 | CT1: 43374 | CU1: 43405 | CV1: 43435 | CW1: 43466 | CX1: 43497 | CY1: 43525 | CZ1: 43556 | DA1: 43586 | DB1: 43617 | DC1: 43647 | DD1: 43678 | DE1: 43709 | DF1: 43739 | DG1: 43770 | DH1: 43800 | DI1: 43831 | DJ1: 43862 | DK1: 43891 | DL1: 43922 | DM1: 43952 | DN1: 43983 | DO1: 44013 | DP1: 44044 | DQ1: 44075 | DR1: 44105 | DS1: 44136 | DT1: 44166 | DU1: 44197 | DV1: 44228 | DW1: 44256 | DX1: 44287 | DY1: 44317 | DZ1: 44348 | EA1: 44378 | EB1: 44409 | EC1: 44440 | EE1: Rolling 12 Month Reported | EF1: Rolling 12 Month Alerted | EG1: Rolling 12 Month Rate
A2: 1.1 | B2: ='raw data'!B3 -> Flex accounts with >=2 cash credits (CR) & at least 1 withdrawal (WD) in same day (occurred at least three times last month). | C2: Flex Accounts with >2 CRs per Day with WD the same day | D2: =+'raw data'!D3/'raw data'!E3 -> 0.5 | E2: =+'raw data'!F3/'raw data'!G3 -> 0.38888889 | F2: =+'raw data'!H3/'raw data'!I3 -> 0.36 | G2: ='raw data'!J3/'raw data'!K3 -> 0.26470588 | H2: ='raw data'!L3/'raw data'!M3 -> 0.16363636 | I2: ='raw data'!N3/'raw data'!O3 -> 0.27536232 | J2: ='raw data'!P3/'raw data'!Q3 -> 0.15789474 | K2: ='raw data'!R3/'raw data'!S3 -> 0.3253012 | L2: ='raw data'!T3/'raw data'!U3 -> 0.23943662 | M2: ='raw data'!V3/'raw data'!W3 -> 0.25333333 | N2: ='raw data'!X3/'raw data'!Y3 -> 0.23880597 | O2: =IF(ISERROR('raw data'!Z3/'raw data'!AA3),0,'raw data'!Z3/'raw data'!AA3) -> 0.23728814 | P2: =IF(ISERROR('raw data'!AB3/'raw data'!AC3),0,'raw data'!AB3/'raw data'!AC3) -> 0.21333333 | Q2: =IF(ISERROR('raw data'!AD3/'raw data'!AE3),0,'raw data'!AD3/'raw data'!AE3) -> 0.16666667 | R2: =IF(ISERROR('raw data'!AF3/'raw data'!AG3),0,'raw data'!AF3/'raw data'!AG3) -> 0.2244898 | S2: =IF(ISERROR('raw data'!AH3/'raw data'!AI3),0,'raw data'!AH3/'raw data'!AI3) -> 0.2739726 | T2: =IF(ISERROR('raw data'!AJ3/'raw data'!AK3),0,'raw data'!AJ3/'raw data'!AK3) -> 0.37209302 | U2: =IF(ISERROR('raw data'!AL3/'raw data'!AM3),0,'raw data'!AL3/'raw data'!AM3) -> 0.13333333 | V2: =IF(ISERROR('raw data'!AN3/'raw data'!AO3),0,'raw data'!AN3/'raw data'!AO3) -> 0.26923077 | W2: =IF(ISERROR('raw data'!AP3/'raw data'!AQ3),0,'raw data'!AP3/'raw data'!AQ3) -> 0.28205128 | X2: =IF(ISERROR('raw data'!AR3/'raw data'!AS3),0,'raw data'!AR3/'raw data'!AS3) -> 0.45 | Y2: =IF(ISERROR('raw data'!AT3/'raw data'!AU3),0,'raw data'!AT3/'raw data'!AU3) -> 0.36666667 | Z2: =IF(ISERROR('raw data'!AV3/'raw data'!AW3),0,'raw data'!AV3/'raw data'!AW3) -> 0.23809524 | AA2: =IF(ISERROR('raw data'!AX3/'raw data'!AY3),0,'raw data'!AX3/'raw data'!AY3) -> 0.18181818 | AB2: =IF(ISERROR('raw data'!AZ3/'raw data'!BA3),0,'raw data'!AZ3/'raw data'!BA3) -> 0.3 | AC2: =IF(ISERROR('raw data'!BB3/'raw data'!BC3),0,'raw data'!BB3/'raw data'!BC3) -> 0.2972973 | AD2: =IF(ISERROR('raw data'!BD3/'raw data'!BE3),0,'raw data'!BD3/'raw data'!BE3) -> 0.41176471 | AE2: =IF(ISERROR('raw data'!BF3/'raw data'!BG3),0,'raw data'!BF3/'raw data'!BG3) -> 0.28571429 | AF2: =IF(ISERROR('raw data'!BH3/'raw data'!BI3),0,'raw data'!BH3/'raw data'!BI3) -> 0.33333333 | AG2: =IF(ISERROR('raw data'!BJ3/'raw data'!BK3),0,'raw data'!BJ3/'raw data'!BK3) -> 0.12903226 | AH2: =IF(ISERROR('raw data'!BL3/'raw data'!BM3),0,'raw data'!BL3/'raw data'!BM3) -> 0.14814815 | AI2: =IF(ISERROR('raw data'!BN3/'raw data'!BO3),0,'raw data'!BN3/'raw data'!BO3) -> 0.225 | AJ2: =IF(ISERROR('raw data'!BP3/'raw data'!BQ3),0,'raw data'!BP3/'raw data'!BQ3) -> 0.1 | AK2: =IF(ISERROR('raw data'!BR3/'raw data'!BS3),0,'raw data'!BR3/'raw data'!BS3) -> 0.25 | AL2: =IF(ISERROR('raw data'!BT3/'raw data'!BU3),0,'raw data'!BT3/'raw data'!BU3) -> 0.2173913 | AM2: =IF(ISERROR('raw data'!BV3/'raw data'!BW3),0,'raw data'!BV3/'raw data'!BW3) -> 0.25641026 | AN2: =IF(ISERROR('raw data'!BX3/'raw data'!BY3),0,'raw data'!BX3/'raw data'!BY3) -> 0.22222222 | AO2: =IF(ISERROR('raw data'!BZ3/'raw data'!CA3),0,'raw data'!BZ3/'raw data'!CA3) -> 0.20754717 | AP2: =IF(ISERROR('raw data'!CB3/'raw data'!CC3),0,'raw data'!CB3/'raw data'!CC3) -> 0.18181818 | AQ2: =IF(ISERROR('raw data'!CD3/'raw data'!CE3),0,'raw data'!CD3/'raw data'!CE3) -> 0.33333333 | AR2: =IF(ISERROR('raw data'!CF3/'raw data'!CG3),0,'raw data'!CF3/'raw data'!CG3) -> 0.33333333 | AS2: =IF(ISERROR('raw data'!CH3/'raw data'!CI3),0,'raw data'!CH3/'raw data'!CI3) -> 0.34693878 | AT2: =IF(ISERROR('raw data'!CJ3/'raw data'!CK3),0,'raw data'!CJ3/'raw data'!CK3) -> 0.23684211 | AU2: =IF(ISERROR('raw data'!CL3/'raw data'!CM3),0,'raw data'!CL3/'raw data'!CM3) -> 0.22807018 | AV2: =IF(ISERROR('raw data'!CN3/'raw data'!CO3),0,'raw data'!CN3/'raw data'!CO3) -> 0.28125 | AW2: =IF(ISERROR('raw data'!CP3/'raw data'!CQ3),0,'raw data'!CP3/'raw data'!CQ3) -> 0.35483871 | AX2: =IF(ISERROR('raw data'!CR3/'raw data'!CS3),0,'raw data'!CR3/'raw data'!CS3) -> 0.25 | AY2: =IF(ISERROR('raw data'!CT3/'raw data'!CU3),0,'raw data'!CT3/'raw data'!CU3) -> 0.3030303 | AZ2: =IF(ISERROR('raw data'!CV3/'raw data'!CW3),0,'raw data'!CV3/'raw data'!CW3) -> 0.37837838 | BA2: =IF(ISERROR('raw data'!CX3/'raw data'!CY3),0,'raw data'!CX3/'raw data'!CY3) -> 0.27027027 | BB2: =IF(ISERROR('raw data'!CZ3/'raw data'!DA3),0,'raw data'!CZ3/'raw data'!DA3) -> 0.43333333 | BC2: =IF(ISERROR('raw data'!DB3/'raw data'!DC3),0,'raw data'!DB3/'raw data'!DC3) -> 0.425 | BD2: 0.36363636 | BE2: =IF(ISERROR('raw data'!DF3/'raw data'!DG3),0,'raw data'!DF3/'raw data'!DG3) -> 0.3 | BF2: =IF(ISERROR('raw data'!DH3/'raw data'!DI3),0,'raw data'!DH3/'raw data'!DI3) -> 0.31578947 | BG2: =IF(ISERROR('raw data'!DJ3/'raw data'!DK3),0,'raw data'!DJ3/'raw data'!DK3) -> 0.34 | BH2: =IF(ISERROR('raw data'!DL3/'raw data'!DM3),0,'raw data'!DL3/'raw data'!DM3) -> 0.28888889 | BI2: =IF(ISERROR('raw data'!DN3/'raw data'!DO3),0,'raw data'!DN3/'raw data'!DO3) -> 0.48979592 | BJ2: =IF(ISERROR('raw data'!DP3/'raw data'!DQ3),0,'raw data'!DP3/'raw data'!DQ3) -> 0.43103448 | BK2: =IF(ISERROR('raw data'!DR3/'raw data'!DS3),0,'raw data'!DR3/'raw data'!DS3) -> 0.35483871 | BL2: =IF(ISERROR('raw data'!DT3/'raw data'!DU3),0,'raw data'!DT3/'raw data'!DU3) -> 0.35897436 | BM2: =IF(ISERROR('raw data'!DV3/'raw data'!DW3),0,'raw data'!DV3/'raw data'!DW3) -> 0.23255814 | BN2: =IF(ISERROR('raw data'!DX3/'raw data'!DY3),0,'raw data'!DX3/'raw data'!DY3) -> 0.32352941 | BO2: =IF(ISERROR('raw data'!DZ3/'raw data'!EA3),0,'raw data'!DZ3/'raw data'!EA3) -> 0.175 | BP2: =IF(ISERROR('raw data'!EB3/'raw data'!EC3),0,'raw data'!EB3/'raw data'!EC3) -> 0.42857143 | BQ2: =IF(ISERROR('raw data'!ED3/'raw data'!EE3),0,'raw data'!ED3/'raw data'!EE3) -> 0.17948718 | BR2: =IF(ISERROR('raw data'!EF3/'raw data'!EG3),0,'raw data'!EF3/'raw data'!EG3) -> 0.30188679 | BS2: =IF(ISERROR('raw data'!EH3/'raw data'!EI3),0,'raw data'!EH3/'raw data'!EI3) -> 0.17777778 | BT2: =IF(ISERROR('raw data'!EJ3/'raw data'!EK3),0,'raw data'!EJ3/'raw data'!EK3) -> 0.25862069 | BU2: =IF(ISERROR('raw data'!EL3/'raw data'!EM3),0,'raw data'!EL3/'raw data'!EM3) -> 0.31428571 | BV2: =IF(ISERROR('raw data'!EN3/'raw data'!EO3),0,'raw data'!EN3/'raw data'!EO3) -> 0.3030303 | BW2: =IF(ISERROR('raw data'!EP3/'raw data'!EQ3),0,'raw data'!EP3/'raw data'!EQ3) -> 0.29268293 | BX2: =IF(ISERROR('raw data'!ER3/'raw data'!ES3),0,'raw data'!ER3/'raw data'!ES3) -> 0.43181818 | BY2: =IF(ISERROR('raw data'!ET3/'raw data'!EU3),0,'raw data'!ET3/'raw data'!EU3) -> 0.30555556 | BZ2: =IF(ISERROR('raw data'!EV3/'raw data'!EW3),0,'raw data'!EV3/'raw data'!EW3) -> 0.26470588 | CA2: =IF(ISERROR('raw data'!EX3/'raw data'!EY3),0,'raw data'!EX3/'raw data'!EY3) -> 0.29310345 | CB2: =IF(ISERROR('raw data'!EZ3/'raw data'!FA3),0,'raw data'!EZ3/'raw data'!FA3) -> 0.31707317 | CC2: =IF(ISERROR('raw data'!FB3/'raw data'!FC3),0,'raw data'!FB3/'raw data'!FC3) -> 0.27272727 | CD2: =IF(ISERROR('raw data'!FD3/'raw data'!FE3),0,'raw data'!FD3/'raw data'!FE3) -> 0.26415094 | CE2: =IF(ISERROR('raw data'!FF3/'raw data'!FG3),0,'raw data'!FF3/'raw data'!FG3) -> 0.36734694 | CF2: =IF(ISERROR('raw data'!FH3/'raw data'!FI3),0,'raw data'!FH3/'raw data'!FI3) -> 0.23255814 | CG2: =IF(ISERROR('raw data'!FJ3/'raw data'!FM3),0,'raw data'!FJ3/'raw data'!FM3) -> 0.23913043 | CH2: =IF(ISERROR('raw data'!FN3/'raw data'!FO3),0,'raw data'!FN3/'raw data'!FO3) -> 0.1 | CI2: =IF(ISERROR('raw data'!FP3/'raw data'!FQ3),0,'raw data'!FP3/'raw data'!FQ3) -> 0.27777778 | CJ2: =IF(ISERROR('raw data'!FR3/'raw data'!FS3),0,'raw data'!FR3/'raw data'!FS3) -> 0.36363636 | CK2: =IF(ISERROR('raw data'!FT3/'raw data'!FU3),0,'raw data'!FT3/'raw data'!FU3) -> 0.38461538 | CL2: =IF(ISERROR('raw data'!FV3/'raw data'!FW3),0,'raw data'!FV3/'raw data'!FW3) -> 0.090909091 | CM2: =IF(ISERROR('raw data'!FX3/'raw data'!FY3),0,'raw data'!FX3/'raw data'!FY3) -> 0.14285714 | CN2: =IF(ISERROR('raw data'!FZ3/'raw data'!GA3),0,'raw data'!FZ3/'raw data'!GA3) -> 0.2 | CO2: =IF(ISERROR('raw data'!GB3/'raw data'!GC3),0,'raw data'!GB3/'raw data'!GC3) -> 0.33333333 | CP2: =IF(ISERROR('raw data'!GD3/'raw data'!GE3),0,'raw data'!GD3/'raw data'!GE3) -> 0.16666667 | CQ2: =IF(ISERROR('raw data'!GF3/'raw data'!GG3),0,'raw data'!GF3/'raw data'!GG3) -> 0.13333333 | CR2: =IF(ISERROR('raw data'!GH3/'raw data'!GI3),0,'raw data'!GH3/'raw data'!GI3) -> 0.4 | CS2: =IF(ISERROR('raw data'!GJ3/'raw data'!GK3),0,'raw data'!GJ3/'raw data'!GK3) -> 0.25 | CT2: =IF(ISERROR('raw data'!GL3/'raw data'!GM3),0,'raw data'!GL3/'raw data'!GM3) -> 0.33333333 | CU2: =IF(ISERROR('raw data'!GN3/'raw data'!GO3),0,'raw data'!GN3/'raw data'!GO3) -> 0.33333333 | CV2: =IF(ISERROR('raw data'!GP3/'raw data'!GQ3),0,'raw data'!GP3/'raw data'!GQ3) -> 0.33333333 | CW2: =IF(ISERROR('raw data'!GR3/'raw data'!GS3),0,'raw data'!GR3/'raw data'!GS3) -> 0.375 | CX2: =IF(ISERROR('raw data'!GT3/'raw data'!GU3),0,'raw data'!GT3/'raw data'!GU3) -> 0.4 | CY2: =IF(ISERROR('raw data'!GV3/'raw data'!GW3),0,'raw data'!GV3/'raw data'!GW3) -> 0.22222222 | CZ2: =IF(ISERROR('raw data'!GX3/'raw data'!GY3),0,'raw data'!GX3/'raw data'!GY3) -> 0.33333333 | DA2: =IF(ISERROR('raw data'!GZ3/'raw data'!HA3),0,'raw data'!GZ3/'raw data'!HA3) -> 0.5 | DB2: =IF(ISERROR('raw data'!HB3/'raw data'!HC3),0,'raw data'!HB3/'raw data'!HC3) -> 0 | DC2: =IF(ISERROR('raw data'!HD3/'raw data'!HE3),0,'raw data'!HD3/'raw data'!HE3) -> 0.125 | DD2: =IF(ISERROR('raw data'!HF3/'raw data'!HG3),0,'raw data'!HF3/'raw data'!HG3) -> 0.25 | DE2: =IF(ISERROR('raw data'!HH3/'raw data'!HI3),0,'raw data'!HH3/'raw data'!HI3) -> 0 | DF2: =IF(ISERROR('raw data'!HJ3/'raw data'!HK3),0,'raw data'!HJ3/'raw data'!HK3) -> 0.33333333 | DG2: =IF(ISERROR('raw data'!HL3/'raw data'!HM3),0,'raw data'!HL3/'raw data'!HM3) -> 0.125 | DH2: =IF(ISERROR('raw data'!HN3/'raw data'!HO3),0,'raw data'!HN3/'raw data'!HO3) -> 0.25 | DI2: =IF(ISERROR('raw data'!HP3/'raw data'!HQ3),0,'raw data'!HP3/'raw data'!HQ3) -> 0.57142857 | DJ2: =IF(ISERROR('raw data'!HR3/'raw data'!HS3),0,'raw data'!HR3/'raw data'!HS3) -> 0.66666667 | DK2: =IF(ISERROR('raw data'!HT3/'raw data'!HU3),0,'raw data'!HT3/'raw data'!HU3) -> 0.33333333 | DL2: =IF(ISERROR('raw data'!HV3/'raw data'!HW3),0,'raw data'!HV3/'raw data'!HW3) -> 0.16666667 | DM2: =IF(ISERROR('raw data'!HX3/'raw data'!HY3),0,'raw data'!HX3/'raw data'!HY3) -> 0.090909091 | DN2: =IF(ISERROR('raw data'!HZ3/'raw data'!IA3),0,'raw data'!HZ3/'raw data'!IA3) -> 0.083333333 | DO2: =IF(ISERROR('raw data'!IB3/'raw data'!IC3),0,'raw data'!IB3/'raw data'!IC3) -> 0.28571429 | DP2: =IF(ISERROR('raw data'!ID3/'raw data'!IE3),0,'raw data'!ID3/'raw data'!IE3) -> 0.33333333 | DQ2: =IF(ISERROR('raw data'!IF3/'raw data'!IG3),0,'raw data'!IF3/'raw data'!IG3) -> 0.57142857 | DR2: =IF(ISERROR('raw data'!IH3/'raw data'!II3),0,'raw data'!IH3/'raw data'!II3) -> 0 | DS2: =IF(ISERROR('raw data'!IJ3/'raw data'!IK3),0,'raw data'!IJ3/'raw data'!IK3) -> 0.2 | DT2: =IF(ISERROR('raw data'!IL3/'raw data'!IM3),0,'raw data'!IL3/'raw data'!IM3) -> 1 | DU2: =IF(ISERROR('raw data'!IN3/'raw data'!IO3),0,'raw data'!IN3/'raw data'!IO3) -> 1 | DV2: =IF(ISERROR('raw data'!IP3/'raw data'!IQ3),0,'raw data'!IP3/'raw data'!IQ3) -> 0 | DW2: =IF(ISERROR('raw data'!IR3/'raw data'!IS3),0,'raw data'!IR3/'raw data'!IS3) -> 1 | DX2: =IF(ISERROR('raw data'!IT3/'raw data'!IU3),0,'raw data'!IT3/'raw data'!IU3) -> 0 | DY2: =IF(ISERROR('raw data'!IV3/'raw data'!IW3),0,'raw data'!IV3/'raw data'!IW3) -> 0.33333333 | DZ2: =IF(ISERROR('raw data'!IX3/'raw data'!IY3),0,'raw data'!IX3/'raw data'!IY3) -> 0.75 | EA2: =IF(ISERROR('raw data'!IZ3/'raw data'!JA3),0,'raw data'!IZ3/'raw data'!JA3) -> 0 | EB2: =IF(ISERROR('raw data'!JB3/'raw data'!JC3),0,'raw data'!JB3/'raw data'!JC3) -> 0.5 | EC2: =IF(ISERROR('raw data'!JD3/'raw data'!JE3),0,'raw data'!JD3/'raw data'!JE3) -> 0.5 | EE2: 13 | EF2: 32 | EG2: =IF(ISERROR(EE2/EF2),0,EE2/EF2) -> 0.40625
A3: 1.2 | B3: ='raw data'!B4 -> Savings accounts with >=2 cash credits (CR) & at least 1 withdrawal (WD) in same day (occurred at least three times in month). | C3: Save Accs with >2 CRs per Day with WD the same day | D3: =+'raw data'!D4/'raw data'!E4 -> 0.53846154 | E3: =+'raw data'!F4/'raw data'!G4 -> 0.35 | F3: =+'raw data'!H4/'raw data'!I4 -> 0.125 | G3: ='raw data'!J4/'raw data'!K4 -> 0.33333333 | H3: ='raw data'!L4/'raw data'!M4 -> 0.32142857 | I3: ='raw data'!N4/'raw data'!O4 -> 0.48780488 | J3: ='raw data'!P4/'raw data'!Q4 -> 0 | K3: ='raw data'!R4/'raw data'!S4 -> 0.23809524 | L3: ='raw data'!T4/'raw data'!U4 -> 0.18181818 | M3: ='raw data'!V4/'raw data'!W4 -> 0.1875 | N3: ='raw data'!X4/'raw data'!Y4 -> 0.17391304 | O3: =IF(ISERROR('raw data'!Z4/'raw data'!AA4),0,'raw data'!Z4/'raw data'!AA4) -> 0.2 | P3: =IF(ISERROR('raw data'!AB4/'raw data'!AC4),0,'raw data'!AB4/'raw data'!AC4) -> 0.32 | Q3: =IF(ISERROR('raw data'!AD4/'raw data'!AE4),0,'raw data'!AD4/'raw data'!AE4) -> 0.30769231 | R3: =IF(ISERROR('raw data'!AF4/'raw data'!AG4),0,'raw data'!AF4/'raw data'!AG4) -> 0.13333333 | S3: =IF(ISERROR('raw data'!AH4/'raw data'!AI4),0,'raw data'!AH4/'raw data'!AI4) -> 0.15384615 | T3: =IF(ISERROR('raw data'!AJ4/'raw data'!AK4),0,'raw data'!AJ4/'raw data'!AK4) -> 0.23076923 | U3: =IF(ISERROR('raw data'!AL4/'raw data'!AM4),0,'raw data'!AL4/'raw data'!AM4) -> 0.066666667 | V3: =IF(ISERROR('raw data'!AN4/'raw data'!AO4),0,'raw data'!AN4/'raw data'!AO4) -> 0.23076923 | W3: =IF(ISERROR('raw data'!AP4/'raw data'!AQ4),0,'raw data'!AP4/'raw data'!AQ4) -> 0.17647059 | X3: =IF(ISERROR('raw data'!AR4/'raw data'!AS4),0,'raw data'!AR4/'raw data'!AS4) -> 0.15384615 | Y3: =IF(ISERROR('raw data'!AT4/'raw data'!AU4),0,'raw data'!AT4/'raw data'!AU4) -> 0.28571429 | Z3: =IF(ISERROR('raw data'!AV4/'raw data'!AW4),0,'raw data'!AV4/'raw data'!AW4) -> 0.31578947 | AA3: =IF(ISERROR('raw data'!AX4/'raw data'!AY4),0,'raw data'!AX4/'raw data'!AY4) -> 0.27272727 | AB3: =IF(ISERROR('raw data'!AZ4/'raw data'!BA4),0,'raw data'!AZ4/'raw data'!BA4) -> 0.3 | AC3: =IF(ISERROR('raw data'!BB4/'raw data'!BC4),0,'raw data'!BB4/'raw data'!BC4) -> 0.15384615 | AD3: =IF(ISERROR('raw data'!BD4/'raw data'!BE4),0,'raw data'!BD4/'raw data'!BE4) -> 0.33333333 | AE3: =IF(ISERROR('raw data'!BF4/'raw data'!BG4),0,'raw data'!BF4/'raw data'!BG4) -> 0.17647059 | AF3: =IF(ISERROR('raw data'!BH4/'raw data'!BI4),0,'raw data'!BH4/'raw data'!BI4) -> 0.375 | AG3: =IF(ISERROR('raw data'!BJ4/'raw data'!BK4),0,'raw data'!BJ4/'raw data'!BK4) -> 0.125 | AH3: =IF(ISERROR('raw data'!BL4/'raw data'!BM4),0,'raw data'!BL4/'raw data'!BM4) -> 0.074074074 | AI3: =IF(ISERROR('raw data'!BN4/'raw data'!BO4),0,'raw data'!BN4/'raw data'!BO4) -> 0.076923077 | AJ3: =IF(ISERROR('raw data'!BP4/'raw data'!BQ4),0,'raw data'!BP4/'raw data'!BQ4) -> 0.18181818 | AK3: =IF(ISERROR('raw data'!BR4/'raw data'!BS4),0,'raw data'!BR4/'raw data'!BS4) -> 0.041666667 | AL3: =IF(ISERROR('raw data'!BT4/'raw data'!BU4),0,'raw data'!BT4/'raw data'!BU4) -> 0.066666667 | AM3: =IF(ISERROR('raw data'!BV4/'raw data'!BW4),0,'raw data'!BV4/'raw data'!BW4) -> 0.25 | AN3: =IF(ISERROR('raw data'!BX4/'raw data'!BY4),0,'raw data'!BX4/'raw data'!BY4) -> 0.17647059 | AO3: =IF(ISERROR('raw data'!BZ4/'raw data'!CA4),0,'raw data'!BZ4/'raw data'!CA4) -> 0.1875 | AP3: =IF(ISERROR('raw data'!CB4/'raw data'!CC4),0,'raw data'!CB4/'raw data'!CC4) -> 0.18181818 | AQ3: =IF(ISERROR('raw data'!CD4/'raw data'!CE4),0,'raw data'!CD4/'raw data'!CE4) -> 0.35294118 | AR3: =IF(ISERROR('raw data'!CF4/'raw data'!CG4),0,'raw data'!CF4/'raw data'!CG4) -> 0 | AS3: =IF(ISERROR('raw data'!CH4/'raw data'!CI4),0,'raw data'!CH4/'raw data'!CI4) -> 0.29411765 | AT3: =IF(ISERROR('raw data'!CJ4/'raw data'!CK4),0,'raw data'!CJ4/'raw data'!CK4) -> 0.2 | AU3: =IF(ISERROR('raw data'!CL4/'raw data'!CM4),0,'raw data'!CL4/'raw data'!CM4) -> 0.29411765 | AV3: =IF(ISERROR('raw data'!CN4/'raw data'!CO4),0,'raw data'!CN4/'raw data'!CO4) -> 0.2 | AW3: =IF(ISERROR('raw data'!CP4/'raw data'!CQ4),0,'raw data'!CP4/'raw data'!CQ4) -> 0.071428571 | AX3: =IF(ISERROR('raw data'!CR4/'raw data'!CS4),0,'raw data'!CR4/'raw data'!CS4) -> 0.15384615 | AY3: =IF(ISERROR('raw data'!CT4/'raw data'!CU4),0,'raw data'!CT4/'raw data'!CU4) -> 0.23529412 | AZ3: =IF(ISERROR('raw data'!CV4/'raw data'!CW4),0,'raw data'!CV4/'raw data'!CW4) -> 0.26086957 | BA3: =IF(ISERROR('raw data'!CX4/'raw data'!CY4),0,'raw data'!CX4/'raw data'!CY4) -> 0.11111111 | BB3: =IF(ISERROR('raw data'!CZ4/'raw data'!DA4),0,'raw data'!CZ4/'raw data'!DA4) -> 0.125 | BC3: =IF(ISERROR('raw data'!DB4/'raw data'!DC4),0,'raw data'!DB4/'raw data'!DC4) -> 0.38461538 | BD3: 0.18181818 | BE3: =IF(ISERROR('raw data'!DF4/'raw data'!DG4),0,'raw data'!DF4/'raw data'!DG4) -> 0.41666667 | BF3: =IF(ISERROR('raw data'!DH4/'raw data'!DI4),0,'raw data'!DH4/'raw data'!DI4) -> 0.23529412 | BG3: =IF(ISERROR('raw data'!DJ4/'raw data'!DK4),0,'raw data'!DJ4/'raw data'!DK4) -> 0.42105263 | BH3: =IF(ISERROR('raw data'!DL4/'raw data'!DM4),0,'raw data'!DL4/'raw data'!DM4) -> 0.35 | BI3: =IF(ISERROR('raw data'!DN4/'raw data'!DO4),0,'raw data'!DN4/'raw data'!DO4) -> 0.15384615 | BJ3: =IF(ISERROR('raw data'!DP4/'raw data'!DQ4),0,'raw data'!DP4/'raw data'!DQ4) -> 0.46666667 | BK3: =IF(ISERROR('raw data'!DR4/'raw data'!DS4),0,'raw data'!DR4/'raw data'!DS4) -> 0.18181818 | BL3: =IF(ISERROR('raw data'!DT4/'raw data'!DU4),0,'raw data'!DT4/'raw data'!DU4) -> 0.23076923 | BM3: =IF(ISERROR('raw data'!DV4/'raw data'!DW4),0,'raw data'!DV4/'raw data'!DW4) -> 0.18181818 | BN3: =IF(ISERROR('raw data'!DX4/'raw data'!DY4),0,'raw data'!DX4/'raw data'!DY4) -> 0 | BO3: =IF(ISERROR('raw data'!DZ4/'raw data'!EA4),0,'raw data'!DZ4/'raw data'!EA4) -> 0.055555556 | BP3: =IF(ISERROR('raw data'!EB4/'raw data'!EC4),0,'raw data'!EB4/'raw data'!EC4) -> 0.2 | BQ3: =IF(ISERROR('raw data'!ED4/'raw data'!EE4),0,'raw data'!ED4/'raw data'!EE4) -> 0.4 | BR3: =IF(ISERROR('raw data'!EF4/'raw data'!EG4),0,'raw data'!EF4/'raw data'!EG4) -> 0.18181818 | BS3: =IF(ISERROR('raw data'!EH4/'raw data'!EI4),0,'raw data'!EH4/'raw data'!EI4) -> 0.18181818 | BT3: =IF(ISERROR('raw data'!EJ4/'raw data'!EK4),0,'raw data'!EJ4/'raw data'!EK4) -> 0.11764706 | BU3: =IF(ISERROR('raw data'!EL4/'raw data'!EM4),0,'raw data'!EL4/'raw data'!EM4) -> 0.18181818 | BV3: =IF(ISERROR('raw data'!EN4/'raw data'!EO4),0,'raw data'!EN4/'raw data'!EO4) -> 0.090909091 | BW3: =IF(ISERROR('raw data'!EP4/'raw data'!EQ4),0,'raw data'!EP4/'raw data'!EQ4) -> 0.18181818 | BX3: =IF(ISERROR('raw data'!ER4/'raw data'!ES4),0,'raw data'!ER4/'raw data'!ES4) -> 0.45454545 | BY3: =IF(ISERROR('raw data'!ET4/'raw data'!EU4),0,'raw data'!ET4/'raw data'!EU4) -> 0.2 | BZ3: =IF(ISERROR('raw data'!EV4/'raw data'!EW4),0,'raw data'!EV4/'raw data'!EW4) -> 0.16666667 | CA3: =IF(ISERROR('raw data'!EX4/'raw data'!EY4),0,'raw data'!EX4/'raw data'!EY4) -> 0.11111111 | CB3: =IF(ISERROR('raw data'!EZ4/'raw data'!FA4),0,'raw data'!EZ4/'raw data'!FA4) -> 0.16666667 | CC3: =IF(ISERROR('raw data'!FB4/'raw data'!FC4),0,'raw data'!FB4/'raw data'!FC4) -> 0.26666667 | CD3: =IF(ISERROR('raw data'!FD4/'raw data'!FE4),0,'raw data'!FD4/'raw data'!FE4) -> 0.083333333 | CE3: =IF(ISERROR('raw data'!FF4/'raw data'!FG4),0,'raw data'!FF4/'raw data'!FG4) -> 0.44444444 | CF3: =IF(ISERROR('raw data'!FH4/'raw data'!FI4),0,'raw data'!FH4/'raw data'!FI4) -> 0.3 | CG3: =IF(ISERROR('raw data'!FJ4/'raw data'!FM4),0,'raw data'!FJ4/'raw data'!FM4) -> 0.125 | CH3: =IF(ISERROR('raw data'!FN4/'raw data'!FO4),0,'raw data'!FN4/'raw data'!FO4) -> 0 | CI3: =IF(ISERROR('raw data'!FP4/'raw data'!FQ4),0,'raw data'!FP4/'raw data'!FQ4) -> 0 | CJ3: =IF(ISERROR('raw data'!FR4/'raw data'!FS4),0,'raw data'!FR4/'raw data'!FS4) -> 0 | CK3: =IF(ISERROR('raw data'!FT4/'raw data'!FU4),0,'raw data'!FT4/'raw data'!FU4) -> 0 | CL3: =IF(ISERROR('raw data'!FV4/'raw data'!FW4),0,'raw data'!FV4/'raw data'!FW4) -> 0.6 | CM3: =IF(ISERROR('raw data'!FX4/'raw data'!FY4),0,'raw data'!FX4/'raw data'!FY4) -> 0 | CN3: =IF(ISERROR('raw data'!FZ4/'raw data'!GA4),0,'raw data'!FZ4/'raw data'!GA4) -> 0 | CO3: =IF(ISERROR('raw data'!GB4/'raw data'!GC4),0,'raw data'!GB4/'raw data'!GC4) -> 0 | CP3: =IF(ISERROR('raw data'!GD4/'raw data'!GE4),0,'raw data'!GD4/'raw data'!GE4) -> 0 | CQ3: =IF(ISERROR('raw data'!GF4/'raw data'!GG4),0,'raw data'!GF4/'raw data'!GG4) -> 0.5 | CR3: =IF(ISERROR('raw data'!GH4/'raw data'!GI4),0,'raw data'!GH4/'raw data'!GI4) -> 0 | CS3: =IF(ISERROR('raw data'!GJ4/'raw data'!GK4),0,'raw data'!GJ4/'raw data'!GK4) -> 0 | CT3: =IF(ISERROR('raw data'!GL4/'raw data'!GM4),0,'raw data'!GL4/'raw data'!GM4) -> 0.33333333 | CU3: =IF(ISERROR('raw data'!GN4/'raw data'!GO4),0,'raw data'!GN4/'raw data'!GO4) -> 0 | CV3: =IF(ISERROR('raw data'!GP4/'raw data'!GQ4),0,'raw data'!GP4/'raw data'!GQ4) -> 0 | CW3: =IF(ISERROR('raw data'!GR4/'raw data'!GS4),0,'raw data'!GR4/'raw data'!GS4) -> 0 | CX3: =IF(ISERROR('raw data'!GT4/'raw data'!GU4),0,'raw data'!GT4/'raw data'!GU4) -> 0 | CY3: =IF(ISERROR('raw data'!GV4/'raw data'!GW4),0,'raw data'!GV4/'raw data'!GW4) -> 0 | CZ3: =IF(ISERROR('raw data'!GX4/'raw data'!GY4),0,'raw data'!GX4/'raw data'!GY4) -> 0 | DA3: =IF(ISERROR('raw data'!GZ4/'raw data'!HA4),0,'raw data'!GZ4/'raw data'!HA4) -> 0 | DB3: =IF(ISERROR('raw data'!HB4/'raw data'!HC4),0,'raw data'!HB4/'raw data'!HC4) -> 1 | DC3: =IF(ISERROR('raw data'!HD4/'raw data'!HE4),0,'raw data'!HD4/'raw data'!HE4) -> 0 | DD3: =IF(ISERROR('raw data'!HF4/'raw data'!HG4),0,'raw data'!HF4/'raw data'!HG4) -> 0 | DE3: =IF(ISERROR('raw data'!HH4/'raw data'!HI4),0,'raw data'!HH4/'raw data'!HI4) -> 0 | DF3: =IF(ISERROR('raw data'!HJ4/'raw data'!HK4),0,'raw data'!HJ4/'raw data'!HK4) -> 0 | DG3: =IF(ISERROR('raw data'!HL4/'raw data'!HM4),0,'raw data'!HL4/'raw data'!HM4) -> 0 | DH3: =IF(ISERROR('raw data'!HN4/'raw data'!HO4),0,'raw data'!HN4/'raw data'!HO4) -> 1 | DI3: =IF(ISERROR('raw data'!HP4/'raw data'!HQ4),0,'raw data'!HP4/'raw data'!HQ4) -> 0 | DJ3: =IF(ISERROR('raw data'!HR4/'raw data'!HS4),0,'raw data'!HR4/'raw data'!HS4) -> 0 | DK3: =IF(ISERROR('raw data'!HT4/'raw data'!HU4),0,'raw data'!HT4/'raw data'!HU4) -> 0 | DL3: =IF(ISERROR('raw data'!HV4/'raw data'!HW4),0,'raw data'!HV4/'raw data'!HW4) -> 0 | DM3: =IF(ISERROR('raw data'!HX4/'raw data'!HY4),0,'raw data'!HX4/'raw data'!HY4) -> 0 | DN3: =IF(ISERROR('raw data'!HZ4/'raw data'!IA4),0,'raw data'!HZ4/'raw data'!IA4) -> 0 | DO3: =IF(ISERROR('raw data'!IB4/'raw data'!IC4),0,'raw data'!IB4/'raw data'!IC4) -> 0 | DP3: =IF(ISERROR('raw data'!ID4/'raw data'!IE4),0,'raw data'!ID4/'raw data'!IE4) -> 0.5 | DQ3: =IF(ISERROR('raw data'!IF4/'raw data'!IG4),0,'raw data'!IF4/'raw data'!IG4) -> 0 | DR3: =IF(ISERROR('raw data'!IH4/'raw data'!II4),0,'raw data'!IH4/'raw data'!II4) -> 0 | DS3: =IF(ISERROR('raw data'!IJ4/'raw data'!IK4),0,'raw data'!IJ4/'raw data'!IK4) -> 0 | DT3: =IF(ISERROR('raw data'!IL4/'raw data'!IM4),0,'raw data'!IL4/'raw data'!IM4) -> 0 | DU3: =IF(ISERROR('raw data'!IN4/'raw data'!IO4),0,'raw data'!IN4/'raw data'!IO4) -> 0 | DV3: =IF(ISERROR('raw data'!IP4/'raw data'!IQ4),0,'raw data'!IP4/'raw data'!IQ4) -> 0 | DW3: =IF(ISERROR('raw data'!IR4/'raw data'!IS4),0,'raw data'!IR4/'raw data'!IS4) -> 0 | DX3: =IF(ISERROR('raw data'!IT4/'raw data'!IU4),0,'raw data'!IT4/'raw data'!IU4) -> 0 | DY3: =IF(ISERROR('raw data'!IV4/'raw data'!IW4),0,'raw data'!IV4/'raw data'!IW4) -> 0 | DZ3: =IF(ISERROR('raw data'!IX4/'raw data'!IY4),0,'raw data'!IX4/'raw data'!IY4) -> 0 | EA3: =IF(ISERROR('raw data'!IZ4/'raw data'!JA4),0,'raw data'!IZ4/'raw data'!JA4) -> 0 | EB3: =IF(ISERROR('raw data'!JB4/'raw data'!JC4),0,'raw data'!JB4/'raw data'!JC4) -> 0 | EC3: =IF(ISERROR('raw data'!JD4/'raw data'!JE4),0,'raw data'!JD4/'raw data'!JE4) -> 0 | EE3: 0 | EF3: 3 | EG3: =IF(ISERROR(EE3/EF3),0,EE3/EF3) -> 0
A4: 1.3 | B4: ='raw data'!B5 -> Flex accounts with large number (7+) of branches used (CR, CQ, WD) and min cash credits of £1k per month. | C4: Flex Accs with >6 branches used | D4: =+'raw data'!D5/'raw data'!E5 -> 0.59259259 | E4: =+'raw data'!F5/'raw data'!G5 -> 0.66666667 | F4: =+'raw data'!H5/'raw data'!I5 -> 0.375 | G4: ='raw data'!J5/'raw data'!K5 -> 0.32142857 | H4: ='raw data'!L5/'raw data'!M5 -> 0.21428571 | I4: ='raw data'!N5/'raw data'!O5 -> 0.37037037 | J4: ='raw data'!P5/'raw data'!Q5 -> 0.25 | K4: ='raw data'!R5/'raw data'!S5 -> 0.26086957 | L4: ='raw data'!T5/'raw data'!U5 -> 0.39473684 | M4: ='raw data'!V5/'raw data'!W5 -> 0.64285714 | N4: ='raw data'!X5/'raw data'!Y5 -> 0.34482759 | O4: =IF(ISERROR('raw data'!Z5/'raw data'!AA5),0,'raw data'!Z5/'raw data'!AA5) -> 0.27027027 | P4: =IF(ISERROR('raw data'!AB5/'raw data'!AC5),0,'raw data'!AB5/'raw data'!AC5) -> 0.25925926 | Q4: =IF(ISERROR('raw data'!AD5/'raw data'!AE5),0,'raw data'!AD5/'raw data'!AE5) -> 0.44444444 | R4: =IF(ISERROR('raw data'!AF5/'raw data'!AG5),0,'raw data'!AF5/'raw data'!AG5) -> 0.61538462 | S4: =IF(ISERROR('raw data'!AH5/'raw data'!AI5),0,'raw data'!AH5/'raw data'!AI5) -> 0.47368421 | T4: =IF(ISERROR('raw data'!AJ5/'raw data'!AK5),0,'raw data'!AJ5/'raw data'!AK5) -> 0.33333333 | U4: =IF(ISERROR('raw data'!AL5/'raw data'!AM5),0,'raw data'!AL5/'raw data'!AM5) -> 0.46666667 | V4: =IF(ISERROR('raw data'!AN5/'raw data'!AO5),0,'raw data'!AN5/'raw data'!AO5) -> 0.4375 | W4: =IF(ISERROR('raw data'!AP5/'raw data'!AQ5),0,'raw data'!AP5/'raw data'!AQ5) -> 0.52380952 | X4: =IF(ISERROR('raw data'!AR5/'raw data'!AS5),0,'raw data'!AR5/'raw data'!AS5) -> 0.5625 | Y4: =IF(ISERROR('raw data'!AT5/'raw data'!AU5),0,'raw data'!AT5/'raw data'!AU5) -> 0.45 | Z4: =IF(ISERROR('raw data'!AV5/'raw data'!AW5),0,'raw data'!AV5/'raw data'!AW5) -> 0.44642857 | AA4: =IF(ISERROR('raw data'!AX5/'raw data'!AY5),0,'raw data'!AX5/'raw data'!AY5) -> 0.52307692 | AB4: =IF(ISERROR('raw data'!AZ5/'raw data'!BA5),0,'raw data'!AZ5/'raw data'!BA5) -> 0.25531915 | AC4: =IF(ISERROR('raw data'!BB5/'raw data'!BC5),0,'raw data'!BB5/'raw data'!BC5) -> 0.55128205 | AD4: =IF(ISERROR('raw data'!BD5/'raw data'!BE5),0,'raw data'!BD5/'raw data'!BE5) -> 0.33898305 | AE4: =IF(ISERROR('raw data'!BF5/'raw data'!BG5),0,'raw data'!BF5/'raw data'!BG5) -> 0.40277778 | AF4: =IF(ISERROR('raw data'!BH5/'raw data'!BI5),0,'raw data'!BH5/'raw data'!BI5) -> 0.36842105 | AG4: =IF(ISERROR('raw data'!BJ5/'raw data'!BK5),0,'raw data'!BJ5/'raw data'!BK5) -> 0.3030303 | AH4: =IF(ISERROR('raw data'!BL5/'raw data'!BM5),0,'raw data'!BL5/'raw data'!BM5) -> 0.32307692 | AI4: =IF(ISERROR('raw data'!BN5/'raw data'!BO5),0,'raw data'!BN5/'raw data'!BO5) -> 0.34020619 | AJ4: =IF(ISERROR('raw data'!BP5/'raw data'!BQ5),0,'raw data'!BP5/'raw data'!BQ5) -> 0.31428571 | AK4: =IF(ISERROR('raw data'!BR5/'raw data'!BS5),0,'raw data'!BR5/'raw data'!BS5) -> 0.34285714 | AL4: =IF(ISERROR('raw data'!BT5/'raw data'!BU5),0,'raw data'!BT5/'raw data'!BU5) -> 0.28421053 | AM4: =IF(ISERROR('raw data'!BV5/'raw data'!BW5),0,'raw data'!BV5/'raw data'!BW5) -> 0.34848485 | AN4: =IF(ISERROR('raw data'!BX5/'raw data'!BY5),0,'raw data'!BX5/'raw data'!BY5) -> 0.42666667 | AO4: =IF(ISERROR('raw data'!BZ5/'raw data'!CA5),0,'raw data'!BZ5/'raw data'!CA5) -> 0.25806452 | AP4: =IF(ISERROR('raw data'!CB5/'raw data'!CC5),0,'raw data'!CB5/'raw data'!CC5) -> 0.30120482 | AQ4: =IF(ISERROR('raw data'!CD5/'raw data'!CE5),0,'raw data'!CD5/'raw data'!CE5) -> 0.45454545 | AR4: =IF(ISERROR('raw data'!CF5/'raw data'!CG5),0,'raw data'!CF5/'raw data'!CG5) -> 0.4 | AS4: =IF(ISERROR('raw data'!CH5/'raw data'!CI5),0,'raw data'!CH5/'raw data'!CI5) -> 0.35064935 | AT4: =IF(ISERROR('raw data'!CJ5/'raw data'!CK5),0,'raw data'!CJ5/'raw data'!CK5) -> 0.31481481 | AU4: =IF(ISERROR('raw data'!CL5/'raw data'!CM5),0,'raw data'!CL5/'raw data'!CM5) -> 0.35714286 | AV4: =IF(ISERROR('raw data'!CN5/'raw data'!CO5),0,'raw data'!CN5/'raw data'!CO5) -> 0.38888889 | AW4: =IF(ISERROR('raw data'!CP5/'raw data'!CQ5),0,'raw data'!CP5/'raw data'!CQ5) -> 0.41 | AX4: =IF(ISERROR('raw data'!CR5/'raw data'!CS5),0,'raw data'!CR5/'raw data'!CS5) -> 0.34782609 | AY4: =IF(ISERROR('raw data'!CT5/'raw data'!CU5),0,'raw data'!CT5/'raw data'!CU5) -> 0.43137255 | AZ4: =IF(ISERROR('raw data'!CV5/'raw data'!CW5),0,'raw data'!CV5/'raw data'!CW5) -> 0.46153846 | BA4: =IF(ISERROR('raw data'!CX5/'raw data'!CY5),0,'raw data'!CX5/'raw data'!CY5) -> 0.55421687 | BB4: =IF(ISERROR('raw data'!CZ5/'raw data'!DA5),0,'raw data'!CZ5/'raw data'!DA5) -> 0.55263158 | BC4: =IF(ISERROR('raw data'!DB5/'raw data'!DC5),0,'raw data'!DB5/'raw data'!DC5) -> 0.48695652 | BD4: 0.55462185 | BE4: =IF(ISERROR('raw data'!DF5/'raw data'!DG5),0,'raw data'!DF5/'raw data'!DG5) -> 0.4787234 | BF4: =IF(ISERROR('raw data'!DH5/'raw data'!DI5),0,'raw data'!DH5/'raw data'!DI5) -> 0.56043956 | BG4: =IF(ISERROR('raw data'!DJ5/'raw data'!DK5),0,'raw data'!DJ5/'raw data'!DK5) -> 0.496 | BH4: =IF(ISERROR('raw data'!DL5/'raw data'!DM5),0,'raw data'!DL5/'raw data'!DM5) -> 0.41538462 | BI4: =IF(ISERROR('raw data'!DN5/'raw data'!DO5),0,'raw data'!DN5/'raw data'!DO5) -> 0.44537815 | BJ4: =IF(ISERROR('raw data'!DP5/'raw data'!DQ5),0,'raw data'!DP5/'raw data'!DQ5) -> 0.51190476 | BK4: =IF(ISERROR('raw data'!DR5/'raw data'!DS5),0,'raw data'!DR5/'raw data'!DS5) -> 0.55844156 | BL4: =IF(ISERROR('raw data'!DT5/'raw data'!DU5),0,'raw data'!DT5/'raw data'!DU5) -> 0.64 | BM4: =IF(ISERROR('raw data'!DV5/'raw data'!DW5),0,'raw data'!DV5/'raw data'!DW5) -> 0.38666667 | BN4: =IF(ISERROR('raw data'!DX5/'raw data'!DY5),0,'raw data'!DX5/'raw data'!DY5) -> 0.36111111 | BO4: =IF(ISERROR('raw data'!DZ5/'raw data'!EA5),0,'raw data'!DZ5/'raw data'!EA5) -> 0.38157895 | BP4: =IF(ISERROR('raw data'!EB5/'raw data'!EC5),0,'raw data'!EB5/'raw data'!EC5) -> 0.55045872 | BQ4: =IF(ISERROR('raw data'!ED5/'raw data'!EE5),0,'raw data'!ED5/'raw data'!EE5) -> 0.45 | BR4: =IF(ISERROR('raw data'!EF5/'raw data'!EG5),0,'raw data'!EF5/'raw data'!EG5) -> 0.3960396 | BS4: =IF(ISERROR('raw data'!EH5/'raw data'!EI5),0,'raw data'!EH5/'raw data'!EI5) -> 0.40659341 | BT4: =IF(ISERROR('raw data'!EJ5/'raw data'!EK5),0,'raw data'!EJ5/'raw data'!EK5) -> 0.48695652 | BU4: =IF(ISERROR('raw data'!EL5/'raw data'!EM5),0,'raw data'!EL5/'raw data'!EM5) -> 0.35051546 | BV4: =IF(ISERROR('raw data'!EN5/'raw data'!EO5),0,'raw data'!EN5/'raw data'!EO5) -> 0.54901961 | BW4: =IF(ISERROR('raw data'!EP5/'raw data'!EQ5),0,'raw data'!EP5/'raw data'!EQ5) -> 0.55660377 | BX4: =IF(ISERROR('raw data'!ER5/'raw data'!ES5),0,'raw data'!ER5/'raw data'!ES5) -> 0.5 | BY4: =IF(ISERROR('raw data'!ET5/'raw data'!EU5),0,'raw data'!ET5/'raw data'!EU5) -> 0.47945205 | BZ4: =IF(ISERROR('raw data'!EV5/'raw data'!EW5),0,'raw data'!EV5/'raw data'!EW5) -> 0.48979592 | CA4: =IF(ISERROR('raw data'!EX5/'raw data'!EY5),0,'raw data'!EX5/'raw data'!EY5) -> 0.47572816 | CB4: =IF(ISERROR('raw data'!EZ5/'raw data'!FA5),0,'raw data'!EZ5/'raw data'!FA5) -> 0.53030303 | CC4: =IF(ISERROR('raw data'!FB5/'raw data'!FC5),0,'raw data'!FB5/'raw data'!FC5) -> 0.46153846 | CD4: =IF(ISERROR('raw data'!FD5/'raw data'!FE5),0,'raw data'!FD5/'raw data'!FE5) -> 0.42424242 | CE4: =IF(ISERROR('raw data'!FF5/'raw data'!FG5),0,'raw data'!FF5/'raw data'!FG5) -> 0.52631579 | CF4: =IF(ISERROR('raw data'!FH5/'raw data'!FI5),0,'raw data'!FH5/'raw data'!FI5) -> 0.44047619 | CG4: =IF(ISERROR('raw data'!FJ5/'raw data'!FM5),0,'raw data'!FJ5/'raw data'!FM5) -> 0.46666667 | CH4: =IF(ISERROR('raw data'!FN5/'raw data'!FO5),0,'raw data'!FN5/'raw data'!FO5) -> 0.3490566 | CI4: =IF(ISERROR('raw data'!FP5/'raw data'!FQ5),0,'raw data'!FP5/'raw data'!FQ5) -> 0.48 | CJ4: =IF(ISERROR('raw data'!FR5/'raw data'!FS5),0,'raw data'!FR5/'raw data'!FS5) -> 0.76470588 | CK4: =IF(ISERROR('raw data'!FT5/'raw data'!FU5),0,'raw data'!FT5/'raw data'!FU5) -> 0.38461538 | CL4: =IF(ISERROR('raw data'!FV5/'raw data'!FW5),0,'raw data'!FV5/'raw data'!FW5) -> 0.25 | CM4: =IF(ISERROR('raw data'!FX5/'raw data'!FY5),0,'raw data'!FX5/'raw data'!FY5) -> 0.33333333 | CN4: =IF(ISERROR('raw data'!FZ5/'raw data'!GA5),0,'raw data'!FZ5/'raw data'!GA5) -> 0.66666667 | CO4: =IF(ISERROR('raw data'!GB5/'raw data'!GC5),0,'raw data'!GB5/'raw data'!GC5) -> 0 | CP4: =IF(ISERROR('raw data'!GD5/'raw data'!GE5),0,'raw data'!GD5/'raw data'!GE5) -> 0 | CQ4: =IF(ISERROR('raw data'!GF5/'raw data'!GG5),0,'raw data'!GF5/'raw data'!GG5) -> 0 | CR4: =IF(ISERROR('raw data'!GH5/'raw data'!GI5),0,'raw data'!GH5/'raw data'!GI5) -> 0 | CS4: =IF(ISERROR('raw data'!GJ5/'raw data'!GK5),0,'raw data'!GJ5/'raw data'!GK5) -> 0.5 | CT4: =IF(ISERROR('raw data'!GL5/'raw data'!GM5),0,'raw data'!GL5/'raw data'!GM5) -> 0 | CU4: =IF(ISERROR('raw data'!GN5/'raw data'!GO5),0,'raw data'!GN5/'raw data'!GO5) -> 0.2 | CV4: =IF(ISERROR('raw data'!GP5/'raw data'!GQ5),0,'raw data'!GP5/'raw data'!GQ5) -> 0.5 | CW4: =IF(ISERROR('raw data'!GR5/'raw data'!GS5),0,'raw data'!GR5/'raw data'!GS5) -> 0 | CX4: =IF(ISERROR('raw data'!GT5/'raw data'!GU5),0,'raw data'!GT5/'raw data'!GU5) -> 0 | CY4: =IF(ISERROR('raw data'!GV5/'raw data'!GW5),0,'raw data'!GV5/'raw data'!GW5) -> 0.5 | CZ4: =IF(ISERROR('raw data'!GX5/'raw data'!GY5),0,'raw data'!GX5/'raw data'!GY5) -> 0 | DA4: =IF(ISERROR('raw data'!GZ5/'raw data'!HA5),0,'raw data'!GZ5/'raw data'!HA5) -> 0 | DB4: =IF(ISERROR('raw data'!HB5/'raw data'!HC5),0,'raw data'!HB5/'raw data'!HC5) -> 1 | DC4: =IF(ISERROR('raw data'!HD5/'raw data'!HE5),0,'raw data'!HD5/'raw data'!HE5) -> 0 | DD4: =IF(ISERROR('raw data'!HF5/'raw data'!HG5),0,'raw data'!HF5/'raw data'!HG5) -> 0 | DE4: =IF(ISERROR('raw data'!HH5/'raw data'!HI5),0,'raw data'!HH5/'raw data'!HI5) -> 0 | DF4: =IF(ISERROR('raw data'!HJ5/'raw data'!HK5),0,'raw data'!HJ5/'raw data'!HK5) -> 0.25 | DG4: =IF(ISERROR('raw data'!HL5/'raw data'!HM5),0,'raw data'!HL5/'raw data'!HM5) -> 0 | DH4: =IF(ISERROR('raw data'!HN5/'raw data'!HO5),0,'raw data'!HN5/'raw data'!HO5) -> 0 | DI4: =IF(ISERROR('raw data'!HP5/'raw data'!HQ5),0,'raw data'!HP5/'raw data'!HQ5) -> 0.25 | DJ4: =IF(ISERROR('raw data'!HR5/'raw data'!HS5),0,'raw data'!HR5/'raw data'!HS5) -> 0 | DK4: =IF(ISERROR('raw data'!HT5/'raw data'!HU5),0,'raw data'!HT5/'raw data'!HU5) -> 1 | DL4: =IF(ISERROR('raw data'!HV5/'raw data'!HW5),0,'raw data'!HV5/'raw data'!HW5) -> 0 | DM4: =IF(ISERROR('raw data'!HX5/'raw data'!HY5),0,'raw data'!HX5/'raw data'!HY5) -> 0 | DN4: =IF(ISERROR('raw data'!HZ5/'raw data'!IA5),0,'raw data'!HZ5/'raw data'!IA5) -> 0 | DO4: =IF(ISERROR('raw data'!IB5/'raw data'!IC5),0,'raw data'!IB5/'raw data'!IC5) -> 0 | DP4: =IF(ISERROR('raw data'!ID5/'raw data'!IE5),0,'raw data'!ID5/'raw data'!IE5) -> 0 | DQ4: =IF(ISERROR('raw data'!IF5/'raw data'!IG5),0,'raw data'!IF5/'raw data'!IG5) -> 0 | DR4: =IF(ISERROR('raw data'!IH5/'raw data'!II5),0,'raw data'!IH5/'raw data'!II5) -> 0 | DS4: =IF(ISERROR('raw data'!IJ5/'raw data'!IK5),0,'raw data'!IJ5/'raw data'!IK5) -> 0 | DT4: =IF(ISERROR('raw data'!IL5/'raw data'!IM5),0,'raw data'!IL5/'raw data'!IM5) -> 0 | DU4: =IF(ISERROR('raw data'!IN5/'raw data'!IO5),0,'raw data'!IN5/'raw data'!IO5) -> 0 | DV4: =IF(ISERROR('raw data'!IP5/'raw data'!IQ5),0,'raw data'!IP5/'raw data'!IQ5) -> 0 | DW4: =IF(ISERROR('raw data'!IR5/'raw data'!IS5),0,'raw data'!IR5/'raw data'!IS5) -> 0 | DX4: =IF(ISERROR('raw data'!IT5/'raw data'!IU5),0,'raw data'!IT5/'raw data'!IU5) -> 0 | DY4: =IF(ISERROR('raw data'!IV5/'raw data'!IW5),0,'raw data'!IV5/'raw data'!IW5) -> 0 | DZ4: =IF(ISERROR('raw data'!IX5/'raw data'!IY5),0,'raw data'!IX5/'raw data'!IY5) -> 0 | EA4: =IF(ISERROR('raw data'!IZ5/'raw data'!JA5),0,'raw data'!IZ5/'raw data'!JA5) -> 0 | EB4: =IF(ISERROR('raw data'!JB5/'raw data'!JC5),0,'raw data'!JB5/'raw data'!JC5) -> 0 | EC4: =IF(ISERROR('raw data'!JD5/'raw data'!JE5),0,'raw data'!JD5/'raw data'!JE5) -> 0 | EE4: 0 | EF4: 0 | EG4: =IF(ISERROR(EE4/EF4),0,EE4/EF4) -> 0
A5: 1.4 | B5: ='raw data'!B6 -> Savings accounts with large number (7+) of branches used (CR, CQ, WD) and min cash credits of £1k per month. | C5: Save Accs with >6 branches used | D5: =+'raw data'!D6/'raw data'!E6 -> 0.3 | E5: =+'raw data'!F6/'raw data'!G6 -> 0.375 | F5: =+'raw data'!H6/'raw data'!I6 -> 0 | G5: ='raw data'!J6/'raw data'!K6 -> 0.29411765 | H5: ='raw data'!L6/'raw data'!M6 -> 0.125 | I5: ='raw data'!N6/'raw data'!O6 -> 0.375 | J5: ='raw data'!P6/'raw data'!Q6 -> 0 | K5: ='raw data'!R6/'raw data'!S6 -> 0.15384615 | L5: ='raw data'!T6/'raw data'!U6 -> 0.3 | M5: ='raw data'!V6/'raw data'!W6 -> 0.33333333 | N5: ='raw data'!X6/'raw data'!Y6 -> 0.33333333 | O5: =IF(ISERROR('raw data'!Z6/'raw data'!AA6),0,'raw data'!Z6/'raw data'!AA6) -> 0.3 | P5: =IF(ISERROR('raw data'!AB6/'raw data'!AC6),0,'raw data'!AB6/'raw data'!AC6) -> 0.42857143 | Q5: =IF(ISERROR('raw data'!AD6/'raw data'!AE6),0,'raw data'!AD6/'raw data'!AE6) -> 0.25 | R5: =IF(ISERROR('raw data'!AF6/'raw data'!AG6),0,'raw data'!AF6/'raw data'!AG6) -> 0.4 | S5: =IF(ISERROR('raw data'!AH6/'raw data'!AI6),0,'raw data'!AH6/'raw data'!AI6) -> 0.66666667 | T5: =IF(ISERROR('raw data'!AJ6/'raw data'!AK6),0,'raw data'!AJ6/'raw data'!AK6) -> 0.4 | U5: =IF(ISERROR('raw data'!AL6/'raw data'!AM6),0,'raw data'!AL6/'raw data'!AM6) -> 0.28571429 | V5: =IF(ISERROR('raw data'!AN6/'raw data'!AO6),0,'raw data'!AN6/'raw data'!AO6) -> 0.25 | W5: =IF(ISERROR('raw data'!AP6/'raw data'!AQ6),0,'raw data'!AP6/'raw data'!AQ6) -> 0.28571429 | X5: =IF(ISERROR('raw data'!AR6/'raw data'!AS6),0,'raw data'!AR6/'raw data'!AS6) -> 0 | Y5: =IF(ISERROR('raw data'!AT6/'raw data'!AU6),0,'raw data'!AT6/'raw data'!AU6) -> 0.31578947 | Z5: =IF(ISERROR('raw data'!AV6/'raw data'!AW6),0,'raw data'!AV6/'raw data'!AW6) -> 0.31818182 | AA5: =IF(ISERROR('raw data'!AX6/'raw data'!AY6),0,'raw data'!AX6/'raw data'!AY6) -> 0.2 | AB5: =IF(ISERROR('raw data'!AZ6/'raw data'!BA6),0,'raw data'!AZ6/'raw data'!BA6) -> 0.12 | AC5: =IF(ISERROR('raw data'!BB6/'raw data'!BC6),0,'raw data'!BB6/'raw data'!BC6) -> 0.17142857 | AD5: =IF(ISERROR('raw data'!BD6/'raw data'!BE6),0,'raw data'!BD6/'raw data'!BE6) -> 0.26666667 | AE5: =IF(ISERROR('raw data'!BF6/'raw data'!BG6),0,'raw data'!BF6/'raw data'!BG6) -> 0.10638298 | AF5: =IF(ISERROR('raw data'!BH6/'raw data'!BI6),0,'raw data'!BH6/'raw data'!BI6) -> 0.033333333 | AG5: =IF(ISERROR('raw data'!BJ6/'raw data'!BK6),0,'raw data'!BJ6/'raw data'!BK6) -> 0.0625 | AH5: =IF(ISERROR('raw data'!BL6/'raw data'!BM6),0,'raw data'!BL6/'raw data'!BM6) -> 0.085714286 | AI5: =IF(ISERROR('raw data'!BN6/'raw data'!BO6),0,'raw data'!BN6/'raw data'!BO6) -> 0.18421053 | AJ5: =IF(ISERROR('raw data'!BP6/'raw data'!BQ6),0,'raw data'!BP6/'raw data'!BQ6) -> 0.20689655 | AK5: =IF(ISERROR('raw data'!BR6/'raw data'!BS6),0,'raw data'!BR6/'raw data'!BS6) -> 0.14285714 | AL5: =IF(ISERROR('raw data'!BT6/'raw data'!BU6),0,'raw data'!BT6/'raw data'!BU6) -> 0.175 | AM5: =IF(ISERROR('raw data'!BV6/'raw data'!BW6),0,'raw data'!BV6/'raw data'!BW6) -> 0.15151515 | AN5: =IF(ISERROR('raw data'!BX6/'raw data'!BY6),0,'raw data'!BX6/'raw data'!BY6) -> 0.24324324 | AO5: =IF(ISERROR('raw data'!BZ6/'raw data'!CA6),0,'raw data'!BZ6/'raw data'!CA6) -> 0.18181818 | AP5: =IF(ISERROR('raw data'!CB6/'raw data'!CC6),0,'raw data'!CB6/'raw data'!CC6) -> 0.25925926 | AQ5: =IF(ISERROR('raw data'!CD6/'raw data'!CE6),0,'raw data'!CD6/'raw data'!CE6) -> 0.21052632 | AR5: =IF(ISERROR('raw data'!CF6/'raw data'!CG6),0,'raw data'!CF6/'raw data'!CG6) -> 0.3030303 | AS5: =IF(ISERROR('raw data'!CH6/'raw data'!CI6),0,'raw data'!CH6/'raw data'!CI6) -> 0.22222222 | AT5: =IF(ISERROR('raw data'!CJ6/'raw data'!CK6),0,'raw data'!CJ6/'raw data'!CK6) -> 0.083333333 | AU5: =IF(ISERROR('raw data'!CL6/'raw data'!CM6),0,'raw data'!CL6/'raw data'!CM6) -> 0.35849057 | AV5: =IF(ISERROR('raw data'!CN6/'raw data'!CO6),0,'raw data'!CN6/'raw data'!CO6) -> 0.3 | AW5: =IF(ISERROR('raw data'!CP6/'raw data'!CQ6),0,'raw data'!CP6/'raw data'!CQ6) -> 0.20588235 | AX5: =IF(ISERROR('raw data'!CR6/'raw data'!CS6),0,'raw data'!CR6/'raw data'!CS6) -> 0.097560976 | AY5: =IF(ISERROR('raw data'!CT6/'raw data'!CU6),0,'raw data'!CT6/'raw data'!CU6) -> 0.36111111 | AZ5: =IF(ISERROR('raw data'!CV6/'raw data'!CW6),0,'raw data'!CV6/'raw data'!CW6) -> 0.11428571 | BA5: =IF(ISERROR('raw data'!CX6/'raw data'!CY6),0,'raw data'!CX6/'raw data'!CY6) -> 0.29268293 | BB5: =IF(ISERROR('raw data'!CZ6/'raw data'!DA6),0,'raw data'!CZ6/'raw data'!DA6) -> 0.36363636 | BC5: =IF(ISERROR('raw data'!DB6/'raw data'!DC6),0,'raw data'!DB6/'raw data'!DC6) -> 0.30434783 | BD5: 0.17857143 | BE5: =IF(ISERROR('raw data'!DF6/'raw data'!DG6),0,'raw data'!DF6/'raw data'!DG6) -> 0.26315789 | BF5: =IF(ISERROR('raw data'!DH6/'raw data'!DI6),0,'raw data'!DH6/'raw data'!DI6) -> 0.28947368 | BG5: =IF(ISERROR('raw data'!DJ6/'raw data'!DK6),0,'raw data'!DJ6/'raw data'!DK6) -> 0.33333333 | BH5: =IF(ISERROR('raw data'!DL6/'raw data'!DM6),0,'raw data'!DL6/'raw data'!DM6) -> 0.30232558 | BI5: =IF(ISERROR('raw data'!DN6/'raw data'!DO6),0,'raw data'!DN6/'raw data'!DO6) -> 0.27906977 | BJ5: =IF(ISERROR('raw data'!DP6/'raw data'!DQ6),0,'raw data'!DP6/'raw data'!DQ6) -> 0.26470588 | BK5: =IF(ISERROR('raw data'!DR6/'raw data'!DS6),0,'raw data'!DR6/'raw data'!DS6) -> 0.22857143 | BL5: =IF(ISERROR('raw data'!DT6/'raw data'!DU6),0,'raw data'!DT6/'raw data'!DU6) -> 0.25 | BM5: =IF(ISERROR('raw data'!DV6/'raw data'!DW6),0,'raw data'!DV6/'raw data'!DW6) -> 0.26666667 | BN5: =IF(ISERROR('raw data'!DX6/'raw data'!DY6),0,'raw data'!DX6/'raw data'!DY6) -> 0.15625 | BO5: =IF(ISERROR('raw data'!DZ6/'raw data'!EA6),0,'raw data'!DZ6/'raw data'!EA6) -> 0.26666667 | BP5: =IF(ISERROR('raw data'!EB6/'raw data'!EC6),0,'raw data'!EB6/'raw data'!EC6) -> 0.2 | BQ5: =IF(ISERROR('raw data'!ED6/'raw data'!EE6),0,'raw data'!ED6/'raw data'!EE6) -> 0.18181818 | BR5: =IF(ISERROR('raw data'!EF6/'raw data'!EG6),0,'raw data'!EF6/'raw data'!EG6) -> 0.10810811 | BS5: =IF(ISERROR('raw data'!EH6/'raw data'!EI6),0,'raw data'!EH6/'raw data'!EI6) -> 0.16666667 | BT5: =IF(ISERROR('raw data'!EJ6/'raw data'!EK6),0,'raw data'!EJ6/'raw data'!EK6) -> 0.1875 | BU5: =IF(ISERROR('raw data'!EL6/'raw data'!EM6),0,'raw data'!EL6/'raw data'!EM6) -> 0.25714286 | BV5: =IF(ISERROR('raw data'!EN6/'raw data'!EO6),0,'raw data'!EN6/'raw data'!EO6) -> 0.096774194 | BW5: =IF(ISERROR('raw data'!EP6/'raw data'!EQ6),0,'raw data'!EP6/'raw data'!EQ6) -> 0.22727273 | BX5: =IF(ISERROR('raw data'!ER6/'raw data'!ES6),0,'raw data'!ER6/'raw data'!ES6) -> 0.47368421 | BY5: =IF(ISERROR('raw data'!ET6/'raw data'!EU6),0,'raw data'!ET6/'raw data'!EU6) -> 0.28 | BZ5: =IF(ISERROR('raw data'!EV6/'raw data'!EW6),0,'raw data'!EV6/'raw data'!EW6) -> 0.057142857 | CA5: =IF(ISERROR('raw data'!EX6/'raw data'!EY6),0,'raw data'!EX6/'raw data'!EY6) -> 0.22222222 | CB5: =IF(ISERROR('raw data'!EZ6/'raw data'!FA6),0,'raw data'!EZ6/'raw data'!FA6) -> 0.17241379 | CC5: =IF(ISERROR('raw data'!FB6/'raw data'!FC6),0,'raw data'!FB6/'raw data'!FC6) -> 0.32142857 | CD5: =IF(ISERROR('raw data'!FD6/'raw data'!FE6),0,'raw data'!FD6/'raw data'!FE6) -> 0.060606061 | CE5: =IF(ISERROR('raw data'!FF6/'raw data'!FG6),0,'raw data'!FF6/'raw data'!FG6) -> 0.27659574 | CF5: =IF(ISERROR('raw data'!FH6/'raw data'!FI6),0,'raw data'!FH6/'raw data'!FI6) -> 0.13513514 | CG5: =IF(ISERROR('raw data'!FJ6/'raw data'!FM6),0,'raw data'!FJ6/'raw data'!FM6) -> 0.052631579 | CH5: =IF(ISERROR('raw data'!FN6/'raw data'!FO6),0,'raw data'!FN6/'raw data'!FO6) -> 0.083333333 | CI5: =IF(ISERROR('raw data'!FP6/'raw data'!FQ6),0,'raw data'!FP6/'raw data'!FQ6) -> 0.27272727 | CJ5: =IF(ISERROR('raw data'!FR6/'raw data'!FS6),0,'raw data'!FR6/'raw data'!FS6) -> 0.19047619 | CK5: =IF(ISERROR('raw data'!FT6/'raw data'!FU6),0,'raw data'!FT6/'raw data'!FU6) -> 0.03125 | CL5: =IF(ISERROR('raw data'!FV6/'raw data'!FW6),0,'raw data'!FV6/'raw data'!FW6) -> 0.11764706 | CM5: =IF(ISERROR('raw data'!FX6/'raw data'!FY6),0,'raw data'!FX6/'raw data'!FY6) -> 0.15 | CN5: =IF(ISERROR('raw data'!FZ6/'raw data'!GA6),0,'raw data'!FZ6/'raw data'!GA6) -> 0.1 | CO5: =IF(ISERROR('raw data'!GB6/'raw data'!GC6),0,'raw data'!GB6/'raw data'!GC6) -> 0.1 | CP5: =IF(ISERROR('raw data'!GD6/'raw data'!GE6),0,'raw data'!GD6/'raw data'!GE6) -> 0.27777778 | CQ5: =IF(ISERROR('raw data'!GF6/'raw data'!GG6),0,'raw data'!GF6/'raw data'!GG6) -> 0.15 | CR5: =IF(ISERROR('raw data'!GH6/'raw data'!GI6),0,'raw data'!GH6/'raw data'!GI6) -> 0.26666667 | CS5: =IF(ISERROR('raw data'!GJ6/'raw data'!GK6),0,'raw data'!GJ6/'raw data'!GK6) -> 0 | CT5: =IF(ISERROR('raw data'!GL6/'raw data'!GM6),0,'raw data'!GL6/'raw data'!GM6) -> 0.3125 | CU5: =IF(ISERROR('raw data'!GN6/'raw data'!GO6),0,'raw data'!GN6/'raw data'!GO6) -> 0.0625 | CV5: =IF(ISERROR('raw data'!GP6/'raw data'!GQ6),0,'raw data'!GP6/'raw data'!GQ6) -> 0 | CW5: =IF(ISERROR('raw data'!GR6/'raw data'!GS6),0,'raw data'!GR6/'raw data'!GS6) -> 0.2 | CX5: =IF(ISERROR('raw data'!GT6/'raw data'!GU6),0,'raw data'!GT6/'raw data'!GU6) -> 0 | CY5: =IF(ISERROR('raw data'!GV6/'raw data'!GW6),0,'raw data'!GV6/'raw data'!GW6) -> 0.18181818 | CZ5: =IF(ISERROR('raw data'!GX6/'raw data'!GY6),0,'raw data'!GX6/'raw data'!GY6) -> 0.11111111 | DA5: =IF(ISERROR('raw data'!GZ6/'raw data'!HA6),0,'raw data'!GZ6/'raw data'!HA6) -> 0.11111111 | DB5: =IF(ISERROR('raw data'!HB6/'raw data'!HC6),0,'raw data'!HB6/'raw data'!HC6) -> 0.15384615 | DC5: =IF(ISERROR('raw data'!HD6/'raw data'!HE6),0,'raw data'!HD6/'raw data'!HE6) -> 0.1875 | DD5: =IF(ISERROR('raw data'!HF6/'raw data'!HG6),0,'raw data'!HF6/'raw data'!HG6) -> 0.066666667 | DE5: =IF(ISERROR('raw data'!HH6/'raw data'!HI6),0,'raw data'!HH6/'raw data'!HI6) -> 0 | DF5: =IF(ISERROR('raw data'!HJ6/'raw data'!HK6),0,'raw data'!HJ6/'raw data'!HK6) -> 0.18181818 | DG5: =IF(ISERROR('raw data'!HL6/'raw data'!HM6),0,'raw data'!HL6/'raw data'!HM6) -> 0 | DH5: =IF(ISERROR('raw data'!HN6/'raw data'!HO6),0,'raw data'!HN6/'raw data'!HO6) -> 0 | DI5: =IF(ISERROR('raw data'!HP6/'raw data'!HQ6),0,'raw data'!HP6/'raw data'!HQ6) -> 0 | DJ5: =IF(ISERROR('raw data'!HR6/'raw data'!HS6),0,'raw data'!HR6/'raw data'!HS6) -> 0.16666667 | DK5: =IF(ISERROR('raw data'!HT6/'raw data'!HU6),0,'raw data'!HT6/'raw data'!HU6) -> 0 | DL5: =IF(ISERROR('raw data'!HV6/'raw data'!HW6),0,'raw data'!HV6/'raw data'!HW6) -> 0 | DM5: =IF(ISERROR('raw data'!HX6/'raw data'!HY6),0,'raw data'!HX6/'raw data'!HY6) -> 0 | DN5: =IF(ISERROR('raw data'!HZ6/'raw data'!IA6),0,'raw data'!HZ6/'raw data'!IA6) -> 0 | DO5: =IF(ISERROR('raw data'!IB6/'raw data'!IC6),0,'raw data'!IB6/'raw data'!IC6) -> 0 | DP5: =IF(ISERROR('raw data'!ID6/'raw data'!IE6),0,'raw data'!ID6/'raw data'!IE6) -> 1 | DQ5: =IF(ISERROR('raw data'!IF6/'raw data'!IG6),0,'raw data'!IF6/'raw data'!IG6) -> 1 | DR5: =IF(ISERROR('raw data'!IH6/'raw data'!II6),0,'raw data'!IH6/'raw data'!II6) -> 0 | DS5: =IF(ISERROR('raw data'!IJ6/'raw data'!IK6),0,'raw data'!IJ6/'raw data'!IK6) -> 0 | DT5: =IF(ISERROR('raw data'!IL6/'raw data'!IM6),0,'raw data'!IL6/'raw data'!IM6) -> 0 | DU5: =IF(ISERROR('raw data'!IN6/'raw data'!IO6),0,'raw data'!IN6/'raw data'!IO6) -> 0 | DV5: =IF(ISERROR('raw data'!IP6/'raw data'!IQ6),0,'raw data'!IP6/'raw data'!IQ6) -> 0 | DW5: =IF(ISERROR('raw data'!IR6/'raw data'!IS6),0,'raw data'!IR6/'raw data'!IS6) -> 1 | DX5: =IF(ISERROR('raw data'!IT6/'raw data'!IU6),0,'raw data'!IT6/'raw data'!IU6) -> 0 | DY5: =IF(ISERROR('raw data'!IV6/'raw data'!IW6),0,'raw data'!IV6/'raw data'!IW6) -> 0.33333333 | DZ5: =IF(ISERROR('raw data'!IX6/'raw data'!IY6),0,'raw data'!IX6/'raw data'!IY6) -> 0 | EA5: =IF(ISERROR('raw data'!IZ6/'raw data'!JA6),0,'raw data'!IZ6/'raw data'!JA6) -> 0 | EB5: =IF(ISERROR('raw data'!JB6/'raw data'!JC6),0,'raw data'!JB6/'raw data'!JC6) -> 0 | EC5: =IF(ISERROR('raw data'!JD6/'raw data'!JE6),0,'raw data'!JD6/'raw data'!JE6) -> 0 | EE5: 2 | EF5: 11 | EG5: =IF(ISERROR(EE5/EF5),0,EE5/EF5) -> 0.18181818
A6: 1.5 | B6: ='raw data'!B7 -> Flex accounts with >=5 £3k+ credits (CR,CQ) and >=4 £3k+ withdrawals (W4,WR) last month. | C6: Accounts with >=5 £3K+ Credits per Month with >=4 £3K+ withdrawal | D6: =+'raw data'!D7/'raw data'!E7 -> 0.27272727 | E6: =+'raw data'!F7/'raw data'!G7 -> 0.5 | F6: =+'raw data'!H7/'raw data'!I7 -> 0.33333333 | G6: ='raw data'!J7/'raw data'!K7 -> 0.21428571 | H6: ='raw data'!L7/'raw data'!M7 -> 0.4 | I6: ='raw data'!N7/'raw data'!O7 -> 0.090909091 | J6: ='raw data'!P7/'raw data'!Q7 -> 0 | K6: ='raw data'!R7/'raw data'!S7 -> 0 | L6: ='raw data'!T7/'raw data'!U7 -> 0.23076923 | M6: ='raw data'!V7/'raw data'!W7 -> 0.14285714 | N6: ='raw data'!X7/'raw data'!Y7 -> 0.071428571 | O6: =IF(ISERROR('raw data'!Z7/'raw data'!AA7),0,'raw data'!Z7/'raw data'!AA7) -> 0.33333333 | P6: =IF(ISERROR('raw data'!AB7/'raw data'!AC7),0,'raw data'!AB7/'raw data'!AC7) -> 0.090909091 | Q6: =IF(ISERROR('raw data'!AD7/'raw data'!AE7),0,'raw data'!AD7/'raw data'!AE7) -> 0 | R6: =IF(ISERROR('raw data'!AF7/'raw data'!AG7),0,'raw data'!AF7/'raw data'!AG7) -> 0 | S6: =IF(ISERROR('raw data'!AH7/'raw data'!AI7),0,'raw data'!AH7/'raw data'!AI7) -> 0 | T6: =IF(ISERROR('raw data'!AJ7/'raw data'!AK7),0,'raw data'!AJ7/'raw data'!AK7) -> 0 | U6: =IF(ISERROR('raw data'!AL7/'raw data'!AM7),0,'raw data'!AL7/'raw data'!AM7) -> 0 | V6: =IF(ISERROR('raw data'!AN7/'raw data'!AO7),0,'raw data'!AN7/'raw data'!AO7) -> 0 | W6: =IF(ISERROR('raw data'!AP7/'raw data'!AQ7),0,'raw data'!AP7/'raw data'!AQ7) -> 0 | X6: =IF(ISERROR('raw data'!AR7/'raw data'!AS7),0,'raw data'!AR7/'raw data'!AS7) -> 0.14285714 | Y6: =IF(ISERROR('raw data'!AT7/'raw data'!AU7),0,'raw data'!AT7/'raw data'!AU7) -> 0.125 | Z6: =IF(ISERROR('raw data'!AV7/'raw data'!AW7),0,'raw data'!AV7/'raw data'!AW7) -> 0.18181818 | AA6: =IF(ISERROR('raw data'!AX7/'raw data'!AY7),0,'raw data'!AX7/'raw data'!AY7) -> 0.33333333 | AB6: =IF(ISERROR('raw data'!AZ7/'raw data'!BA7),0,'raw data'!AZ7/'raw data'!BA7) -> 0 | AC6: =IF(ISERROR('raw data'!BB7/'raw data'!BC7),0,'raw data'!BB7/'raw data'!BC7) -> 0 | AD6: =IF(ISERROR('raw data'!BD7/'raw data'!BE7),0,'raw data'!BD7/'raw data'!BE7) -> 1 | AE6: =IF(ISERROR('raw data'!BF7/'raw data'!BG7),0,'raw data'!BF7/'raw data'!BG7) -> 0 | AF6: =IF(ISERROR('raw data'!BH7/'raw data'!BI7),0,'raw data'!BH7/'raw data'!BI7) -> 0 | AG6: =IF(ISERROR('raw data'!BJ7/'raw data'!BK7),0,'raw data'!BJ7/'raw data'!BK7) -> 0 | AH6: =IF(ISERROR('raw data'!BL7/'raw data'!BM7),0,'raw data'!BL7/'raw data'!BM7) -> 0.16666667 | AI6: =IF(ISERROR('raw data'!BN7/'raw data'!BO7),0,'raw data'!BN7/'raw data'!BO7) -> 0.14285714 | AJ6: =IF(ISERROR('raw data'!BP7/'raw data'!BQ7),0,'raw data'!BP7/'raw data'!BQ7) -> 0 | AK6: =IF(ISERROR('raw data'!BR7/'raw data'!BS7),0,'raw data'!BR7/'raw data'!BS7) -> 0 | AL6: =IF(ISERROR('raw data'!BT7/'raw data'!BU7),0,'raw data'!BT7/'raw data'!BU7) -> 0.22222222 | AM6: =IF(ISERROR('raw data'!BV7/'raw data'!BW7),0,'raw data'!BV7/'raw data'!BW7) -> 0 | AN6: =IF(ISERROR('raw data'!BX7/'raw data'!BY7),0,'raw data'!BX7/'raw data'!BY7) -> 0.25 | AO6: =IF(ISERROR('raw data'!BZ7/'raw data'!CA7),0,'raw data'!BZ7/'raw data'!CA7) -> 0 | AP6: =IF(ISERROR('raw data'!CB7/'raw data'!CC7),0,'raw data'!CB7/'raw data'!CC7) -> 0.5 | AQ6: =IF(ISERROR('raw data'!CD7/'raw data'!CE7),0,'raw data'!CD7/'raw data'!CE7) -> 0.33333333 | AR6: =IF(ISERROR('raw data'!CF7/'raw data'!CG7),0,'raw data'!CF7/'raw data'!CG7) -> 0 | AS6: =IF(ISERROR('raw data'!CH7/'raw data'!CI7),0,'raw data'!CH7/'raw data'!CI7) -> 0 | AT6: =IF(ISERROR('raw data'!CJ7/'raw data'!CK7),0,'raw data'!CJ7/'raw data'!CK7) -> 0.2 | AU6: =IF(ISERROR('raw data'!CL7/'raw data'!CM7),0,'raw data'!CL7/'raw data'!CM7) -> 0.2 | AV6: =IF(ISERROR('raw data'!CN7/'raw data'!CO7),0,'raw data'!CN7/'raw data'!CO7) -> 0.11111111 | AW6: =IF(ISERROR('raw data'!CP7/'raw data'!CQ7),0,'raw data'!CP7/'raw data'!CQ7) -> 0 | AX6: =IF(ISERROR('raw data'!CR7/'raw data'!CS7),0,'raw data'!CR7/'raw data'!CS7) -> 0.5 | AY6: =IF(ISERROR('raw data'!CT7/'raw data'!CU7),0,'raw data'!CT7/'raw data'!CU7) -> 0 | AZ6: =IF(ISERROR('raw data'!CV7/'raw data'!CW7),0,'raw data'!CV7/'raw data'!CW7) -> 0 | BA6: =IF(ISERROR('raw data'!CX7/'raw data'!CY7),0,'raw data'!CX7/'raw data'!CY7) -> 0.2 | BB6: =IF(ISERROR('raw data'!CZ7/'raw data'!DA7),0,'raw data'!CZ7/'raw data'!DA7) -> 0 | BC6: =IF(ISERROR('raw data'!DB7/'raw data'!DC7),0,'raw data'!DB7/'raw data'!DC7) -> 0.2 | BD6: 0 | BE6: =IF(ISERROR('raw data'!DF7/'raw data'!DG7),0,'raw data'!DF7/'raw data'!DG7) -> 0.33333333 | BF6: =IF(ISERROR('raw data'!DH7/'raw data'!DI7),0,'raw data'!DH7/'raw data'!DI7) -> 0.16666667 | BG6: =IF(ISERROR('raw data'!DJ7/'raw data'!DK7),0,'raw data'!DJ7/'raw data'!DK7) -> 0 | BH6: =IF(ISERROR('raw data'!DL7/'raw data'!DM7),0,'raw data'!DL7/'raw data'!DM7) -> 0.28571429 | BI6: =IF(ISERROR('raw data'!DN7/'raw data'!DO7),0,'raw data'!DN7/'raw data'!DO7) -> 0 | BJ6: =IF(ISERROR('raw data'!DP7/'raw data'!DQ7),0,'raw data'!DP7/'raw data'!DQ7) -> 0.33333333 | BK6: =IF(ISERROR('raw data'!DR7/'raw data'!DS7),0,'raw data'!DR7/'raw data'!DS7) -> 0 | BL6: =IF(ISERROR('raw data'!DT7/'raw data'!DU7),0,'raw data'!DT7/'raw data'!DU7) -> 0.16666667 | BM6: =IF(ISERROR('raw data'!DV7/'raw data'!DW7),0,'raw data'!DV7/'raw data'!DW7) -> 0 | BN6: =IF(ISERROR('raw data'!DX7/'raw data'!DY7),0,'raw data'!DX7/'raw data'!DY7) -> 0 | BO6: =IF(ISERROR('raw data'!DZ7/'raw data'!EA7),0,'raw data'!DZ7/'raw data'!EA7) -> 0 | BP6: =IF(ISERROR('raw data'!EB7/'raw data'!EC7),0,'raw data'!EB7/'raw data'!EC7) -> 0.16666667 | BQ6: =IF(ISERROR('raw data'!ED7/'raw data'!EE7),0,'raw data'!ED7/'raw data'!EE7) -> 0.2 | BR6: =IF(ISERROR('raw data'!EF7/'raw data'!EG7),0,'raw data'!EF7/'raw data'!EG7) -> 0 | BS6: =IF(ISERROR('raw data'!EH7/'raw data'!EI7),0,'raw data'!EH7/'raw data'!EI7) -> 0 | BT6: =IF(ISERROR('raw data'!EJ7/'raw data'!EK7),0,'raw data'!EJ7/'raw data'!EK7) -> 0.125 | BU6: =IF(ISERROR('raw data'!EL7/'raw data'!EM7),0,'raw data'!EL7/'raw data'!EM7) -> 0.33333333 | BV6: =IF(ISERROR('raw data'!EN7/'raw data'!EO7),0,'raw data'!EN7/'raw data'!EO7) -> 0 | BW6: =IF(ISERROR('raw data'!EP7/'raw data'!EQ7),0,'raw data'!EP7/'raw data'!EQ7) -> 0 | BX6: =IF(ISERROR('raw data'!ER7/'raw data'!ES7),0,'raw data'!ER7/'raw data'!ES7) -> 0 | BY6: =IF(ISERROR('raw data'!ET7/'raw data'!EU7),0,'raw data'!ET7/'raw data'!EU7) -> 0.25 | BZ6: Decomissioned | CA6: Decomissioned | CB6: Decomissioned | CC6: Decomissioned | CD6: Decomissioned | CE6: Decomissioned | CF6: Decomissioned | CG6: Decomissioned | CH6: Decomissioned | CI6: Decomissioned | CJ6: Decomissioned | CK6: Decomissioned | CL6: Decomissioned | CM6: Decomissioned | CN6: Decomissioned | CO6: Decomissioned | CP6: Decomissioned | CQ6: Decomissioned | CR6: Decomissioned | CS6: Decomissioned | CT6: Decomissioned | CU6: Decomissioned | CV6: Decomissioned | CW6: Decomissioned | CX6: Decomissioned | CY6: Decomissioned | CZ6: Decomissioned | DA6: Decomissioned | DB6: Decomissioned | DC6: Decomissioned | DD6: Decomissioned | DE6: Decomissioned | DF6: Decomissioned | DG6: Decomissioned | DH6: Decomissioned | DI6: Decomissioned | DJ6: Decomissioned | DK6: Decomissioned | DL6: Decomissioned | DM6: Decomissioned | DN6: Decomissioned | DO6: Decomissioned | DP6: Decomissioned | DQ6: Decomissioned | DR6: Decomissioned | DS6: Decomissioned | DT6: Decomissioned | DU6: Decomissioned | DV6: Decomissioned | DW6: Decomissioned | DX6: Decomissioned | DY6: Decomissioned | DZ6: Decomissioned | EA6: Decomissioned | EB6: Decomissioned | EC6: Decomissioned | EE6: 0 | EF6: 0 | EG6: =IF(ISERROR(EE6/EF6),0,EE6/EF6) -> 0
A7: 1.6 | B7: ='raw data'!B8 -> Fixed term Bonds/ISAs closed within 6 months of opening, but after cooling-off period, and Nationwide cheque issued. | C7: Bonds closed within 6 months/ Nationwide cheque issued | D7: =+'raw data'!D8/'raw data'!E8 -> 0 | E7: =+'raw data'!F8/'raw data'!G8 -> 0 | F7: =+'raw data'!H8/'raw data'!I8 -> 0 | G7: ='raw data'!J8/'raw data'!K8 -> 0 | H7: ='raw data'!L8/'raw data'!M8 -> 0.071428571 | I7: ='raw data'!N8/'raw data'!O8 -> 0 | J7: ='raw data'!P8/'raw data'!Q8 -> 0 | K7: ='raw data'!R8/'raw data'!S8 -> 0 | L7: ='raw data'!T8/'raw data'!U8 -> 0 | M7: ='raw data'!V8/'raw data'!W8 -> 0 | N7: ='raw data'!X8/'raw data'!Y8 -> 0 | O7: =IF(ISERROR('raw data'!Z8/'raw data'!AA8),0,'raw data'!Z8/'raw data'!AA8) -> 0 | P7: =IF(ISERROR('raw data'!AB8/'raw data'!AC8),0,'raw data'!AB8/'raw data'!AC8) -> 0 | Q7: =IF(ISERROR('raw data'!AD8/'raw data'!AE8),0,'raw data'!AD8/'raw data'!AE8) -> 0 | R7: =IF(ISERROR('raw data'!AF8/'raw data'!AG8),0,'raw data'!AF8/'raw data'!AG8) -> 0 | S7: =IF(ISERROR('raw data'!AH8/'raw data'!AI8),0,'raw data'!AH8/'raw data'!AI8) -> 0 | T7: =IF(ISERROR('raw data'!AJ8/'raw data'!AK8),0,'raw data'!AJ8/'raw data'!AK8) -> 0 | U7: =IF(ISERROR('raw data'!AL8/'raw data'!AM8),0,'raw data'!AL8/'raw data'!AM8) -> 0 | V7: =IF(ISERROR('raw data'!AN8/'raw data'!AO8),0,'raw data'!AN8/'raw data'!AO8) -> 0 | W7: =IF(ISERROR('raw data'!AP8/'raw data'!AQ8),0,'raw data'!AP8/'raw data'!AQ8) -> 0 | X7: =IF(ISERROR('raw data'!AR8/'raw data'!AS8),0,'raw data'!AR8/'raw data'!AS8) -> 0 | Y7: =IF(ISERROR('raw data'!AT8/'raw data'!AU8),0,'raw data'!AT8/'raw data'!AU8) -> 0 | Z7: =IF(ISERROR('raw data'!AV8/'raw data'!AW8),0,'raw data'!AV8/'raw data'!AW8) -> 0 | AA7: =IF(ISERROR('raw data'!AX8/'raw data'!AY8),0,'raw data'!AX8/'raw data'!AY8) -> 0 | AB7: =IF(ISERROR('raw data'!AZ8/'raw data'!BA8),0,'raw data'!AZ8/'raw data'!BA8) -> 0 | AC7: =IF(ISERROR('raw data'!BB8/'raw data'!BC8),0,'raw data'!BB8/'raw data'!BC8) -> 0 | AD7: =IF(ISERROR('raw data'!BD8/'raw data'!BE8),0,'raw data'!BD8/'raw data'!BE8) -> 0 | AE7: =IF(ISERROR('raw data'!BF8/'raw data'!BG8),0,'raw data'!BF8/'raw data'!BG8) -> 0 | AF7: =IF(ISERROR('raw data'!BH8/'raw data'!BI8),0,'raw data'!BH8/'raw data'!BI8) -> 0 | AG7: =IF(ISERROR('raw data'!BJ8/'raw data'!BK8),0,'raw data'!BJ8/'raw data'!BK8) -> 0 | AH7: =IF(ISERROR('raw data'!BL8/'raw data'!BM8),0,'raw data'!BL8/'raw data'!BM8) -> 0 | AI7: =IF(ISERROR('raw data'!BN8/'raw data'!BO8),0,'raw data'!BN8/'raw data'!BO8) -> 0 | AJ7: =IF(ISERROR('raw data'!BP8/'raw data'!BQ8),0,'raw data'!BP8/'raw data'!BQ8) -> 0 | AK7: =IF(ISERROR('raw data'!BR8/'raw data'!BS8),0,'raw data'!BR8/'raw data'!BS8) -> 0 | AL7: =IF(ISERROR('raw data'!BT8/'raw data'!BU8),0,'raw data'!BT8/'raw data'!BU8) -> 0 | AM7: =IF(ISERROR('raw data'!BV8/'raw data'!BW8),0,'raw data'!BV8/'raw data'!BW8) -> 0 | AN7: =IF(ISERROR('raw data'!BX8/'raw data'!BY8),0,'raw data'!BX8/'raw data'!BY8) -> 0 | AO7: =IF(ISERROR('raw data'!BZ8/'raw data'!CA8),0,'raw data'!BZ8/'raw data'!CA8) -> 0 | AP7: =IF(ISERROR('raw data'!CB8/'raw data'!CC8),0,'raw data'!CB8/'raw data'!CC8) -> 0 | AQ7: =IF(ISERROR('raw data'!CD8/'raw data'!CE8),0,'raw data'!CD8/'raw data'!CE8) -> 0.0097087379 | AR7: =IF(ISERROR('raw data'!CF8/'raw data'!CG8),0,'raw data'!CF8/'raw data'!CG8) -> 0 | AS7: =IF(ISERROR('raw data'!CH8/'raw data'!CI8),0,'raw data'!CH8/'raw data'!CI8) -> 0.022988506 | AT7: =IF(ISERROR('raw data'!CJ8/'raw data'!CK8),0,'raw data'!CJ8/'raw data'!CK8) -> 0.01010101 | AU7: =IF(ISERROR('raw data'!CL8/'raw data'!CM8),0,'raw data'!CL8/'raw data'!CM8) -> 0 | AV7: =IF(ISERROR('raw data'!CN8/'raw data'!CO8),0,'raw data'!CN8/'raw data'!CO8) -> 0.013793103 | AW7: =IF(ISERROR('raw data'!CP8/'raw data'!CQ8),0,'raw data'!CP8/'raw data'!CQ8) -> 0.0061728395 | AX7: =IF(ISERROR('raw data'!CR8/'raw data'!CS8),0,'raw data'!CR8/'raw data'!CS8) -> 0 | AY7: =IF(ISERROR('raw data'!CT8/'raw data'!CU8),0,'raw data'!CT8/'raw data'!CU8) -> 0.0073529412 | AZ7: =IF(ISERROR('raw data'!CV8/'raw data'!CW8),0,'raw data'!CV8/'raw data'!CW8) -> 0.008 | BA7: =IF(ISERROR('raw data'!CX8/'raw data'!CY8),0,'raw data'!CX8/'raw data'!CY8) -> 0.015625 | BB7: =IF(ISERROR('raw data'!CZ8/'raw data'!DA8),0,'raw data'!CZ8/'raw data'!DA8) -> 0.0042918455 | BC7: =IF(ISERROR('raw data'!DB8/'raw data'!DC8),0,'raw data'!DB8/'raw data'!DC8) -> 0 | BD7: 0 | BE7: Decomissioned | BF7: Decomissioned | BG7: Decomissioned | BH7: Decomissioned | BI7: Decomissioned | BJ7: Decomissioned | BK7: Decomissioned | BL7: Decomissioned | BM7: Decomissioned | BN7: Decomissioned | BO7: Decomissioned | BP7: Decomissioned | BQ7: Decomissioned | BR7: Decomissioned | BS7: Decomissioned | BT7: Decomissioned | BU7: Decomissioned | BV7: Decomissioned | BW7: Decomissioned | BX7: Decomissioned | BY7: Decomissioned | BZ7: Decomissioned | CA7: Decomissioned | CB7: Decomissioned | CC7: Decomissioned | CD7: Decomissioned | CE7: Decomissioned | CF7: Decomissioned | CG7: Decomissioned | CH7: Decomissioned | CI7: Decomissioned | CJ7: Decomissioned | CK7: Decomissioned | CL7: Decomissioned | CM7: Decomissioned | CN7: Decomissioned | CO7: Decomissioned | CP7: Decomissioned | CQ7: Decomissioned | CR7: Decomissioned | CS7: Decomissioned | CT7: Decomissioned | CU7: Decomissioned | CV7: Decomissioned | CW7: Decomissioned | CX7: Decomissioned | CY7: Decomissioned | CZ7: Decomissioned | DA7: Decomissioned | DB7: Decomissioned | DC7: Decomissioned | DD7: Decomissioned | DE7: Decomissioned | DF7: Decomissioned | DG7: Decomissioned | DH7: Decomissioned | DI7: Decomissioned | DJ7: Decomissioned | DK7: Decomissioned | DL7: Decomissioned | DM7: Decomissioned | DN7: Decomissioned | DO7: Decomissioned | DP7: Decomissioned | DQ7: Decomissioned | DR7: Decomissioned | DS7: Decomissioned | DT7: Decomissioned | DU7: Decomissioned | DV7: Decomissioned | DW7: Decomissioned | DX7: Decomissioned | DY7: Decomissioned | DZ7: Decomissioned | EA7: Decomissioned | EB7: Decomissioned | EC7: Decomissioned | EE7: 0 | EF7: 0 | EG7: =IF(ISERROR(EE7/EF7),0,EE7/EF7) -> 0
A8: 1.7 | B8: ='raw data'!B9 -> Child accounts with >1 credit (CR, CQ) and at least 1 debit (WA, WD, TW, W4), each £1k+, totalling at least £2k in & £2.5k out last month. | C8: Child accounts with more than £1K in and out in a month | D8: =+'raw data'!D9/'raw data'!E9 -> 0.31707317 | E8: =+'raw data'!F9/'raw data'!G9 -> 0.13333333 | F8: =+'raw data'!H9/'raw data'!I9 -> 0.21428571 | G8: ='raw data'!J9/'raw data'!K9 -> 0.17777778 | H8: ='raw data'!L9/'raw data'!M9 -> 0.23529412 | I8: ='raw data'!N9/'raw data'!O9 -> 0.2 | J8: ='raw data'!P9/'raw data'!Q9 -> 0.4 | K8: ='raw data'!R9/'raw data'!S9 -> 0.275 | L8: ='raw data'!T9/'raw data'!U9 -> 0.10714286 | M8: ='raw data'!V9/'raw data'!W9 -> 0.24 | N8: ='raw data'!X9/'raw data'!Y9 -> 0.043478261 | O8: =IF(ISERROR('raw data'!Z9/'raw data'!AA9),0,'raw data'!Z9/'raw data'!AA9) -> 0.028571429 | P8: =IF(ISERROR('raw data'!AB9/'raw data'!AC9),0,'raw data'!AB9/'raw data'!AC9) -> 0.25925926 | Q8: =IF(ISERROR('raw data'!AD9/'raw data'!AE9),0,'raw data'!AD9/'raw data'!AE9) -> 0.071428571 | R8: =IF(ISERROR('raw data'!AF9/'raw data'!AG9),0,'raw data'!AF9/'raw data'!AG9) -> 0.19230769 | S8: =IF(ISERROR('raw data'!AH9/'raw data'!AI9),0,'raw data'!AH9/'raw data'!AI9) -> 0.20930233 | T8: =IF(ISERROR('raw data'!AJ9/'raw data'!AK9),0,'raw data'!AJ9/'raw data'!AK9) -> 0.16 | U8: =IF(ISERROR('raw data'!AL9/'raw data'!AM9),0,'raw data'!AL9/'raw data'!AM9) -> 0.11111111 | V8: =IF(ISERROR('raw data'!AN9/'raw data'!AO9),0,'raw data'!AN9/'raw data'!AO9) -> 0.17391304 | W8: =IF(ISERROR('raw data'!AP9/'raw data'!AQ9),0,'raw data'!AP9/'raw data'!AQ9) -> 0.073170732 | X8: =IF(ISERROR('raw data'!AR9/'raw data'!AS9),0,'raw data'!AR9/'raw data'!AS9) -> 0.23333333 | Y8: =IF(ISERROR('raw data'!AT9/'raw data'!AU9),0,'raw data'!AT9/'raw data'!AU9) -> 0.16 | Z8: =IF(ISERROR('raw data'!AV9/'raw data'!AW9),0,'raw data'!AV9/'raw data'!AW9) -> 0.15 | AA8: =IF(ISERROR('raw data'!AX9/'raw data'!AY9),0,'raw data'!AX9/'raw data'!AY9) -> 0.22222222 | AB8: =IF(ISERROR('raw data'!AZ9/'raw data'!BA9),0,'raw data'!AZ9/'raw data'!BA9) -> 0.18181818 | AC8: =IF(ISERROR('raw data'!BB9/'raw data'!BC9),0,'raw data'!BB9/'raw data'!BC9) -> 0.27027027 | AD8: =IF(ISERROR('raw data'!BD9/'raw data'!BE9),0,'raw data'!BD9/'raw data'!BE9) -> 0.33333333 | AE8: =IF(ISERROR('raw data'!BF9/'raw data'!BG9),0,'raw data'!BF9/'raw data'!BG9) -> 0.33333333 | AF8: =IF(ISERROR('raw data'!BH9/'raw data'!BI9),0,'raw data'!BH9/'raw data'!BI9) -> 0.039215686 | AG8: =IF(ISERROR('raw data'!BJ9/'raw data'!BK9),0,'raw data'!BJ9/'raw data'!BK9) -> 0.41666667 | AH8: =IF(ISERROR('raw data'!BL9/'raw data'!BM9),0,'raw data'!BL9/'raw data'!BM9) -> 0.11111111 | AI8: =IF(ISERROR('raw data'!BN9/'raw data'!BO9),0,'raw data'!BN9/'raw data'!BO9) -> 0.090909091 | AJ8: =IF(ISERROR('raw data'!BP9/'raw data'!BQ9),0,'raw data'!BP9/'raw data'!BQ9) -> 0.24137931 | AK8: =IF(ISERROR('raw data'!BR9/'raw data'!BS9),0,'raw data'!BR9/'raw data'!BS9) -> 0.20833333 | AL8: =IF(ISERROR('raw data'!BT9/'raw data'!BU9),0,'raw data'!BT9/'raw data'!BU9) -> 0.12903226 | AM8: =IF(ISERROR('raw data'!BV9/'raw data'!BW9),0,'raw data'!BV9/'raw data'!BW9) -> 0.4137931 | AN8: =IF(ISERROR('raw data'!BX9/'raw data'!BY9),0,'raw data'!BX9/'raw data'!BY9) -> 0.53333333 | AO8: =IF(ISERROR('raw data'!BZ9/'raw data'!CA9),0,'raw data'!BZ9/'raw data'!CA9) -> 0.48148148 | AP8: =IF(ISERROR('raw data'!CB9/'raw data'!CC9),0,'raw data'!CB9/'raw data'!CC9) -> 0.44444444 | AQ8: =IF(ISERROR('raw data'!CD9/'raw data'!CE9),0,'raw data'!CD9/'raw data'!CE9) -> 0.086956522 | AR8: =IF(ISERROR('raw data'!CF9/'raw data'!CG9),0,'raw data'!CF9/'raw data'!CG9) -> 0.16666667 | AS8: =IF(ISERROR('raw data'!CH9/'raw data'!CI9),0,'raw data'!CH9/'raw data'!CI9) -> 0.29032258 | AT8: =IF(ISERROR('raw data'!CJ9/'raw data'!CK9),0,'raw data'!CJ9/'raw data'!CK9) -> 0.36363636 | AU8: =IF(ISERROR('raw data'!CL9/'raw data'!CM9),0,'raw data'!CL9/'raw data'!CM9) -> 0.23809524 | AV8: =IF(ISERROR('raw data'!CN9/'raw data'!CO9),0,'raw data'!CN9/'raw data'!CO9) -> 0.16666667 | AW8: =IF(ISERROR('raw data'!CP9/'raw data'!CQ9),0,'raw data'!CP9/'raw data'!CQ9) -> 0.22222222 | AX8: =IF(ISERROR('raw data'!CR9/'raw data'!CS9),0,'raw data'!CR9/'raw data'!CS9) -> 0.17647059 | AY8: =IF(ISERROR('raw data'!CT9/'raw data'!CU9),0,'raw data'!CT9/'raw data'!CU9) -> 0.33333333 | AZ8: =IF(ISERROR('raw data'!CV9/'raw data'!CW9),0,'raw data'!CV9/'raw data'!CW9) -> 0.26315789 | BA8: =IF(ISERROR('raw data'!CX9/'raw data'!CY9),0,'raw data'!CX9/'raw data'!CY9) -> 0.13333333 | BB8: =IF(ISERROR('raw data'!CZ9/'raw data'!DA9),0,'raw data'!CZ9/'raw data'!DA9) -> 0.375 | BC8: =IF(ISERROR('raw data'!DB9/'raw data'!DC9),0,'raw data'!DB9/'raw data'!DC9) -> 0.1 | BD8: 0.27272727 | BE8: =IF(ISERROR('raw data'!DF9/'raw data'!DG9),0,'raw data'!DF9/'raw data'!DG9) -> 0.33333333 | BF8: =IF(ISERROR('raw data'!DH9/'raw data'!DI9),0,'raw data'!DH9/'raw data'!DI9) -> 0.5 | BG8: =IF(ISERROR('raw data'!DJ9/'raw data'!DK9),0,'raw data'!DJ9/'raw data'!DK9) -> 0 | BH8: =IF(ISERROR('raw data'!DL9/'raw data'!DM9),0,'raw data'!DL9/'raw data'!DM9) -> 0.38095238 | BI8: =IF(ISERROR('raw data'!DN9/'raw data'!DO9),0,'raw data'!DN9/'raw data'!DO9) -> 0.2173913 | BJ8: =IF(ISERROR('raw data'!DP9/'raw data'!DQ9),0,'raw data'!DP9/'raw data'!DQ9) -> 0.30769231 | BK8: =IF(ISERROR('raw data'!DR9/'raw data'!DS9),0,'raw data'!DR9/'raw data'!DS9) -> 0.35294118 | BL8: =IF(ISERROR('raw data'!DT9/'raw data'!DU9),0,'raw data'!DT9/'raw data'!DU9) -> 0.33333333 | BM8: =IF(ISERROR('raw data'!DV9/'raw data'!DW9),0,'raw data'!DV9/'raw data'!DW9) -> 0.25 | BN8: =IF(ISERROR('raw data'!DX9/'raw data'!DY9),0,'raw data'!DX9/'raw data'!DY9) -> 0.21428571 | BO8: =IF(ISERROR('raw data'!DZ9/'raw data'!EA9),0,'raw data'!DZ9/'raw data'!EA9) -> 0.16666667 | BP8: =IF(ISERROR('raw data'!EB9/'raw data'!EC9),0,'raw data'!EB9/'raw data'!EC9) -> 0.04 | BQ8: =IF(ISERROR('raw data'!ED9/'raw data'!EE9),0,'raw data'!ED9/'raw data'!EE9) -> 0 | BR8: =IF(ISERROR('raw data'!EF9/'raw data'!EG9),0,'raw data'!EF9/'raw data'!EG9) -> 0.0625 | BS8: =IF(ISERROR('raw data'!EH9/'raw data'!EI9),0,'raw data'!EH9/'raw data'!EI9) -> 0.11764706 | BT8: =IF(ISERROR('raw data'!EJ9/'raw data'!EK9),0,'raw data'!EJ9/'raw data'!EK9) -> 0.14285714 | BU8: =IF(ISERROR('raw data'!EL9/'raw data'!EM9),0,'raw data'!EL9/'raw data'!EM9) -> 0 | BV8: =IF(ISERROR('raw data'!EN9/'raw data'!EO9),0,'raw data'!EN9/'raw data'!EO9) -> 0 | BW8: =IF(ISERROR('raw data'!EP9/'raw data'!EQ9),0,'raw data'!EP9/'raw data'!EQ9) -> 0 | BX8: =IF(ISERROR('raw data'!ER9/'raw data'!ES9),0,'raw data'!ER9/'raw data'!ES9) -> 0.23076923 | BY8: =IF(ISERROR('raw data'!ET9/'raw data'!EU9),0,'raw data'!ET9/'raw data'!EU9) -> 0.3125 | BZ8: =IF(ISERROR('raw data'!EV9/'raw data'!EW9),0,'raw data'!EV9/'raw data'!EW9) -> 0 | CA8: =IF(ISERROR('raw data'!EX9/'raw data'!EY9),0,'raw data'!EX9/'raw data'!EY9) -> 0.21428571 | CB8: =IF(ISERROR('raw data'!EZ9/'raw data'!FA9),0,'raw data'!EZ9/'raw data'!FA9) -> 0.076923077 | CC8: =IF(ISERROR('raw data'!FB9/'raw data'!FC9),0,'raw data'!FB9/'raw data'!FC9) -> 0.33333333 | CD8: =IF(ISERROR('raw data'!FD9/'raw data'!FE9),0,'raw data'!FD9/'raw data'!FE9) -> 0.2 | CE8: =IF(ISERROR('raw data'!FF9/'raw data'!FG9),0,'raw data'!FF9/'raw data'!FG9) -> 0.33333333 | CF8: =IF(ISERROR('raw data'!FH9/'raw data'!FI9),0,'raw data'!FH9/'raw data'!FI9) -> 0.05 | CG8: =IF(ISERROR('raw data'!FJ9/'raw data'!FM9),0,'raw data'!FJ9/'raw data'!FM9) -> 0.2 | CH8: =IF(ISERROR('raw data'!FN9/'raw data'!FO9),0,'raw data'!FN9/'raw data'!FO9) -> 0.23076923 | CI8: =IF(ISERROR('raw data'!FP9/'raw data'!FQ9),0,'raw data'!FP9/'raw data'!FQ9) -> 0.44444444 | CJ8: =IF(ISERROR('raw data'!FR9/'raw data'!FS9),0,'raw data'!FR9/'raw data'!FS9) -> 0.22222222 | CK8: =IF(ISERROR('raw data'!FT9/'raw data'!FU9),0,'raw data'!FT9/'raw data'!FU9) -> 0.31578947 | CL8: =IF(ISERROR('raw data'!FV9/'raw data'!FW9),0,'raw data'!FV9/'raw data'!FW9) -> 0.1 | CM8: =IF(ISERROR('raw data'!FX9/'raw data'!FY9),0,'raw data'!FX9/'raw data'!FY9) -> 0.2 | CN8: =IF(ISERROR('raw data'!FZ9/'raw data'!GA9),0,'raw data'!FZ9/'raw data'!GA9) -> 0 | CO8: =IF(ISERROR('raw data'!GB9/'raw data'!GC9),0,'raw data'!GB9/'raw data'!GC9) -> 0 | CP8: =IF(ISERROR('raw data'!GD9/'raw data'!GE9),0,'raw data'!GD9/'raw data'!GE9) -> 0.2 | CQ8: =IF(ISERROR('raw data'!GF9/'raw data'!GG9),0,'raw data'!GF9/'raw data'!GG9) -> 0 | CR8: =IF(ISERROR('raw data'!GH9/'raw data'!GI9),0,'raw data'!GH9/'raw data'!GI9) -> 0.1 | CS8: =IF(ISERROR('raw data'!GJ9/'raw data'!GK9),0,'raw data'!GJ9/'raw data'!GK9) -> 0 | CT8: =IF(ISERROR('raw data'!GL9/'raw data'!GM9),0,'raw data'!GL9/'raw data'!GM9) -> 0.1875 | CU8: =IF(ISERROR('raw data'!GN9/'raw data'!GO9),0,'raw data'!GN9/'raw data'!GO9) -> 0 | CV8: =IF(ISERROR('raw data'!GP9/'raw data'!GQ9),0,'raw data'!GP9/'raw data'!GQ9) -> 0.25 | CW8: =IF(ISERROR('raw data'!GR9/'raw data'!GS9),0,'raw data'!GR9/'raw data'!GS9) -> 0.18181818 | CX8: =IF(ISERROR('raw data'!GT9/'raw data'!GU9),0,'raw data'!GT9/'raw data'!GU9) -> 0.11111111 | CY8: =IF(ISERROR('raw data'!GV9/'raw data'!GW9),0,'raw data'!GV9/'raw data'!GW9) -> 0 | CZ8: =IF(ISERROR('raw data'!GX9/'raw data'!GY9),0,'raw data'!GX9/'raw data'!GY9) -> 0.058823529 | DA8: =IF(ISERROR('raw data'!GZ9/'raw data'!HA9),0,'raw data'!GZ9/'raw data'!HA9) -> 0 | DB8: =IF(ISERROR('raw data'!HB9/'raw data'!HC9),0,'raw data'!HB9/'raw data'!HC9) -> 0.33333333 | DC8: =IF(ISERROR('raw data'!HD9/'raw data'!HE9),0,'raw data'!HD9/'raw data'!HE9) -> 0.071428571 | DD8: =IF(ISERROR('raw data'!HF9/'raw data'!HG9),0,'raw data'!HF9/'raw data'!HG9) -> 0.125 | DE8: =IF(ISERROR('raw data'!HH9/'raw data'!HI9),0,'raw data'!HH9/'raw data'!HI9) -> 0.375 | DF8: =IF(ISERROR('raw data'!HJ9/'raw data'!HK9),0,'raw data'!HJ9/'raw data'!HK9) -> 0.33333333 | DG8: =IF(ISERROR('raw data'!HL9/'raw data'!HM9),0,'raw data'!HL9/'raw data'!HM9) -> 0 | DH8: =IF(ISERROR('raw data'!HN9/'raw data'!HO9),0,'raw data'!HN9/'raw data'!HO9) -> 0 | DI8: =IF(ISERROR('raw data'!HP9/'raw data'!HQ9),0,'raw data'!HP9/'raw data'!HQ9) -> 0 | DJ8: =IF(ISERROR('raw data'!HR9/'raw data'!HS9),0,'raw data'!HR9/'raw data'!HS9) -> 0.33333333 | DK8: =IF(ISERROR('raw data'!HT9/'raw data'!HU9),0,'raw data'!HT9/'raw data'!HU9) -> 0 | DL8: =IF(ISERROR('raw data'!HV9/'raw data'!HW9),0,'raw data'!HV9/'raw data'!HW9) -> 0 | DM8: =IF(ISERROR('raw data'!HX9/'raw data'!HY9),0,'raw data'!HX9/'raw data'!HY9) -> 0 | DN8: =IF(ISERROR('raw data'!HZ9/'raw data'!IA9),0,'raw data'!HZ9/'raw data'!IA9) -> 0 | DO8: =IF(ISERROR('raw data'!IB9/'raw data'!IC9),0,'raw data'!IB9/'raw data'!IC9) -> 0.25 | DP8: =IF(ISERROR('raw data'!ID9/'raw data'!IE9),0,'raw data'!ID9/'raw data'!IE9) -> 0 | DQ8: =IF(ISERROR('raw data'!IF9/'raw data'!IG9),0,'raw data'!IF9/'raw data'!IG9) -> 0.3 | DR8: =IF(ISERROR('raw data'!IH9/'raw data'!II9),0,'raw data'!IH9/'raw data'!II9) -> 0.25 | DS8: =IF(ISERROR('raw data'!IJ9/'raw data'!IK9),0,'raw data'!IJ9/'raw data'!IK9) -> 0.33333333 | DT8: =IF(ISERROR('raw data'!IL9/'raw data'!IM9),0,'raw data'!IL9/'raw data'!IM9) -> 0.14285714 | DU8: =IF(ISERROR('raw data'!IN9/'raw data'!IO9),0,'raw data'!IN9/'raw data'!IO9) -> 1 | DV8: =IF(ISERROR('raw data'!IP9/'raw data'!IQ9),0,'raw data'!IP9/'raw data'!IQ9) -> 0 | DW8: =IF(ISERROR('raw data'!IR9/'raw data'!IS9),0,'raw data'!IR9/'raw data'!IS9) -> 0.25 | DX8: =IF(ISERROR('raw data'!IT9/'raw data'!IU9),0,'raw data'!IT9/'raw data'!IU9) -> 0.625 | DY8: =IF(ISERROR('raw data'!IV9/'raw data'!IW9),0,'raw data'!IV9/'raw data'!IW9) -> 0.2 | DZ8: =IF(ISERROR('raw data'!IX9/'raw data'!IY9),0,'raw data'!IX9/'raw data'!IY9) -> 0 | EA8: =IF(ISERROR('raw data'!IZ9/'raw data'!JA9),0,'raw data'!IZ9/'raw data'!JA9) -> 0.5 | EB8: =IF(ISERROR('raw data'!JB9/'raw data'!JC9),0,'raw data'!JB9/'raw data'!JC9) -> 0 | EC8: =IF(ISERROR('raw data'!JD9/'raw data'!JE9),0,'raw data'!JD9/'raw data'!JE9) -> 0.375 | EE8: 19 | EF8: 63 | EG8: =IF(ISERROR(EE8/EF8),0,EE8/EF8) -> 0.3015873
A9: 1.11 | B9: ='raw data'!B10 -> Flex accounts of Eastern Europeans, possibly benefits paid (Child Benefit, JSA etc) and may live abroad (2 or more VW in last 3 months). | C9: Flex Accounts of Eastern Europeans, possibly benefits paid (Child Benefit, JSA etc) and may live abroad | J9: ='raw data'!P10/'raw data'!Q10 -> 0.10294118 | L9: ='raw data'!T10/'raw data'!U10 -> 0.18181818 | M9: ='raw data'!V10/'raw data'!W10 -> 0.3 | N9: ='raw data'!X10/'raw data'!Y10 -> 0.30769231 | O9: =IF(ISERROR('raw data'!Z10/'raw data'!AA10),0,'raw data'!Z10/'raw data'!AA10) -> 0.16666667 | P9: =IF(ISERROR('raw data'!AB10/'raw data'!AC10),0,'raw data'!AB10/'raw data'!AC10) -> 0 | Q9: =IF(ISERROR('raw data'!AD10/'raw data'!AE10),0,'raw data'!AD10/'raw data'!AE10) -> 0 | R9: =IF(ISERROR('raw data'!AF10/'raw data'!AG10),0,'raw data'!AF10/'raw data'!AG10) -> 0 | S9: =IF(ISERROR('raw data'!AH10/'raw data'!AI10),0,'raw data'!AH10/'raw data'!AI10) -> 0.125 | T9: =IF(ISERROR('raw data'!AJ10/'raw data'!AK10),0,'raw data'!AJ10/'raw data'!AK10) -> 0.33333333 | U9: =IF(ISERROR('raw data'!AL10/'raw data'!AM10),0,'raw data'!AL10/'raw data'!AM10) -> 0 | V9: =IF(ISERROR('raw data'!AN10/'raw data'!AO10),0,'raw data'!AN10/'raw data'!AO10) -> 0.45454545 | W9: =IF(ISERROR('raw data'!AP10/'raw data'!AQ10),0,'raw data'!AP10/'raw data'!AQ10) -> 0.25 | X9: =IF(ISERROR('raw data'!AR10/'raw data'!AS10),0,'raw data'!AR10/'raw data'!AS10) -> 0 | Y9: =IF(ISERROR('raw data'!AT10/'raw data'!AU10),0,'raw data'!AT10/'raw data'!AU10) -> 0.33333333 | Z9: =IF(ISERROR('raw data'!AV10/'raw data'!AW10),0,'raw data'!AV10/'raw data'!AW10) -> 0.4 | AA9: =IF(ISERROR('raw data'!AX10/'raw data'!AY10),0,'raw data'!AX10/'raw data'!AY10) -> 0.5 | AB9: =IF(ISERROR('raw data'!AZ10/'raw data'!BA10),0,'raw data'!AZ10/'raw data'!BA10) -> 0 | AC9: =IF(ISERROR('raw data'!BB10/'raw data'!BC10),0,'raw data'!BB10/'raw data'!BC10) -> 0 | AD9: =IF(ISERROR('raw data'!BD10/'raw data'!BE10),0,'raw data'!BD10/'raw data'!BE10) -> 0 | AE9: =IF(ISERROR('raw data'!BF10/'raw data'!BG10),0,'raw data'!BF10/'raw data'!BG10) -> 0.66666667 | AF9: =IF(ISERROR('raw data'!BH10/'raw data'!BI10),0,'raw data'!BH10/'raw data'!BI10) -> 0 | AG9: =IF(ISERROR('raw data'!BJ10/'raw data'!BK10),0,'raw data'!BJ10/'raw data'!BK10) -> 1 | AH9: =IF(ISERROR('raw data'!BL10/'raw data'!BM10),0,'raw data'!BL10/'raw data'!BM10) -> 0.5 | AI9: =IF(ISERROR('raw data'!BN10/'raw data'!BO10),0,'raw data'!BN10/'raw data'!BO10) -> 0 | AJ9: =IF(ISERROR('raw data'!BP10/'raw data'!BQ10),0,'raw data'!BP10/'raw data'!BQ10) -> 0.14285714 | AK9: =IF(ISERROR('raw data'!BR10/'raw data'!BS10),0,'raw data'!BR10/'raw data'!BS10) -> 0 | AL9: =IF(ISERROR('raw data'!BT10/'raw data'!BU10),0,'raw data'!BT10/'raw data'!BU10) -> 0.1875 | AM9: =IF(ISERROR('raw data'!BV10/'raw data'!BW10),0,'raw data'!BV10/'raw data'!BW10) -> 0.11111111 | AN9: =IF(ISERROR('raw data'!BX10/'raw data'!BY10),0,'raw data'!BX10/'raw data'!BY10) -> 0.26666667 | AO9: =IF(ISERROR('raw data'!BZ10/'raw data'!CA10),0,'raw data'!BZ10/'raw data'!CA10) -> 0.75 | AP9: =IF(ISERROR('raw data'!CB10/'raw data'!CC10),0,'raw data'!CB10/'raw data'!CC10) -> 0.75 | AQ9: =IF(ISERROR('raw data'!CD10/'raw data'!CE10),0,'raw data'!CD10/'raw data'!CE10) -> 0 | AR9: =IF(ISERROR('raw data'!CF10/'raw data'!CG10),0,'raw data'!CF10/'raw data'!CG10) -> 0.66666667 | AS9: =IF(ISERROR('raw data'!CH10/'raw data'!CI10),0,'raw data'!CH10/'raw data'!CI10) -> 0 | AT9: =IF(ISERROR('raw data'!CJ10/'raw data'!CK10),0,'raw data'!CJ10/'raw data'!CK10) -> 0 | AU9: =IF(ISERROR('raw data'!CL10/'raw data'!CM10),0,'raw data'!CL10/'raw data'!CM10) -> 0 | AV9: =IF(ISERROR('raw data'!CN10/'raw data'!CO10),0,'raw data'!CN10/'raw data'!CO10) -> 0.81818182 | AW9: =IF(ISERROR('raw data'!CP10/'raw data'!CQ10),0,'raw data'!CP10/'raw data'!CQ10) -> 0.45454545 | AX9: =IF(ISERROR('raw data'!CR10/'raw data'!CS10),0,'raw data'!CR10/'raw data'!CS10) -> 0.5 | AY9: =IF(ISERROR('raw data'!CT10/'raw data'!CU10),0,'raw data'!CT10/'raw data'!CU10) -> 1 | AZ9: =IF(ISERROR('raw data'!CV10/'raw data'!CW10),0,'raw data'!CV10/'raw data'!CW10) -> 0.6 | BA9: =IF(ISERROR('raw data'!CX10/'raw data'!CY10),0,'raw data'!CX10/'raw data'!CY10) -> 0.4 | BB9: =IF(ISERROR('raw data'!CZ10/'raw data'!DA10),0,'raw data'!CZ10/'raw data'!DA10) -> 0.6 | BC9: =IF(ISERROR('raw data'!DB10/'raw data'!DC10),0,'raw data'!DB10/'raw data'!DC10) -> 0.57142857 | BD9: 0 | BE9: =IF(ISERROR('raw data'!DF10/'raw data'!DG10),0,'raw data'!DF10/'raw data'!DG10) -> 0 | BF9: =IF(ISERROR('raw data'!DH10/'raw data'!DI10),0,'raw data'!DH10/'raw data'!DI10) -> 0 | BG9: =IF(ISERROR('raw data'!DJ10/'raw data'!DK10),0,'raw data'!DJ10/'raw data'!DK10) -> 0 | BH9: =IF(ISERROR('raw data'!DL10/'raw data'!DM10),0,'raw data'!DL10/'raw data'!DM10) -> 0 | BI9: =IF(ISERROR('raw data'!DN10/'raw data'!DO10),0,'raw data'!DN10/'raw data'!DO10) -> 0 | BJ9: =IF(ISERROR('raw data'!DP10/'raw data'!DQ10),0,'raw data'!DP10/'raw data'!DQ10) -> 0 | BK9: =IF(ISERROR('raw data'!DR10/'raw data'!DS10),0,'raw data'!DR10/'raw data'!DS10) -> 0.58823529 | BL9: =IF(ISERROR('raw data'!DT10/'raw data'!DU10),0,'raw data'!DT10/'raw data'!DU10) -> 0.42857143 | BM9: =IF(ISERROR('raw data'!DV10/'raw data'!DW10),0,'raw data'!DV10/'raw data'!DW10) -> 0.5 | BN9: =IF(ISERROR('raw data'!DX10/'raw data'!DY10),0,'raw data'!DX10/'raw data'!DY10) -> 0.2 | BO9: =IF(ISERROR('raw data'!DZ10/'raw data'!EA10),0,'raw data'!DZ10/'raw data'!EA10) -> 0.18181818 | BP9: =IF(ISERROR('raw data'!EB10/'raw data'!EC10),0,'raw data'!EB10/'raw data'!EC10) -> 0 | BQ9: =IF(ISERROR('raw data'!ED10/'raw data'!EE10),0,'raw data'!ED10/'raw data'!EE10) -> 0.14285714 | BR9: =IF(ISERROR('raw data'!EF10/'raw data'!EG10),0,'raw data'!EF10/'raw data'!EG10) -> 0 | BS9: =IF(ISERROR('raw data'!EH10/'raw data'!EI10),0,'raw data'!EH10/'raw data'!EI10) -> 0.066666667 | BT9: =IF(ISERROR('raw data'!EJ10/'raw data'!EK10),0,'raw data'!EJ10/'raw data'!EK10) -> 0.13043478 | BU9: =IF(ISERROR('raw data'!EL10/'raw data'!EM10),0,'raw data'!EL10/'raw data'!EM10) -> 0.090909091 | BV9: =IF(ISERROR('raw data'!EN10/'raw data'!EO10),0,'raw data'!EN10/'raw data'!EO10) -> 0.090909091 | BW9: =IF(ISERROR('raw data'!EP10/'raw data'!EQ10),0,'raw data'!EP10/'raw data'!EQ10) -> 0.14285714 | BX9: =IF(ISERROR('raw data'!ER10/'raw data'!ES10),0,'raw data'!ER10/'raw data'!ES10) -> 0.043478261 | BY9: =IF(ISERROR('raw data'!ET10/'raw data'!EU10),0,'raw data'!ET10/'raw data'!EU10) -> 0.058823529 | BZ9: Decomissioned | CA9: Decomissioned | CB9: Decomissioned | CC9: Decomissioned | CD9: Decomissioned | CE9: Decomissioned | CF9: Decomissioned | CG9: Decomissioned | CH9: Decomissioned | CI9: Decomissioned | CJ9: Decomissioned | CK9: Decomissioned | CL9: Decomissioned | CM9: Decomissioned | CN9: Decomissioned | CO9: Decomissioned | CP9: Decomissioned | CQ9: Decomissioned | CR9: Decomissioned | CS9: Decomissioned | CT9: Decomissioned | CU9: Decomissioned | CV9: Decomissioned | CW9: Decomissioned | CX9: Decomissioned | CY9: Decomissioned | CZ9: Decomissioned | DA9: Decomissioned | DB9: Decomissioned | DC9: Decomissioned | DD9: Decomissioned | DE9: Decomissioned | DF9: Decomissioned | DG9: Decomissioned | DH9: Decomissioned | DI9: Decomissioned | DJ9: Decomissioned | DK9: Decomissioned | DL9: Decomissioned | DM9: Decomissioned | DN9: Decomissioned | DO9: Decomissioned | DP9: Decomissioned | DQ9: Decomissioned | DR9: Decomissioned | DS9: Decomissioned | DT9: Decomissioned | DU9: Decomissioned | DV9: Decomissioned | DW9: Decomissioned | DX9: Decomissioned | DY9: Decomissioned | DZ9: Decomissioned | EA9: Decomissioned | EB9: Decomissioned | EC9: Decomissioned | EE9: 0 | EF9: 0 | EG9: =IF(ISERROR(EE9/EF9),0,EE9/EF9) -> 0
